Workbook

Sheet Metrica
A1: EMPRESA | B1: TERCERO | C1: N° PRODUCTO | D1: FECHA MAX PARA PAGAR | E1: CUOTA IN | F1: CUOTA FIN | G1: SALDO CAPITAL ANTERIOR | H1: SALDO CAPITAL | I1: CUOTA CAPITAL | J1: INTERES | K1: MORA | L1: TOTAL A PAGAR | M1: DIAS VENCIDO | N1: VALOR PAGADO | O1: FECHA DE PAGO | P1: ESTADO
A2: LAMAR OPTICAL S.A.S | B2: BANCO DE BOGOTÁ | C2: 00656006174 | D2: {=IFERROR(INDEX(DATA!$E$2:$E$1036, MATCH(CONCATENATE(YEAR(TODAY()), MONTH(TODAY()), Metrica!$C2), CONCATENATE(DATA!$A$2:$A$1036, DATA!$D$2:$D$1036), 0)), "")} -> 45559 | E2: {=IFERROR(INDEX(DATA!$F$2:$F$1036, MATCH(CONCATENATE(YEAR(TODAY()), MONTH(TODAY()), Metrica!$C2), CONCATENATE(DATA!$A$2:$A$1036, DATA!$D$2:$D$1036), 0)), "")} -> 35 | F2: {=IFERROR(INDEX(DATA!$G$2:$G$1036, MATCH(CONCATENATE(YEAR(TODAY()), MONTH(TODAY()), Metrica!$C2), CONCATENATE(DATA!$A$2:$A$1036, DATA!$D$2:$D$1036), 0)), "")} -> 0 | G2: {=IFERROR(INDEX(DATA!$Q$2:$Q$1036, MATCH(CONCATENATE(YEAR(TODAY()), MONTH(TODAY()-31), Metrica!$C2), CONCATENATE(DATA!$A$2:$A$1036, DATA!$D$2:$D$1036), 0)), 0)} -> 1944444.6 | H2: {=IFERROR(INDEX(DATA!$Q$2:$Q$1036, MATCH(CONCATENATE(YEAR(TODAY()), MONTH(TODAY()), Metrica!$C2), CONCATENATE(DATA!$A$2:$A$1036, DATA!$D$2:$D$1036), 0)), 0)} -> 0.16000003 | I2: {=IFERROR(INDEX(DATA!$H$2:$H$1036, MATCH(CONCATENATE(YEAR(TODAY()), MONTH(TODAY()), Metrica!$C2), CONCATENATE(DATA!$A$2:$A$1036, DATA!$D$2:$D$1036), 0)), 0)} -> 1944444.4 | J2: {=IFERROR(INDEX(DATA!$I$2:$I$1036, MATCH(CONCATENATE(YEAR(TODAY()), MONTH(TODAY()), Metrica!$C2), CONCATENATE(DATA!$A$2:$A$1036, DATA!$D$2:$D$1036), 0)), 0)} -> 82115.612 | K2: {=IFERROR(INDEX(DATA!$L$2:$L$1036, MATCH(CONCATENATE(YEAR(TODAY()), MONTH(TODAY()), Metrica!$C2), CONCATENATE(DATA!$A$2:$A$1036, DATA!$D$2:$D$1036), 0)), 0)} -> 280638.89 | L2: {=IFERROR(INDEX(DATA!$P$2:$P$1036, MATCH(CONCATENATE(YEAR(TODAY()), MONTH(TODAY()), Metrica!$C2), CONCATENATE(DATA!$A$2:$A$1036, DATA!$D$2:$D$1036), 0)), 0)} -> 2307436.9 | M2: {=IFERROR(INDEX(DATA!$R$2:$R$1036, MATCH(CONCATENATE(YEAR(TODAY()), MONTH(TODAY()), Metrica!$C2), CONCATENATE(DATA!$A$2:$A$1036, DATA!$D$2:$D$1036), 0)), 0)} -> -21 | N2: {=IFERROR(INDEX(DATA!$S$2:$S$1036, MATCH(CONCATENATE(YEAR(TODAY()), MONTH(TODAY()), Metrica!$C2), CONCATENATE(DATA!$A$2:$A$1036, DATA!$D$2:$D$1036), 0)), 0)} -> 0 | O2: {=IFERROR(IF(INDEX(DATA!$O$2:$O$1036,MATCH(CONCATENATE(YEAR(TODAY()), MONTH(TODAY()), Metrica!$C2), CONCATENATE(DATA!$A$2 $A$1036, DATA!$D$2:$D$1036), 0)) = 0,"",INDEX(DATA!$O$2:$O$1036,MATCH(CONCATENATE(YEAR(TODAY()), MONTH(TODAY()), Metrica!$C2), CONCATENATE(DATA!$A$2:$A$1036, DATA!$D$2:$D$1036), 0))),"")} | P2: {=IFERROR(INDEX(DATA!$U$2:$U$1036, MATCH(CONCATENATE(YEAR(TODAY()), MONTH(TODAY()), Metrica!$C2), CONCATENATE(DATA!$A$2:$A$1036, DATA!$D$2:$D$1036), 0)), 0)} -> PENDIENTE
A3: INVERSIONES RUEDA S.A.S | B3: SERFINANZAS | C3: 111000176344 | D3: {=IFERROR(INDEX(DATA!$E$2:$E$1036, MATCH(CONCATENATE(YEAR(TODAY()), MONTH(TODAY()), Metrica!$C3), CONCATENATE(DATA!$A$2:$A$1036, DATA!$D$2:$D$1036), 0)), "")} -> 45561 | E3: {=IFERROR(INDEX(DATA!$F$2:$F$1036, MATCH(CONCATENATE(YEAR(TODAY()), MONTH(TODAY()), Metrica!$C3), CONCATENATE(DATA!$A$2:$A$1036, DATA!$D$2:$D$1036), 0)), "")} -> 28 | F3: {=IFERROR(INDEX(DATA!$G$2:$G$1036, MATCH(CONCATENATE(YEAR(TODAY()), MONTH(TODAY()), Metrica!$C3), CONCATENATE(DATA!$A$2:$A$1036, DATA!$D$2:$D$1036), 0)), "")} -> 8 | G3: {=IFERROR(INDEX(DATA!$Q$2:$Q$1036, MATCH(CONCATENATE(YEAR(TODAY()), MONTH(TODAY()-31), Metrica!$C3), CONCATENATE(DATA!$A$2:$A$1036, DATA!$D$2:$D$1036), 0)), 0)} -> 5134675.5 | H3: {=IFERROR(INDEX(DATA!$Q$2:$Q$1036, MATCH(CONCATENATE(YEAR(TODAY()), MONTH(TODAY()), Metrica!$C3), CONCATENATE(DATA!$A$2:$A$1036, DATA!$D$2:$D$1036), 0)), 0)} -> 4612962.6 | I3: {=IFERROR(INDEX(DATA!$H$2:$H$1036, MATCH(CONCATENATE(YEAR(TODAY()), MONTH(TODAY()), Metrica!$C3), CONCATENATE(DATA!$A$2:$A$1036, DATA!$D$2:$D$1036), 0)), 0)} -> 521712.93 | J3: {=IFERROR(INDEX(DATA!$I$2:$I$1036, MATCH(CONCATENATE(YEAR(TODAY()), MONTH(TODAY()), Metrica!$C3), CONCATENATE(DATA!$A$2:$A$1036, DATA!$D$2:$D$1036), 0)), 0)} -> 84085.088 | K3: {=IFERROR(INDEX(DATA!$L$2:$L$1036, MATCH(CONCATENATE(YEAR(TODAY()), MONTH(TODAY()), Metrica!$C3), CONCATENATE(DATA!$A$2:$A$1036, DATA!$D$2:$D$1036), 0)), 0)} -> 0 | L3: {=IFERROR(INDEX(DATA!$P$2:$P$1036, MATCH(CONCATENATE(YEAR(TODAY()), MONTH(TODAY()), Metrica!$C3), CONCATENATE(DATA!$A$2:$A$1036, DATA!$D$2:$D$1036), 0)), 0)} -> 605798.01 | M3: {=IFERROR(INDEX(DATA!$R$2:$R$1036, MATCH(CONCATENATE(YEAR(TODAY()), MONTH(TODAY()), Metrica!$C3), CONCATENATE(DATA!$A$2:$A$1036, DATA!$D$2:$D$1036), 0)), 0)} -> 8 | N3: {=IFERROR(INDEX(DATA!$S$2:$S$1036, MATCH(CONCATENATE(YEAR(TODAY()), MONTH(TODAY()), Metrica!$C3), CONCATENATE(DATA!$A$2:$A$1036, DATA!$D$2:$D$1036), 0)), 0)} -> 0 | O3: {=IFERROR(IF(INDEX(DATA!$O$2:$O$1036,MATCH(CONCATENATE(YEAR(TODAY()), MONTH(TODAY()), Metrica!$C3), CONCATENATE(DATA!$A$2 $A$1036, DATA!$D$2:$D$1036), 0)) = 0,"",INDEX(DATA!$O$2:$O$1036,MATCH(CONCATENATE(YEAR(TODAY()), MONTH(TODAY()), Metrica!$C3), CONCATENATE(DATA!$A$2:$A$1036, DATA!$D$2:$D$1036), 0))),"")} | P3: {=IFERROR(INDEX(DATA!$U$2:$U$1036, MATCH(CONCATENATE(YEAR(TODAY()), MONTH(TODAY()), Metrica!$C3), CONCATENATE(DATA!$A$2:$A$1036, DATA!$D$2:$D$1036), 0)), 0)} -> PENDIENTE
A4: INVERSIONES RUEDA S.A.S | B4: SERFINANZAS | C4: 111000206579 | D4: {=IFERROR(INDEX(DATA!$E$2:$E$1036, MATCH(CONCATENATE(YEAR(TODAY()), MONTH(TODAY()), Metrica!$C4), CONCATENATE(DATA!$A$2:$A$1036, DATA!$D$2:$D$1036), 0)), "")} -> 45565 | E4: {=IFERROR(INDEX(DATA!$F$2:$F$1036, MATCH(CONCATENATE(YEAR(TODAY()), MONTH(TODAY()), Metrica!$C4), CONCATENATE(DATA!$A$2:$A$1036, DATA!$D$2:$D$1036), 0)), "")} -> 20 | F4: {=IFERROR(INDEX(DATA!$G$2:$G$1036, MATCH(CONCATENATE(YEAR(TODAY()), MONTH(TODAY()), Metrica!$C4), CONCATENATE(DATA!$A$2:$A$1036, DATA!$D$2:$D$1036), 0)), "")} -> 16 | G4: {=IFERROR(INDEX(DATA!$Q$2:$Q$1036, MATCH(CONCATENATE(YEAR(TODAY()), MONTH(TODAY()-31), Metrica!$C4), CONCATENATE(DATA!$A$2:$A$1036, DATA!$D$2:$D$1036), 0)), 0)} -> 5650159.5 | H4: {=IFERROR(INDEX(DATA!$Q$2:$Q$1036, MATCH(CONCATENATE(YEAR(TODAY()), MONTH(TODAY()), Metrica!$C4), CONCATENATE(DATA!$A$2:$A$1036, DATA!$D$2:$D$1036), 0)), 0)} -> 5384474.9 | I4: {=IFERROR(INDEX(DATA!$H$2:$H$1036, MATCH(CONCATENATE(YEAR(TODAY()), MONTH(TODAY()), Metrica!$C4), CONCATENATE(DATA!$A$2:$A$1036, DATA!$D$2:$D$1036), 0)), 0)} -> 265684.6 | J4: {=IFERROR(INDEX(DATA!$I$2:$I$1036, MATCH(CONCATENATE(YEAR(TODAY()), MONTH(TODAY()), Metrica!$C4), CONCATENATE(DATA!$A$2:$A$1036, DATA!$D$2:$D$1036), 0)), 0)} -> 119291.76 | K4: {=IFERROR(INDEX(DATA!$L$2:$L$1036, MATCH(CONCATENATE(YEAR(TODAY()), MONTH(TODAY()), Metrica!$C4), CONCATENATE(DATA!$A$2:$A$1036, DATA!$D$2:$D$1036), 0)), 0)} -> 0 | L4: {=IFERROR(INDEX(DATA!$P$2:$P$1036, MATCH(CONCATENATE(YEAR(TODAY()), MONTH(TODAY()), Metrica!$C4), CONCATENATE(DATA!$A$2:$A$1036, DATA!$D$2:$D$1036), 0)), 0)} -> 384976.37 | M4: {=IFERROR(INDEX(DATA!$R$2:$R$1036, MATCH(CONCATENATE(YEAR(TODAY()), MONTH(TODAY()), Metrica!$C4), CONCATENATE(DATA!$A$2:$A$1036, DATA!$D$2:$D$1036), 0)), 0)} -> 4 | N4: {=IFERROR(INDEX(DATA!$S$2:$S$1036, MATCH(CONCATENATE(YEAR(TODAY()), MONTH(TODAY()), Metrica!$C4), CONCATENATE(DATA!$A$2:$A$1036, DATA!$D$2:$D$1036), 0)), 0)} -> 0 | O4: {=IFERROR(IF(INDEX(DATA!$O$2:$O$1036,MATCH(CONCATENATE(YEAR(TODAY()), MONTH(TODAY()), Metrica!$C4), CONCATENATE(DATA!$A$2 $A$1036, DATA!$D$2:$D$1036), 0)) = 0,"",INDEX(DATA!$O$2:$O$1036,MATCH(CONCATENATE(YEAR(TODAY()), MONTH(TODAY()), Metrica!$C4), CONCATENATE(DATA!$A$2:$A$1036, DATA!$D$2:$D$1036), 0))),"")} | P4: {=IFERROR(INDEX(DATA!$U$2:$U$1036, MATCH(CONCATENATE(YEAR(TODAY()), MONTH(TODAY()), Metrica!$C4), CONCATENATE(DATA!$A$2:$A$1036, DATA!$D$2:$D$1036), 0)), 0)} -> PENDIENTE
A5: INVERSIONES RUEDA S.A.S | B5: SERFINANZAS | C5: 111000194235 | D5: {=IFERROR(INDEX(DATA!$E$2:$E$1036, MATCH(CONCATENATE(YEAR(TODAY()), MONTH(TODAY()), Metrica!$C5), CONCATENATE(DATA!$A$2:$A$1036, DATA!$D$2:$D$1036), 0)), "")} -> 45560 | E5: {=IFERROR(INDEX(DATA!$F$2:$F$1036, MATCH(CONCATENATE(YEAR(TODAY()), MONTH(TODAY()), Metrica!$C5), CONCATENATE(DATA!$A$2:$A$1036, DATA!$D$2:$D$1036), 0)), "")} -> 23 | F5: {=IFERROR(INDEX(DATA!$G$2:$G$1036, MATCH(CONCATENATE(YEAR(TODAY()), MONTH(TODAY()), Metrica!$C5), CONCATENATE(DATA!$A$2:$A$1036, DATA!$D$2:$D$1036), 0)), "")} -> 13 | G5: {=IFERROR(INDEX(DATA!$Q$2:$Q$1036, MATCH(CONCATENATE(YEAR(TODAY()), MONTH(TODAY()-31), Metrica!$C5), CONCATENATE(DATA!$A$2:$A$1036, DATA!$D$2:$D$1036), 0)), 0)} -> 6220317.7 | H5: {=IFERROR(INDEX(DATA!$Q$2:$Q$1036, MATCH(CONCATENATE(YEAR(TODAY()), MONTH(TODAY()), Metrica!$C5), CONCATENATE(DATA!$A$2:$A$1036, DATA!$D$2:$D$1036), 0)), 0)} -> 5825194.1 | I5: {=IFERROR(INDEX(DATA!$H$2:$H$1036, MATCH(CONCATENATE(YEAR(TODAY()), MONTH(TODAY()), Metrica!$C5), CONCATENATE(DATA!$A$2:$A$1036, DATA!$D$2:$D$1036), 0)), 0)} -> 395123.6 | J5: {=IFERROR(INDEX(DATA!$I$2:$I$1036, MATCH(CONCATENATE(YEAR(TODAY()), MONTH(TODAY()), Metrica!$C5), CONCATENATE(DATA!$A$2:$A$1036, DATA!$D$2:$D$1036), 0)), 0)} -> 110824.26 | K5: {=IFERROR(INDEX(DATA!$L$2:$L$1036, MATCH(CONCATENATE(YEAR(TODAY()), MONTH(TODAY()), Metrica!$C5), CONCATENATE(DATA!$A$2:$A$1036, DATA!$D$2:$D$1036), 0)), 0)} -> 0 | L5: {=IFERROR(INDEX(DATA!$P$2:$P$1036, MATCH(CONCATENATE(YEAR(TODAY()), MONTH(TODAY()), Metrica!$C5), CONCATENATE(DATA!$A$2:$A$1036, DATA!$D$2:$D$1036), 0)), 0)} -> 505947.86 | M5: {=IFERROR(INDEX(DATA!$R$2:$R$1036, MATCH(CONCATENATE(YEAR(TODAY()), MONTH(TODAY()), Metrica!$C5), CONCATENATE(DATA!$A$2:$A$1036, DATA!$D$2:$D$1036), 0)), 0)} -> 9 | N5: {=IFERROR(INDEX(DATA!$S$2:$S$1036, MATCH(CONCATENATE(YEAR(TODAY()), MONTH(TODAY()), Metrica!$C5), CONCATENATE(DATA!$A$2:$A$1036, DATA!$D$2:$D$1036), 0)), 0)} -> 0 | O5: {=IFERROR(IF(INDEX(DATA!$O$2:$O$1036,MATCH(CONCATENATE(YEAR(TODAY()), MONTH(TODAY()), Metrica!$C5), CONCATENATE(DATA!$A$2 $A$1036, DATA!$D$2:$D$1036), 0)) = 0,"",INDEX(DATA!$O$2:$O$1036,MATCH(CONCATENATE(YEAR(TODAY()), MONTH(TODAY()), Metrica!$C5), CONCATENATE(DATA!$A$2:$A$1036, DATA!$D$2:$D$1036), 0))),"")} | P5: {=IFERROR(INDEX(DATA!$U$2:$U$1036, MATCH(CONCATENATE(YEAR(TODAY()), MONTH(TODAY()), Metrica!$C5), CONCATENATE(DATA!$A$2:$A$1036, DATA!$D$2:$D$1036), 0)), 0)} -> PENDIENTE
A6: LAMAR OPTICAL S.A.S | B6: BANCOLOMBIA | C6: 8140099320 | D6: {=IFERROR(INDEX(DATA!$E$2:$E$1036, MATCH(CONCATENATE(YEAR(TODAY()), MONTH(TODAY()), Metrica!$C6), CONCATENATE(DATA!$A$2:$A$1036, DATA!$D$2:$D$1036), 0)), "")} -> 45548 | E6: {=IFERROR(INDEX(DATA!$F$2:$F$1036, MATCH(CONCATENATE(YEAR(TODAY()), MONTH(TODAY()), Metrica!$C6), CONCATENATE(DATA!$A$2:$A$1036, DATA!$D$2:$D$1036), 0)), "")} -> 7 | F6: {=IFERROR(INDEX(DATA!$G$2:$G$1036, MATCH(CONCATENATE(YEAR(TODAY()), MONTH(TODAY()), Metrica!$C6), CONCATENATE(DATA!$A$2:$A$1036, DATA!$D$2:$D$1036), 0)), "")} -> 5 | G6: {=IFERROR(INDEX(DATA!$Q$2:$Q$1036, MATCH(CONCATENATE(YEAR(TODAY()), MONTH(TODAY()-31), Metrica!$C6), CONCATENATE(DATA!$A$2:$A$1036, DATA!$D$2:$D$1036), 0)), 0)} -> 8861046 | H6: {=IFERROR(INDEX(DATA!$Q$2:$Q$1036, MATCH(CONCATENATE(YEAR(TODAY()), MONTH(TODAY()), Metrica!$C6), CONCATENATE(DATA!$A$2:$A$1036, DATA!$D$2:$D$1036), 0)), 0)} -> 7384205 | I6: {=IFERROR(INDEX(DATA!$H$2:$H$1036, MATCH(CONCATENATE(YEAR(TODAY()), MONTH(TODAY()), Metrica!$C6), CONCATENATE(DATA!$A$2:$A$1036, DATA!$D$2:$D$1036), 0)), 0)} -> 1476841 | J6: {=IFERROR(INDEX(DATA!$I$2:$I$1036, MATCH(CONCATENATE(YEAR(TODAY()), MONTH(TODAY()), Metrica!$C6), CONCATENATE(DATA!$A$2:$A$1036, DATA!$D$2:$D$1036), 0)), 0)} -> 120510.23 | K6: {=IFERROR(INDEX(DATA!$L$2:$L$1036, MATCH(CONCATENATE(YEAR(TODAY()), MONTH(TODAY()), Metrica!$C6), CONCATENATE(DATA!$A$2:$A$1036, DATA!$D$2:$D$1036), 0)), 0)} -> 8727.564 | L6: {=IFERROR(INDEX(DATA!$P$2:$P$1036, MATCH(CONCATENATE(YEAR(TODAY()), MONTH(TODAY()), Metrica!$C6), CONCATENATE(DATA!$A$2:$A$1036, DATA!$D$2:$D$1036), 0)), 0)} -> 1606078.8 | M6: {=IFERROR(INDEX(DATA!$R$2:$R$1036, MATCH(CONCATENATE(YEAR(TODAY()), MONTH(TODAY()), Metrica!$C6), CONCATENATE(DATA!$A$2:$A$1036, DATA!$D$2:$D$1036), 0)), 0)} -> -10 | N6: {=IFERROR(INDEX(DATA!$S$2:$S$1036, MATCH(CONCATENATE(YEAR(TODAY()), MONTH(TODAY()), Metrica!$C6), CONCATENATE(DATA!$A$2:$A$1036, DATA!$D$2:$D$1036), 0)), 0)} -> 0 | O6: {=IFERROR(IF(INDEX(DATA!$O$2:$O$1036,MATCH(CONCATENATE(YEAR(TODAY()), MONTH(TODAY()), Metrica!$C6), CONCATENATE(DATA!$A$2 $A$1036, DATA!$D$2:$D$1036), 0)) = 0,"",INDEX(DATA!$O$2:$O$1036,MATCH(CONCATENATE(YEAR(TODAY()), MONTH(TODAY()), Metrica!$C6), CONCATENATE(DATA!$A$2:$A$1036, DATA!$D$2:$D$1036), 0))),"")} | P6: {=IFERROR(INDEX(DATA!$U$2:$U$1036, MATCH(CONCATENATE(YEAR(TODAY()), MONTH(TODAY()), Metrica!$C6), CONCATENATE(DATA!$A$2:$A$1036, DATA!$D$2:$D$1036), 0)), 0)} -> PENDIENTE
A7: GLADYS JEANNETH CORREA RUEDA | B7: SERFINANZAS | C7: 5420603691529285 | D7: {=IFERROR(INDEX(DATA!$E$2:$E$1036, MATCH(CONCATENATE(YEAR(TODAY()), MONTH(TODAY()), Metrica!$C7), CONCATENATE(DATA!$A$2:$A$1036, DATA!$D$2:$D$1036), 0)), "")} -> 45540 | E7: {=IFERROR(INDEX(DATA!$F$2:$F$1036, MATCH(CONCATENATE(YEAR(TODAY()), MONTH(TODAY()), Metrica!$C7), CONCATENATE(DATA!$A$2:$A$1036, DATA!$D$2:$D$1036), 0)), "")} -> 21 | F7: {=IFERROR(INDEX(DATA!$G$2:$G$1036, MATCH(CONCATENATE(YEAR(TODAY()), MONTH(TODAY()), Metrica!$C7), CONCATENATE(DATA!$A$2:$A$1036, DATA!$D$2:$D$1036), 0)), "")} -> 27 | G7: {=IFERROR(INDEX(DATA!$Q$2:$Q$1036, MATCH(CONCATENATE(YEAR(TODAY()), MONTH(TODAY()-31), Metrica!$C7), CONCATENATE(DATA!$A$2:$A$1036, DATA!$D$2:$D$1036), 0)), 0)} -> 9537523.9 | H7: {=IFERROR(INDEX(DATA!$Q$2:$Q$1036, MATCH(CONCATENATE(YEAR(TODAY()), MONTH(TODAY()), Metrica!$C7), CONCATENATE(DATA!$A$2:$A$1036, DATA!$D$2:$D$1036), 0)), 0)} -> 9074953.1 | I7: {=IFERROR(INDEX(DATA!$H$2:$H$1036, MATCH(CONCATENATE(YEAR(TODAY()), MONTH(TODAY()), Metrica!$C7), CONCATENATE(DATA!$A$2:$A$1036, DATA!$D$2:$D$1036), 0)), 0)} -> 462570.86 | J7: {=IFERROR(INDEX(DATA!$I$2:$I$1036, MATCH(CONCATENATE(YEAR(TODAY()), MONTH(TODAY()), Metrica!$C7), CONCATENATE(DATA!$A$2:$A$1036, DATA!$D$2:$D$1036), 0)), 0)} -> 68670.172 | K7: {=IFERROR(INDEX(DATA!$L$2:$L$1036, MATCH(CONCATENATE(YEAR(TODAY()), MONTH(TODAY()), Metrica!$C7), CONCATENATE(DATA!$A$2:$A$1036, DATA!$D$2:$D$1036), 0)), 0)} -> 2073122.3 | L7: {=IFERROR(INDEX(DATA!$P$2:$P$1036, MATCH(CONCATENATE(YEAR(TODAY()), MONTH(TODAY()), Metrica!$C7), CONCATENATE(DATA!$A$2:$A$1036, DATA!$D$2:$D$1036), 0)), 0)} -> 2630263.3 | M7: {=IFERROR(INDEX(DATA!$R$2:$R$1036, MATCH(CONCATENATE(YEAR(TODAY()), MONTH(TODAY()), Metrica!$C7), CONCATENATE(DATA!$A$2:$A$1036, DATA!$D$2:$D$1036), 0)), 0)} -> -2 | N7: {=IFERROR(INDEX(DATA!$S$2:$S$1036, MATCH(CONCATENATE(YEAR(TODAY()), MONTH(TODAY()), Metrica!$C7), CONCATENATE(DATA!$A$2:$A$1036, DATA!$D$2:$D$1036), 0)), 0)} -> 0 | O7: {=IFERROR(IF(INDEX(DATA!$O$2:$O$1036,MATCH(CONCATENATE(YEAR(TODAY()), MONTH(TODAY()), Metrica!$C7), CONCATENATE(DATA!$A$2 $A$1036, DATA!$D$2:$D$1036), 0)) = 0,"",INDEX(DATA!$O$2:$O$1036,MATCH(CONCATENATE(YEAR(TODAY()), MONTH(TODAY()), Metrica!$C7), CONCATENATE(DATA!$A$2:$A$1036, DATA!$D$2:$D$1036), 0))),"")} | P7: {=IFERROR(INDEX(DATA!$U$2:$U$1036, MATCH(CONCATENATE(YEAR(TODAY()), MONTH(TODAY()), Metrica!$C7), CONCATENATE(DATA!$A$2:$A$1036, DATA!$D$2:$D$1036), 0)), 0)} -> PENDIENTE
A8: LAMAR OPTICAL S.A.S | B8: BANCOLOMBIA | C8: 8140097009 | D8: {=IFERROR(INDEX(DATA!$E$2:$E$1036, MATCH(CONCATENATE(YEAR(TODAY()), MONTH(TODAY()), Metrica!$C8), CONCATENATE(DATA!$A$2:$A$1036, DATA!$D$2:$D$1036), 0)), "")} -> 45543 | E8: {=IFERROR(INDEX(DATA!$F$2:$F$1036, MATCH(CONCATENATE(YEAR(TODAY()), MONTH(TODAY()), Metrica!$C8), CONCATENATE(DATA!$A$2:$A$1036, DATA!$D$2:$D$1036), 0)), "")} -> 22 | F8: {=IFERROR(INDEX(DATA!$G$2:$G$1036, MATCH(CONCATENATE(YEAR(TODAY()), MONTH(TODAY()), Metrica!$C8), CONCATENATE(DATA!$A$2:$A$1036, DATA!$D$2:$D$1036), 0)), "")} -> 14 | G8: {=IFERROR(INDEX(DATA!$Q$2:$Q$1036, MATCH(CONCATENATE(YEAR(TODAY()), MONTH(TODAY()-31), Metrica!$C8), CONCATENATE(DATA!$A$2:$A$1036, DATA!$D$2:$D$1036), 0)), 0)} -> 9568352 | H8: {=IFERROR(INDEX(DATA!$Q$2:$Q$1036, MATCH(CONCATENATE(YEAR(TODAY()), MONTH(TODAY()), Metrica!$C8), CONCATENATE(DATA!$A$2:$A$1036, DATA!$D$2:$D$1036), 0)), 0)} -> 8930464 | I8: {=IFERROR(INDEX(DATA!$H$2:$H$1036, MATCH(CONCATENATE(YEAR(TODAY()), MONTH(TODAY()), Metrica!$C8), CONCATENATE(DATA!$A$2:$A$1036, DATA!$D$2:$D$1036), 0)), 0)} -> 637888 | J8: {=IFERROR(INDEX(DATA!$I$2:$I$1036, MATCH(CONCATENATE(YEAR(TODAY()), MONTH(TODAY()), Metrica!$C8), CONCATENATE(DATA!$A$2:$A$1036, DATA!$D$2:$D$1036), 0)), 0)} -> 194603.39 | K8: {=IFERROR(INDEX(DATA!$L$2:$L$1036, MATCH(CONCATENATE(YEAR(TODAY()), MONTH(TODAY()), Metrica!$C8), CONCATENATE(DATA!$A$2:$A$1036, DATA!$D$2:$D$1036), 0)), 0)} -> 17579.144 | L8: {=IFERROR(INDEX(DATA!$P$2:$P$1036, MATCH(CONCATENATE(YEAR(TODAY()), MONTH(TODAY()), Metrica!$C8), CONCATENATE(DATA!$A$2:$A$1036, DATA!$D$2:$D$1036), 0)), 0)} -> 850070.53 | M8: {=IFERROR(INDEX(DATA!$R$2:$R$1036, MATCH(CONCATENATE(YEAR(TODAY()), MONTH(TODAY()), Metrica!$C8), CONCATENATE(DATA!$A$2:$A$1036, DATA!$D$2:$D$1036), 0)), 0)} -> -5 | N8: {=IFERROR(INDEX(DATA!$S$2:$S$1036, MATCH(CONCATENATE(YEAR(TODAY()), MONTH(TODAY()), Metrica!$C8), CONCATENATE(DATA!$A$2:$A$1036, DATA!$D$2:$D$1036), 0)), 0)} -> 0 | O8: {=IFERROR(IF(INDEX(DATA!$O$2:$O$1036,MATCH(CONCATENATE(YEAR(TODAY()), MONTH(TODAY()), Metrica!$C8), CONCATENATE(DATA!$A$2 $A$1036, DATA!$D$2:$D$1036), 0)) = 0,"",INDEX(DATA!$O$2:$O$1036,MATCH(CONCATENATE(YEAR(TODAY()), MONTH(TODAY()), Metrica!$C8), CONCATENATE(DATA!$A$2:$A$1036, DATA!$D$2:$D$1036), 0))),"")} | P8: {=IFERROR(INDEX(DATA!$U$2:$U$1036, MATCH(CONCATENATE(YEAR(TODAY()), MONTH(TODAY()), Metrica!$C8), CONCATENATE(DATA!$A$2:$A$1036, DATA!$D$2:$D$1036), 0)), 0)} -> PENDIENTE
A9: LAMAR OPTICAL S.A.S | B9: SERFINANZAS | C9: 111000176362 | D9: {=IFERROR(INDEX(DATA!$E$2:$E$1036, MATCH(CONCATENATE(YEAR(TODAY()), MONTH(TODAY()), Metrica!$C9), CONCATENATE(DATA!$A$2:$A$1036, DATA!$D$2:$D$1036), 0)), "")} -> 45561 | E9: {=IFERROR(INDEX(DATA!$F$2:$F$1036, MATCH(CONCATENATE(YEAR(TODAY()), MONTH(TODAY()), Metrica!$C9), CONCATENATE(DATA!$A$2:$A$1036, DATA!$D$2:$D$1036), 0)), "")} -> 28 | F9: {=IFERROR(INDEX(DATA!$G$2:$G$1036, MATCH(CONCATENATE(YEAR(TODAY()), MONTH(TODAY()), Metrica!$C9), CONCATENATE(DATA!$A$2:$A$1036, DATA!$D$2:$D$1036), 0)), "")} -> 8 | G9: {=IFERROR(INDEX(DATA!$Q$2:$Q$1036, MATCH(CONCATENATE(YEAR(TODAY()), MONTH(TODAY()-31), Metrica!$C9), CONCATENATE(DATA!$A$2:$A$1036, DATA!$D$2:$D$1036), 0)), 0)} -> 9746814 | H9: {=IFERROR(INDEX(DATA!$Q$2:$Q$1036, MATCH(CONCATENATE(YEAR(TODAY()), MONTH(TODAY()), Metrica!$C9), CONCATENATE(DATA!$A$2:$A$1036, DATA!$D$2:$D$1036), 0)), 0)} -> 8702971 | I9: {=IFERROR(INDEX(DATA!$H$2:$H$1036, MATCH(CONCATENATE(YEAR(TODAY()), MONTH(TODAY()), Metrica!$C9), CONCATENATE(DATA!$A$2:$A$1036, DATA!$D$2:$D$1036), 0)), 0)} -> 1043843 | J9: {=IFERROR(INDEX(DATA!$I$2:$I$1036, MATCH(CONCATENATE(YEAR(TODAY()), MONTH(TODAY()), Metrica!$C9), CONCATENATE(DATA!$A$2:$A$1036, DATA!$D$2:$D$1036), 0)), 0)} -> 185580.9 | K9: {=IFERROR(INDEX(DATA!$L$2:$L$1036, MATCH(CONCATENATE(YEAR(TODAY()), MONTH(TODAY()), Metrica!$C9), CONCATENATE(DATA!$A$2:$A$1036, DATA!$D$2:$D$1036), 0)), 0)} -> 0 | L9: {=IFERROR(INDEX(DATA!$P$2:$P$1036, MATCH(CONCATENATE(YEAR(TODAY()), MONTH(TODAY()), Metrica!$C9), CONCATENATE(DATA!$A$2:$A$1036, DATA!$D$2:$D$1036), 0)), 0)} -> 1229424 | M9: {=IFERROR(INDEX(DATA!$R$2:$R$1036, MATCH(CONCATENATE(YEAR(TODAY()), MONTH(TODAY()), Metrica!$C9), CONCATENATE(DATA!$A$2:$A$1036, DATA!$D$2:$D$1036), 0)), 0)} -> 8 | N9: {=IFERROR(INDEX(DATA!$S$2:$S$1036, MATCH(CONCATENATE(YEAR(TODAY()), MONTH(TODAY()), Metrica!$C9), CONCATENATE(DATA!$A$2:$A$1036, DATA!$D$2:$D$1036), 0)), 0)} -> 0 | O9: {=IFERROR(IF(INDEX(DATA!$O$2:$O$1036,MATCH(CONCATENATE(YEAR(TODAY()), MONTH(TODAY()), Metrica!$C9), CONCATENATE(DATA!$A$2 $A$1036, DATA!$D$2:$D$1036), 0)) = 0,"",INDEX(DATA!$O$2:$O$1036,MATCH(CONCATENATE(YEAR(TODAY()), MONTH(TODAY()), Metrica!$C9), CONCATENATE(DATA!$A$2:$A$1036, DATA!$D$2:$D$1036), 0))),"")} | P9: {=IFERROR(INDEX(DATA!$U$2:$U$1036, MATCH(CONCATENATE(YEAR(TODAY()), MONTH(TODAY()), Metrica!$C9), CONCATENATE(DATA!$A$2:$A$1036, DATA!$D$2:$D$1036), 0)), 0)} -> PENDIENTE
A10: INVERSIONES RUEDA S.A.S | B10: SERFINANZAS | C10: 111000149580 | D10: {=IFERROR(INDEX(DATA!$E$2:$E$1036, MATCH(CONCATENATE(YEAR(TODAY()), MONTH(TODAY()), Metrica!$C10), CONCATENATE(DATA!$A$2:$A$1036, DATA!$D$2:$D$1036), 0)), "")} -> 45548 | E10: {=IFERROR(INDEX(DATA!$F$2:$F$1036, MATCH(CONCATENATE(YEAR(TODAY()), MONTH(TODAY()), Metrica!$C10), CONCATENATE(DATA!$A$2:$A$1036, DATA!$D$2:$D$1036), 0)), "")} -> 35 | F10: {=IFERROR(INDEX(DATA!$G$2:$G$1036, MATCH(CONCATENATE(YEAR(TODAY()), MONTH(TODAY()), Metrica!$C10), CONCATENATE(DATA!$A$2:$A$1036, DATA!$D$2:$D$1036), 0)), "")} -> 1 | G10: {=IFERROR(INDEX(DATA!$Q$2:$Q$1036, MATCH(CONCATENATE(YEAR(TODAY()), MONTH(TODAY()-31), Metrica!$C10), CONCATENATE(DATA!$A$2:$A$1036, DATA!$D$2:$D$1036), 0)), 0)} -> 10053092 | H10: {=IFERROR(INDEX(DATA!$Q$2:$Q$1036, MATCH(CONCATENATE(YEAR(TODAY()), MONTH(TODAY()), Metrica!$C10), CONCATENATE(DATA!$A$2:$A$1036, DATA!$D$2:$D$1036), 0)), 0)} -> 6827147.9 | I10: {=IFERROR(INDEX(DATA!$H$2:$H$1036, MATCH(CONCATENATE(YEAR(TODAY()), MONTH(TODAY()), Metrica!$C10), CONCATENATE(DATA!$A$2:$A$1036, DATA!$D$2:$D$1036), 0)), 0)} -> 3225943.9 | J10: {=IFERROR(INDEX(DATA!$I$2:$I$1036, MATCH(CONCATENATE(YEAR(TODAY()), MONTH(TODAY()), Metrica!$C10), CONCATENATE(DATA!$A$2:$A$1036, DATA!$D$2:$D$1036), 0)), 0)} -> 167068.2 | K10: {=IFERROR(INDEX(DATA!$L$2:$L$1036, MATCH(CONCATENATE(YEAR(TODAY()), MONTH(TODAY()), Metrica!$C10), CONCATENATE(DATA!$A$2:$A$1036, DATA!$D$2:$D$1036), 0)), 0)} -> 0 | L10: {=IFERROR(INDEX(DATA!$P$2:$P$1036, MATCH(CONCATENATE(YEAR(TODAY()), MONTH(TODAY()), Metrica!$C10), CONCATENATE(DATA!$A$2:$A$1036, DATA!$D$2:$D$1036), 0)), 0)} -> 3393012.1 | M10: {=IFERROR(INDEX(DATA!$R$2:$R$1036, MATCH(CONCATENATE(YEAR(TODAY()), MONTH(TODAY()), Metrica!$C10), CONCATENATE(DATA!$A$2:$A$1036, DATA!$D$2:$D$1036), 0)), 0)} -> 21 | N10: {=IFERROR(INDEX(DATA!$S$2:$S$1036, MATCH(CONCATENATE(YEAR(TODAY()), MONTH(TODAY()), Metrica!$C10), CONCATENATE(DATA!$A$2:$A$1036, DATA!$D$2:$D$1036), 0)), 0)} -> 0 | O10: {=IFERROR(IF(INDEX(DATA!$O$2:$O$1036,MATCH(CONCATENATE(YEAR(TODAY()), MONTH(TODAY()), Metrica!$C10), CONCATENATE(DATA!$A$2 $A$1036, DATA!$D$2:$D$1036), 0)) = 0,"",INDEX(DATA!$O$2:$O$1036,MATCH(CONCATENATE(YEAR(TODAY()), MONTH(TODAY()), Metrica!$C10), CONCATENATE(DATA!$A$2:$A$1036, DATA!$D$2:$D$1036), 0))),"")} | P10: {=IFERROR(INDEX(DATA!$U$2:$U$1036, MATCH(CONCATENATE(YEAR(TODAY()), MONTH(TODAY()), Metrica!$C10), CONCATENATE(DATA!$A$2:$A$1036, DATA!$D$2:$D$1036), 0)), 0)} -> PENDIENTE
A11: LAMAR OPTICAL S.A.S | B11: SERFINANZAS | C11: 111000206819 | D11: {=IFERROR(INDEX(DATA!$E$2:$E$1036, MATCH(CONCATENATE(YEAR(TODAY()), MONTH(TODAY()), Metrica!$C11), CONCATENATE(DATA!$A$2:$A$1036, DATA!$D$2:$D$1036), 0)), "")} -> 45565 | E11: {=IFERROR(INDEX(DATA!$F$2:$F$1036, MATCH(CONCATENATE(YEAR(TODAY()), MONTH(TODAY()), Metrica!$C11), CONCATENATE(DATA!$A$2:$A$1036, DATA!$D$2:$D$1036), 0)), "")} -> 20 | F11: {=IFERROR(INDEX(DATA!$G$2:$G$1036, MATCH(CONCATENATE(YEAR(TODAY()), MONTH(TODAY()), Metrica!$C11), CONCATENATE(DATA!$A$2:$A$1036, DATA!$D$2:$D$1036), 0)), "")} -> 16 | G11: {=IFERROR(INDEX(DATA!$Q$2:$Q$1036, MATCH(CONCATENATE(YEAR(TODAY()), MONTH(TODAY()-31), Metrica!$C11), CONCATENATE(DATA!$A$2:$A$1036, DATA!$D$2:$D$1036), 0)), 0)} -> 12482227 | H11: {=IFERROR(INDEX(DATA!$Q$2:$Q$1036, MATCH(CONCATENATE(YEAR(TODAY()), MONTH(TODAY()), Metrica!$C11), CONCATENATE(DATA!$A$2:$A$1036, DATA!$D$2:$D$1036), 0)), 0)} -> 11830102 | I11: {=IFERROR(INDEX(DATA!$H$2:$H$1036, MATCH(CONCATENATE(YEAR(TODAY()), MONTH(TODAY()), Metrica!$C11), CONCATENATE(DATA!$A$2:$A$1036, DATA!$D$2:$D$1036), 0)), 0)} -> 652125.61 | J11: {=IFERROR(INDEX(DATA!$I$2:$I$1036, MATCH(CONCATENATE(YEAR(TODAY()), MONTH(TODAY()), Metrica!$C11), CONCATENATE(DATA!$A$2:$A$1036, DATA!$D$2:$D$1036), 0)), 0)} -> 261137.75 | K11: {=IFERROR(INDEX(DATA!$L$2:$L$1036, MATCH(CONCATENATE(YEAR(TODAY()), MONTH(TODAY()), Metrica!$C11), CONCATENATE(DATA!$A$2:$A$1036, DATA!$D$2:$D$1036), 0)), 0)} -> 0 | L11: {=IFERROR(INDEX(DATA!$P$2:$P$1036, MATCH(CONCATENATE(YEAR(TODAY()), MONTH(TODAY()), Metrica!$C11), CONCATENATE(DATA!$A$2:$A$1036, DATA!$D$2:$D$1036), 0)), 0)} -> 913263.35 | M11: {=IFERROR(INDEX(DATA!$R$2:$R$1036, MATCH(CONCATENATE(YEAR(TODAY()), MONTH(TODAY()), Metrica!$C11), CONCATENATE(DATA!$A$2:$A$1036, DATA!$D$2:$D$1036), 0)), 0)} -> 4 | N11: {=IFERROR(INDEX(DATA!$S$2:$S$1036, MATCH(CONCATENATE(YEAR(TODAY()), MONTH(TODAY()), Metrica!$C11), CONCATENATE(DATA!$A$2:$A$1036, DATA!$D$2:$D$1036), 0)), 0)} -> 0 | O11: {=IFERROR(IF(INDEX(DATA!$O$2:$O$1036,MATCH(CONCATENATE(YEAR(TODAY()), MONTH(TODAY()), Metrica!$C11), CONCATENATE(DATA!$A$2 $A$1036, DATA!$D$2:$D$1036), 0)) = 0,"",INDEX(DATA!$O$2:$O$1036,MATCH(CONCATENATE(YEAR(TODAY()), MONTH(TODAY()), Metrica!$C11), CONCATENATE(DATA!$A$2:$A$1036, DATA!$D$2:$D$1036), 0))),"")} | P11: {=IFERROR(INDEX(DATA!$U$2:$U$1036, MATCH(CONCATENATE(YEAR(TODAY()), MONTH(TODAY()), Metrica!$C11), CONCATENATE(DATA!$A$2:$A$1036, DATA!$D$2:$D$1036), 0)), 0)} -> PENDIENTE
A12: LAMAR OPTICAL S.A.S | B12: BANCOLOMBIA | C12: 8140098987 | D12: {=IFERROR(INDEX(DATA!$E$2:$E$1036, MATCH(CONCATENATE(YEAR(TODAY()), MONTH(TODAY()), Metrica!$C12), CONCATENATE(DATA!$A$2:$A$1036, DATA!$D$2:$D$1036), 0)), "")} -> 45564 | E12: {=IFERROR(INDEX(DATA!$F$2:$F$1036, MATCH(CONCATENATE(YEAR(TODAY()), MONTH(TODAY()), Metrica!$C12), CONCATENATE(DATA!$A$2:$A$1036, DATA!$D$2:$D$1036), 0)), "")} -> 10 | F12: {=IFERROR(INDEX(DATA!$G$2:$G$1036, MATCH(CONCATENATE(YEAR(TODAY()), MONTH(TODAY()), Metrica!$C12), CONCATENATE(DATA!$A$2:$A$1036, DATA!$D$2:$D$1036), 0)), "")} -> 2 | G12: {=IFERROR(INDEX(DATA!$Q$2:$Q$1036, MATCH(CONCATENATE(YEAR(TODAY()), MONTH(TODAY()-31), Metrica!$C12), CONCATENATE(DATA!$A$2:$A$1036, DATA!$D$2:$D$1036), 0)), 0)} -> 15000000 | H12: {=IFERROR(INDEX(DATA!$Q$2:$Q$1036, MATCH(CONCATENATE(YEAR(TODAY()), MONTH(TODAY()), Metrica!$C12), CONCATENATE(DATA!$A$2:$A$1036, DATA!$D$2:$D$1036), 0)), 0)} -> 10000000 | I12: {=IFERROR(INDEX(DATA!$H$2:$H$1036, MATCH(CONCATENATE(YEAR(TODAY()), MONTH(TODAY()), Metrica!$C12), CONCATENATE(DATA!$A$2:$A$1036, DATA!$D$2:$D$1036), 0)), 0)} -> 5000000 | J12: {=IFERROR(INDEX(DATA!$I$2:$I$1036, MATCH(CONCATENATE(YEAR(TODAY()), MONTH(TODAY()), Metrica!$C12), CONCATENATE(DATA!$A$2:$A$1036, DATA!$D$2:$D$1036), 0)), 0)} -> 241475 | K12: {=IFERROR(INDEX(DATA!$L$2:$L$1036, MATCH(CONCATENATE(YEAR(TODAY()), MONTH(TODAY()), Metrica!$C12), CONCATENATE(DATA!$A$2:$A$1036, DATA!$D$2:$D$1036), 0)), 0)} -> 204505.67 | L12: {=IFERROR(INDEX(DATA!$P$2:$P$1036, MATCH(CONCATENATE(YEAR(TODAY()), MONTH(TODAY()), Metrica!$C12), CONCATENATE(DATA!$A$2:$A$1036, DATA!$D$2:$D$1036), 0)), 0)} -> 5445980.7 | M12: {=IFERROR(INDEX(DATA!$R$2:$R$1036, MATCH(CONCATENATE(YEAR(TODAY()), MONTH(TODAY()), Metrica!$C12), CONCATENATE(DATA!$A$2:$A$1036, DATA!$D$2:$D$1036), 0)), 0)} -> -26 | N12: {=IFERROR(INDEX(DATA!$S$2:$S$1036, MATCH(CONCATENATE(YEAR(TODAY()), MONTH(TODAY()), Metrica!$C12), CONCATENATE(DATA!$A$2:$A$1036, DATA!$D$2:$D$1036), 0)), 0)} -> 0 | O12: {=IFERROR(IF(INDEX(DATA!$O$2:$O$1036,MATCH(CONCATENATE(YEAR(TODAY()), MONTH(TODAY()), Metrica!$C12), CONCATENATE(DATA!$A$2 $A$1036, DATA!$D$2:$D$1036), 0)) = 0,"",INDEX(DATA!$O$2:$O$1036,MATCH(CONCATENATE(YEAR(TODAY()), MONTH(TODAY()), Metrica!$C12), CONCATENATE(DATA!$A$2:$A$1036, DATA!$D$2:$D$1036), 0))),"")} | P12: {=IFERROR(INDEX(DATA!$U$2:$U$1036, MATCH(CONCATENATE(YEAR(TODAY()), MONTH(TODAY()), Metrica!$C12), CONCATENATE(DATA!$A$2:$A$1036, DATA!$D$2:$D$1036), 0)), 0)} -> PENDIENTE
A13: INVERSIONES RUEDA S.A.S | B13: BANCOLOMBIA | C13: 8140098556 | D13: {=IFERROR(INDEX(DATA!$E$2:$E$1036, MATCH(CONCATENATE(YEAR(TODAY()), MONTH(TODAY()), Metrica!$C13), CONCATENATE(DATA!$A$2:$A$1036, DATA!$D$2:$D$1036), 0)), "")} -> 45565 | E13: {=IFERROR(INDEX(DATA!$F$2:$F$1036, MATCH(CONCATENATE(YEAR(TODAY()), MONTH(TODAY()), Metrica!$C13), CONCATENATE(DATA!$A$2:$A$1036, DATA!$D$2:$D$1036), 0)), "")} -> 13 | F13: {=IFERROR(INDEX(DATA!$G$2:$G$1036, MATCH(CONCATENATE(YEAR(TODAY()), MONTH(TODAY()), Metrica!$C13), CONCATENATE(DATA!$A$2:$A$1036, DATA!$D$2:$D$1036), 0)), "")} -> 9 | G13: {=IFERROR(INDEX(DATA!$Q$2:$Q$1036, MATCH(CONCATENATE(YEAR(TODAY()), MONTH(TODAY()-31), Metrica!$C13), CONCATENATE(DATA!$A$2:$A$1036, DATA!$D$2:$D$1036), 0)), 0)} -> 16859504 | H13: {=IFERROR(INDEX(DATA!$Q$2:$Q$1036, MATCH(CONCATENATE(YEAR(TODAY()), MONTH(TODAY()), Metrica!$C13), CONCATENATE(DATA!$A$2:$A$1036, DATA!$D$2:$D$1036), 0)), 0)} -> 15173582 | I13: {=IFERROR(INDEX(DATA!$H$2:$H$1036, MATCH(CONCATENATE(YEAR(TODAY()), MONTH(TODAY()), Metrica!$C13), CONCATENATE(DATA!$A$2:$A$1036, DATA!$D$2:$D$1036), 0)), 0)} -> 1685922 | J13: {=IFERROR(INDEX(DATA!$I$2:$I$1036, MATCH(CONCATENATE(YEAR(TODAY()), MONTH(TODAY()), Metrica!$C13), CONCATENATE(DATA!$A$2:$A$1036, DATA!$D$2:$D$1036), 0)), 0)} -> 257568.73 | K13: {=IFERROR(INDEX(DATA!$L$2:$L$1036, MATCH(CONCATENATE(YEAR(TODAY()), MONTH(TODAY()), Metrica!$C13), CONCATENATE(DATA!$A$2:$A$1036, DATA!$D$2:$D$1036), 0)), 0)} -> 0 | L13: {=IFERROR(INDEX(DATA!$P$2:$P$1036, MATCH(CONCATENATE(YEAR(TODAY()), MONTH(TODAY()), Metrica!$C13), CONCATENATE(DATA!$A$2:$A$1036, DATA!$D$2:$D$1036), 0)), 0)} -> 1943490.7 | M13: {=IFERROR(INDEX(DATA!$R$2:$R$1036, MATCH(CONCATENATE(YEAR(TODAY()), MONTH(TODAY()), Metrica!$C13), CONCATENATE(DATA!$A$2:$A$1036, DATA!$D$2:$D$1036), 0)), 0)} -> 3 | N13: {=IFERROR(INDEX(DATA!$S$2:$S$1036, MATCH(CONCATENATE(YEAR(TODAY()), MONTH(TODAY()), Metrica!$C13), CONCATENATE(DATA!$A$2:$A$1036, DATA!$D$2:$D$1036), 0)), 0)} -> 0 | O13: {=IFERROR(IF(INDEX(DATA!$O$2:$O$1036,MATCH(CONCATENATE(YEAR(TODAY()), MONTH(TODAY()), Metrica!$C13), CONCATENATE(DATA!$A$2 $A$1036, DATA!$D$2:$D$1036), 0)) = 0,"",INDEX(DATA!$O$2:$O$1036,MATCH(CONCATENATE(YEAR(TODAY()), MONTH(TODAY()), Metrica!$C13), CONCATENATE(DATA!$A$2:$A$1036, DATA!$D$2:$D$1036), 0))),"")} | P13: {=IFERROR(INDEX(DATA!$U$2:$U$1036, MATCH(CONCATENATE(YEAR(TODAY()), MONTH(TODAY()), Metrica!$C13), CONCATENATE(DATA!$A$2:$A$1036, DATA!$D$2:$D$1036), 0)), 0)} -> PENDIENTE
A14: GLADYS JEANNETH CORREA RUEDA | B14: SERFINANZAS | C14: 121000638199 | D14: {=IFERROR(INDEX(DATA!$E$2:$E$1036, MATCH(CONCATENATE(YEAR(TODAY()), MONTH(TODAY()), Metrica!$C14), CONCATENATE(DATA!$A$2:$A$1036, DATA!$D$2:$D$1036), 0)), "")} -> 45545 | E14: {=IFERROR(INDEX(DATA!$F$2:$F$1036, MATCH(CONCATENATE(YEAR(TODAY()), MONTH(TODAY()), Metrica!$C14), CONCATENATE(DATA!$A$2:$A$1036, DATA!$D$2:$D$1036), 0)), "")} -> 30 | F14: {=IFERROR(INDEX(DATA!$G$2:$G$1036, MATCH(CONCATENATE(YEAR(TODAY()), MONTH(TODAY()), Metrica!$C14), CONCATENATE(DATA!$A$2:$A$1036, DATA!$D$2:$D$1036), 0)), "")} -> 30 | G14: {=IFERROR(INDEX(DATA!$Q$2:$Q$1036, MATCH(CONCATENATE(YEAR(TODAY()), MONTH(TODAY()-31), Metrica!$C14), CONCATENATE(DATA!$A$2:$A$1036, DATA!$D$2:$D$1036), 0)), 0)} -> 19644721 | H14: {=IFERROR(INDEX(DATA!$Q$2:$Q$1036, MATCH(CONCATENATE(YEAR(TODAY()), MONTH(TODAY()), Metrica!$C14), CONCATENATE(DATA!$A$2:$A$1036, DATA!$D$2:$D$1036), 0)), 0)} -> 19155132 | I14: {=IFERROR(INDEX(DATA!$H$2:$H$1036, MATCH(CONCATENATE(YEAR(TODAY()), MONTH(TODAY()), Metrica!$C14), CONCATENATE(DATA!$A$2:$A$1036, DATA!$D$2:$D$1036), 0)), 0)} -> 489588.41 | J14: {=IFERROR(INDEX(DATA!$I$2:$I$1036, MATCH(CONCATENATE(YEAR(TODAY()), MONTH(TODAY()), Metrica!$C14), CONCATENATE(DATA!$A$2:$A$1036, DATA!$D$2:$D$1036), 0)), 0)} -> 371285.23 | K14: {=IFERROR(INDEX(DATA!$L$2:$L$1036, MATCH(CONCATENATE(YEAR(TODAY()), MONTH(TODAY()), Metrica!$C14), CONCATENATE(DATA!$A$2:$A$1036, DATA!$D$2:$D$1036), 0)), 0)} -> 0 | L14: {=IFERROR(INDEX(DATA!$P$2:$P$1036, MATCH(CONCATENATE(YEAR(TODAY()), MONTH(TODAY()), Metrica!$C14), CONCATENATE(DATA!$A$2:$A$1036, DATA!$D$2:$D$1036), 0)), 0)} -> 860873.63 | M14: {=IFERROR(INDEX(DATA!$R$2:$R$1036, MATCH(CONCATENATE(YEAR(TODAY()), MONTH(TODAY()), Metrica!$C14), CONCATENATE(DATA!$A$2:$A$1036, DATA!$D$2:$D$1036), 0)), 0)} -> 24 | N14: {=IFERROR(INDEX(DATA!$S$2:$S$1036, MATCH(CONCATENATE(YEAR(TODAY()), MONTH(TODAY()), Metrica!$C14), CONCATENATE(DATA!$A$2:$A$1036, DATA!$D$2:$D$1036), 0)), 0)} -> 0 | O14: {=IFERROR(IF(INDEX(DATA!$O$2:$O$1036,MATCH(CONCATENATE(YEAR(TODAY()), MONTH(TODAY()), Metrica!$C14), CONCATENATE(DATA!$A$2 $A$1036, DATA!$D$2:$D$1036), 0)) = 0,"",INDEX(DATA!$O$2:$O$1036,MATCH(CONCATENATE(YEAR(TODAY()), MONTH(TODAY()), Metrica!$C14), CONCATENATE(DATA!$A$2:$A$1036, DATA!$D$2:$D$1036), 0))),"")} | P14: {=IFERROR(INDEX(DATA!$U$2:$U$1036, MATCH(CONCATENATE(YEAR(TODAY()), MONTH(TODAY()), Metrica!$C14), CONCATENATE(DATA!$A$2:$A$1036, DATA!$D$2:$D$1036), 0)), 0)} -> PENDIENTE
A15: LAMAR OPTICAL S.A.S | B15: SERFINANZAS | C15: 111000149294 | D15: {=IFERROR(INDEX(DATA!$E$2:$E$1036, MATCH(CONCATENATE(YEAR(TODAY()), MONTH(TODAY()), Metrica!$C15), CONCATENATE(DATA!$A$2:$A$1036, DATA!$D$2:$D$1036), 0)), "")} -> 45547 | E15: {=IFERROR(INDEX(DATA!$F$2:$F$1036, MATCH(CONCATENATE(YEAR(TODAY()), MONTH(TODAY()), Metrica!$C15), CONCATENATE(DATA!$A$2:$A$1036, DATA!$D$2:$D$1036), 0)), "")} -> 35 | F15: {=IFERROR(INDEX(DATA!$G$2:$G$1036, MATCH(CONCATENATE(YEAR(TODAY()), MONTH(TODAY()), Metrica!$C15), CONCATENATE(DATA!$A$2:$A$1036, DATA!$D$2:$D$1036), 0)), "")} -> 1 | G15: {=IFERROR(INDEX(DATA!$Q$2:$Q$1036, MATCH(CONCATENATE(YEAR(TODAY()), MONTH(TODAY()-31), Metrica!$C15), CONCATENATE(DATA!$A$2:$A$1036, DATA!$D$2:$D$1036), 0)), 0)} -> 27948785 | H15: {=IFERROR(INDEX(DATA!$Q$2:$Q$1036, MATCH(CONCATENATE(YEAR(TODAY()), MONTH(TODAY()), Metrica!$C15), CONCATENATE(DATA!$A$2:$A$1036, DATA!$D$2:$D$1036), 0)), 0)} -> 22998688 | I15: {=IFERROR(INDEX(DATA!$H$2:$H$1036, MATCH(CONCATENATE(YEAR(TODAY()), MONTH(TODAY()), Metrica!$C15), CONCATENATE(DATA!$A$2:$A$1036, DATA!$D$2:$D$1036), 0)), 0)} -> 4950096.4 | J15: {=IFERROR(INDEX(DATA!$I$2:$I$1036, MATCH(CONCATENATE(YEAR(TODAY()), MONTH(TODAY()), Metrica!$C15), CONCATENATE(DATA!$A$2:$A$1036, DATA!$D$2:$D$1036), 0)), 0)} -> 146692.96 | K15: {=IFERROR(INDEX(DATA!$L$2:$L$1036, MATCH(CONCATENATE(YEAR(TODAY()), MONTH(TODAY()), Metrica!$C15), CONCATENATE(DATA!$A$2:$A$1036, DATA!$D$2:$D$1036), 0)), 0)} -> 0 | L15: {=IFERROR(INDEX(DATA!$P$2:$P$1036, MATCH(CONCATENATE(YEAR(TODAY()), MONTH(TODAY()), Metrica!$C15), CONCATENATE(DATA!$A$2:$A$1036, DATA!$D$2:$D$1036), 0)), 0)} -> 5096789.4 | M15: {=IFERROR(INDEX(DATA!$R$2:$R$1036, MATCH(CONCATENATE(YEAR(TODAY()), MONTH(TODAY()), Metrica!$C15), CONCATENATE(DATA!$A$2:$A$1036, DATA!$D$2:$D$1036), 0)), 0)} -> 22 | N15: {=IFERROR(INDEX(DATA!$S$2:$S$1036, MATCH(CONCATENATE(YEAR(TODAY()), MONTH(TODAY()), Metrica!$C15), CONCATENATE(DATA!$A$2:$A$1036, DATA!$D$2:$D$1036), 0)), 0)} -> 0 | O15: {=IFERROR(IF(INDEX(DATA!$O$2:$O$1036,MATCH(CONCATENATE(YEAR(TODAY()), MONTH(TODAY()), Metrica!$C15), CONCATENATE(DATA!$A$2 $A$1036, DATA!$D$2:$D$1036), 0)) = 0,"",INDEX(DATA!$O$2:$O$1036,MATCH(CONCATENATE(YEAR(TODAY()), MONTH(TODAY()), Metrica!$C15), CONCATENATE(DATA!$A$2:$A$1036, DATA!$D$2:$D$1036), 0))),"")} | P15: {=IFERROR(INDEX(DATA!$U$2:$U$1036, MATCH(CONCATENATE(YEAR(TODAY()), MONTH(TODAY()), Metrica!$C15), CONCATENATE(DATA!$A$2:$A$1036, DATA!$D$2:$D$1036), 0)), 0)} -> PENDIENTE
A16: LAMAR OPTICAL S.A.S | B16: SERFINANZAS | C16: 111000194208 | D16: {=IFERROR(INDEX(DATA!$E$2:$E$1036, MATCH(CONCATENATE(YEAR(TODAY()), MONTH(TODAY()), Metrica!$C16), CONCATENATE(DATA!$A$2:$A$1036, DATA!$D$2:$D$1036), 0)), "")} -> 45560 | E16: {=IFERROR(INDEX(DATA!$F$2:$F$1036, MATCH(CONCATENATE(YEAR(TODAY()), MONTH(TODAY()), Metrica!$C16), CONCATENATE(DATA!$A$2:$A$1036, DATA!$D$2:$D$1036), 0)), "")} -> 23 | F16: {=IFERROR(INDEX(DATA!$G$2:$G$1036, MATCH(CONCATENATE(YEAR(TODAY()), MONTH(TODAY()), Metrica!$C16), CONCATENATE(DATA!$A$2:$A$1036, DATA!$D$2:$D$1036), 0)), "")} -> 13 | G16: {=IFERROR(INDEX(DATA!$Q$2:$Q$1036, MATCH(CONCATENATE(YEAR(TODAY()), MONTH(TODAY()-31), Metrica!$C16), CONCATENATE(DATA!$A$2:$A$1036, DATA!$D$2:$D$1036), 0)), 0)} -> 35960145 | H16: {=IFERROR(INDEX(DATA!$Q$2:$Q$1036, MATCH(CONCATENATE(YEAR(TODAY()), MONTH(TODAY()), Metrica!$C16), CONCATENATE(DATA!$A$2:$A$1036, DATA!$D$2:$D$1036), 0)), 0)} -> 33691408 | I16: {=IFERROR(INDEX(DATA!$H$2:$H$1036, MATCH(CONCATENATE(YEAR(TODAY()), MONTH(TODAY()), Metrica!$C16), CONCATENATE(DATA!$A$2:$A$1036, DATA!$D$2:$D$1036), 0)), 0)} -> 2268737 | J16: {=IFERROR(INDEX(DATA!$I$2:$I$1036, MATCH(CONCATENATE(YEAR(TODAY()), MONTH(TODAY()), Metrica!$C16), CONCATENATE(DATA!$A$2:$A$1036, DATA!$D$2:$D$1036), 0)), 0)} -> 636335.29 | K16: {=IFERROR(INDEX(DATA!$L$2:$L$1036, MATCH(CONCATENATE(YEAR(TODAY()), MONTH(TODAY()), Metrica!$C16), CONCATENATE(DATA!$A$2:$A$1036, DATA!$D$2:$D$1036), 0)), 0)} -> 0 | L16: {=IFERROR(INDEX(DATA!$P$2:$P$1036, MATCH(CONCATENATE(YEAR(TODAY()), MONTH(TODAY()), Metrica!$C16), CONCATENATE(DATA!$A$2:$A$1036, DATA!$D$2:$D$1036), 0)), 0)} -> 2905072.3 | M16: {=IFERROR(INDEX(DATA!$R$2:$R$1036, MATCH(CONCATENATE(YEAR(TODAY()), MONTH(TODAY()), Metrica!$C16), CONCATENATE(DATA!$A$2:$A$1036, DATA!$D$2:$D$1036), 0)), 0)} -> 9 | N16: {=IFERROR(INDEX(DATA!$S$2:$S$1036, MATCH(CONCATENATE(YEAR(TODAY()), MONTH(TODAY()), Metrica!$C16), CONCATENATE(DATA!$A$2:$A$1036, DATA!$D$2:$D$1036), 0)), 0)} -> 0 | O16: {=IFERROR(IF(INDEX(DATA!$O$2:$O$1036,MATCH(CONCATENATE(YEAR(TODAY()), MONTH(TODAY()), Metrica!$C16), CONCATENATE(DATA!$A$2 $A$1036, DATA!$D$2:$D$1036), 0)) = 0,"",INDEX(DATA!$O$2:$O$1036,MATCH(CONCATENATE(YEAR(TODAY()), MONTH(TODAY()), Metrica!$C16), CONCATENATE(DATA!$A$2:$A$1036, DATA!$D$2:$D$1036), 0))),"")} | P16: {=IFERROR(INDEX(DATA!$U$2:$U$1036, MATCH(CONCATENATE(YEAR(TODAY()), MONTH(TODAY()), Metrica!$C16), CONCATENATE(DATA!$A$2:$A$1036, DATA!$D$2:$D$1036), 0)), 0)} -> PENDIENTE
A17: GLADYS JEANNETH CORREA RUEDA | B17: DAVIVIENDA | C17: 5.904046e+15 | D17: {=IFERROR(INDEX(DATA!$E$2:$E$1036, MATCH(CONCATENATE(YEAR(TODAY()), MONTH(TODAY()), Metrica!$C17), CONCATENATE(DATA!$A$2:$A$1036, DATA!$D$2:$D$1036), 0)), "")} -> 45550 | E17: {=IFERROR(INDEX(DATA!$F$2:$F$1036, MATCH(CONCATENATE(YEAR(TODAY()), MONTH(TODAY()), Metrica!$C17), CONCATENATE(DATA!$A$2:$A$1036, DATA!$D$2:$D$1036), 0)), "")} -> 45 | F17: {=IFERROR(INDEX(DATA!$G$2:$G$1036, MATCH(CONCATENATE(YEAR(TODAY()), MONTH(TODAY()), Metrica!$C17), CONCATENATE(DATA!$A$2:$A$1036, DATA!$D$2:$D$1036), 0)), "")} -> 75 | G17: {=IFERROR(INDEX(DATA!$Q$2:$Q$1036, MATCH(CONCATENATE(YEAR(TODAY()), MONTH(TODAY()-31), Metrica!$C17), CONCATENATE(DATA!$A$2:$A$1036, DATA!$D$2:$D$1036), 0)), 0)} -> 47853611 | H17: {=IFERROR(INDEX(DATA!$Q$2:$Q$1036, MATCH(CONCATENATE(YEAR(TODAY()), MONTH(TODAY()), Metrica!$C17), CONCATENATE(DATA!$A$2:$A$1036, DATA!$D$2:$D$1036), 0)), 0)} -> 47253917 | I17: {=IFERROR(INDEX(DATA!$H$2:$H$1036, MATCH(CONCATENATE(YEAR(TODAY()), MONTH(TODAY()), Metrica!$C17), CONCATENATE(DATA!$A$2:$A$1036, DATA!$D$2:$D$1036), 0)), 0)} -> 599694.1 | J17: {=IFERROR(INDEX(DATA!$I$2:$I$1036, MATCH(CONCATENATE(YEAR(TODAY()), MONTH(TODAY()), Metrica!$C17), CONCATENATE(DATA!$A$2:$A$1036, DATA!$D$2:$D$1036), 0)), 0)} -> 371072.86 | K17: {=IFERROR(INDEX(DATA!$L$2:$L$1036, MATCH(CONCATENATE(YEAR(TODAY()), MONTH(TODAY()), Metrica!$C17), CONCATENATE(DATA!$A$2:$A$1036, DATA!$D$2:$D$1036), 0)), 0)} -> 0 | L17: {=IFERROR(INDEX(DATA!$P$2:$P$1036, MATCH(CONCATENATE(YEAR(TODAY()), MONTH(TODAY()), Metrica!$C17), CONCATENATE(DATA!$A$2:$A$1036, DATA!$D$2:$D$1036), 0)), 0)} -> 970766.96 | M17: {=IFERROR(INDEX(DATA!$R$2:$R$1036, MATCH(CONCATENATE(YEAR(TODAY()), MONTH(TODAY()), Metrica!$C17), CONCATENATE(DATA!$A$2:$A$1036, DATA!$D$2:$D$1036), 0)), 0)} -> -12 | N17: {=IFERROR(INDEX(DATA!$S$2:$S$1036, MATCH(CONCATENATE(YEAR(TODAY()), MONTH(TODAY()), Metrica!$C17), CONCATENATE(DATA!$A$2:$A$1036, DATA!$D$2:$D$1036), 0)), 0)} -> 0 | O17: {=IFERROR(IF(INDEX(DATA!$O$2:$O$1036,MATCH(CONCATENATE(YEAR(TODAY()), MONTH(TODAY()), Metrica!$C17), CONCATENATE(DATA!$A$2 $A$1036, DATA!$D$2:$D$1036), 0)) = 0,"",INDEX(DATA!$O$2:$O$1036,MATCH(CONCATENATE(YEAR(TODAY()), MONTH(TODAY()), Metrica!$C17), CONCATENATE(DATA!$A$2:$A$1036, DATA!$D$2:$D$1036), 0))),"")} | P17: {=IFERROR(INDEX(DATA!$U$2:$U$1036, MATCH(CONCATENATE(YEAR(TODAY()), MONTH(TODAY()), Metrica!$C17), CONCATENATE(DATA!$A$2:$A$1036, DATA!$D$2:$D$1036), 0)), 0)} -> PENDIENTE
A18: LAMAR OPTICAL S.A.S | B18: BANCOLOMBIA | C18: 8140099327 | D18: {=IFERROR(INDEX(DATA!$E$2:$E$1036, MATCH(CONCATENATE(YEAR(TODAY()), MONTH(TODAY()), Metrica!$C18), CONCATENATE(DATA!$A$2:$A$1036, DATA!$D$2:$D$1036), 0)), "")} | E18: {=IFERROR(INDEX(DATA!$F$2:$F$1036, MATCH(CONCATENATE(YEAR(TODAY()), MONTH(TODAY()), Metrica!$C18), CONCATENATE(DATA!$A$2:$A$1036, DATA!$D$2:$D$1036), 0)), "")} | F18: {=IFERROR(INDEX(DATA!$G$2:$G$1036, MATCH(CONCATENATE(YEAR(TODAY()), MONTH(TODAY()), Metrica!$C18), CONCATENATE(DATA!$A$2:$A$1036, DATA!$D$2:$D$1036), 0)), "")} | G18: {=IFERROR(INDEX(DATA!$Q$2:$Q$1036, MATCH(CONCATENATE(YEAR(TODAY()), MONTH(TODAY()-31), Metrica!$C18), CONCATENATE(DATA!$A$2:$A$1036, DATA!$D$2:$D$1036), 0)), 0)} -> 63750000 | H18: {=IFERROR(INDEX(DATA!$Q$2:$Q$1036, MATCH(CONCATENATE(YEAR(TODAY()), MONTH(TODAY()), Metrica!$C18), CONCATENATE(DATA!$A$2:$A$1036, DATA!$D$2:$D$1036), 0)), 0)} -> 0 | I18: {=IFERROR(INDEX(DATA!$H$2:$H$1036, MATCH(CONCATENATE(YEAR(TODAY()), MONTH(TODAY()), Metrica!$C18), CONCATENATE(DATA!$A$2:$A$1036, DATA!$D$2:$D$1036), 0)), 0)} -> 0 | J18: {=IFERROR(INDEX(DATA!$I$2:$I$1036, MATCH(CONCATENATE(YEAR(TODAY()), MONTH(TODAY()), Metrica!$C18), CONCATENATE(DATA!$A$2:$A$1036, DATA!$D$2:$D$1036), 0)), 0)} -> 0 | K18: {=IFERROR(INDEX(DATA!$L$2:$L$1036, MATCH(CONCATENATE(YEAR(TODAY()), MONTH(TODAY()), Metrica!$C18), CONCATENATE(DATA!$A$2:$A$1036, DATA!$D$2:$D$1036), 0)), 0)} -> 0 | L18: {=IFERROR(INDEX(DATA!$P$2:$P$1036, MATCH(CONCATENATE(YEAR(TODAY()), MONTH(TODAY()), Metrica!$C18), CONCATENATE(DATA!$A$2:$A$1036, DATA!$D$2:$D$1036), 0)), 0)} -> 0 | M18: {=IFERROR(INDEX(DATA!$R$2:$R$1036, MATCH(CONCATENATE(YEAR(TODAY()), MONTH(TODAY()), Metrica!$C18), CONCATENATE(DATA!$A$2:$A$1036, DATA!$D$2:$D$1036), 0)), 0)} -> 0 | N18: {=IFERROR(INDEX(DATA!$S$2:$S$1036, MATCH(CONCATENATE(YEAR(TODAY()), MONTH(TODAY()), Metrica!$C18), CONCATENATE(DATA!$A$2:$A$1036, DATA!$D$2:$D$1036), 0)), 0)} -> 0 | O18: {=IFERROR(IF(INDEX(DATA!$O$2:$O$1036,MATCH(CONCATENATE(YEAR(TODAY()), MONTH(TODAY()), Metrica!$C18), CONCATENATE(DATA!$A$2 $A$1036, DATA!$D$2:$D$1036), 0)) = 0,"",INDEX(DATA!$O$2:$O$1036,MATCH(CONCATENATE(YEAR(TODAY()), MONTH(TODAY()), Metrica!$C18), CONCATENATE(DATA!$A$2:$A$1036, DATA!$D$2:$D$1036), 0))),"")} | P18: {=IFERROR(INDEX(DATA!$U$2:$U$1036, MATCH(CONCATENATE(YEAR(TODAY()), MONTH(TODAY()), Metrica!$C18), CONCATENATE(DATA!$A$2:$A$1036, DATA!$D$2:$D$1036), 0)), 0)} -> 0
A19: INVERSIONES RUEDA S.A.S | B19: DAVIVIENDA | C19: 7104046002627555 | D19: {=IFERROR(INDEX(DATA!$E$2:$E$1036, MATCH(CONCATENATE(YEAR(TODAY()), MONTH(TODAY()), Metrica!$C19), CONCATENATE(DATA!$A$2:$A$1036, DATA!$D$2:$D$1036), 0)), "")} -> 45565 | E19: {=IFERROR(INDEX(DATA!$F$2:$F$1036, MATCH(CONCATENATE(YEAR(TODAY()), MONTH(TODAY()), Metrica!$C19), CONCATENATE(DATA!$A$2:$A$1036, DATA!$D$2:$D$1036), 0)), "")} -> 13 | F19: {=IFERROR(INDEX(DATA!$G$2:$G$1036, MATCH(CONCATENATE(YEAR(TODAY()), MONTH(TODAY()), Metrica!$C19), CONCATENATE(DATA!$A$2:$A$1036, DATA!$D$2:$D$1036), 0)), "")} -> 23 | G19: {=IFERROR(INDEX(DATA!$Q$2:$Q$1036, MATCH(CONCATENATE(YEAR(TODAY()), MONTH(TODAY()-31), Metrica!$C19), CONCATENATE(DATA!$A$2:$A$1036, DATA!$D$2:$D$1036), 0)), 0)} -> 68666667 | H19: {=IFERROR(INDEX(DATA!$Q$2:$Q$1036, MATCH(CONCATENATE(YEAR(TODAY()), MONTH(TODAY()), Metrica!$C19), CONCATENATE(DATA!$A$2:$A$1036, DATA!$D$2:$D$1036), 0)), 0)} -> 65805556 | I19: {=IFERROR(INDEX(DATA!$H$2:$H$1036, MATCH(CONCATENATE(YEAR(TODAY()), MONTH(TODAY()), Metrica!$C19), CONCATENATE(DATA!$A$2:$A$1036, DATA!$D$2:$D$1036), 0)), 0)} -> 2861111.1 | J19: {=IFERROR(INDEX(DATA!$I$2:$I$1036, MATCH(CONCATENATE(YEAR(TODAY()), MONTH(TODAY()), Metrica!$C19), CONCATENATE(DATA!$A$2:$A$1036, DATA!$D$2:$D$1036), 0)), 0)} -> 1602615.9 | K19: {=IFERROR(INDEX(DATA!$L$2:$L$1036, MATCH(CONCATENATE(YEAR(TODAY()), MONTH(TODAY()), Metrica!$C19), CONCATENATE(DATA!$A$2:$A$1036, DATA!$D$2:$D$1036), 0)), 0)} -> 0 | L19: {=IFERROR(INDEX(DATA!$P$2:$P$1036, MATCH(CONCATENATE(YEAR(TODAY()), MONTH(TODAY()), Metrica!$C19), CONCATENATE(DATA!$A$2:$A$1036, DATA!$D$2:$D$1036), 0)), 0)} -> 4463727 | M19: {=IFERROR(INDEX(DATA!$R$2:$R$1036, MATCH(CONCATENATE(YEAR(TODAY()), MONTH(TODAY()), Metrica!$C19), CONCATENATE(DATA!$A$2:$A$1036, DATA!$D$2:$D$1036), 0)), 0)} -> 4 | N19: {=IFERROR(INDEX(DATA!$S$2:$S$1036, MATCH(CONCATENATE(YEAR(TODAY()), MONTH(TODAY()), Metrica!$C19), CONCATENATE(DATA!$A$2:$A$1036, DATA!$D$2:$D$1036), 0)), 0)} -> 0 | O19: {=IFERROR(IF(INDEX(DATA!$O$2:$O$1036,MATCH(CONCATENATE(YEAR(TODAY()), MONTH(TODAY()), Metrica!$C19), CONCATENATE(DATA!$A$2 $A$1036, DATA!$D$2:$D$1036), 0)) = 0,"",INDEX(DATA!$O$2:$O$1036,MATCH(CONCATENATE(YEAR(TODAY()), MONTH(TODAY()), Metrica!$C19), CONCATENATE(DATA!$A$2:$A$1036, DATA!$D$2:$D$1036), 0))),"")} | P19: {=IFERROR(INDEX(DATA!$U$2:$U$1036, MATCH(CONCATENATE(YEAR(TODAY()), MONTH(TODAY()), Metrica!$C19), CONCATENATE(DATA!$A$2:$A$1036, DATA!$D$2:$D$1036), 0)), 0)} -> PENDIENTE
A20: INVERSIONES RUEDA S.A.S | B20: BANCOLOMBIA | C20: 8140098558 | D20: {=IFERROR(INDEX(DATA!$E$2:$E$1036, MATCH(CONCATENATE(YEAR(TODAY()), MONTH(TODAY()), Metrica!$C20), CONCATENATE(DATA!$A$2:$A$1036, DATA!$D$2:$D$1036), 0)), "")} -> 45565 | E20: {=IFERROR(INDEX(DATA!$F$2:$F$1036, MATCH(CONCATENATE(YEAR(TODAY()), MONTH(TODAY()), Metrica!$C20), CONCATENATE(DATA!$A$2:$A$1036, DATA!$D$2:$D$1036), 0)), "")} -> 13 | F20: {=IFERROR(INDEX(DATA!$G$2:$G$1036, MATCH(CONCATENATE(YEAR(TODAY()), MONTH(TODAY()), Metrica!$C20), CONCATENATE(DATA!$A$2:$A$1036, DATA!$D$2:$D$1036), 0)), "")} -> 35 | G20: {=IFERROR(INDEX(DATA!$Q$2:$Q$1036, MATCH(CONCATENATE(YEAR(TODAY()), MONTH(TODAY()-31), Metrica!$C20), CONCATENATE(DATA!$A$2:$A$1036, DATA!$D$2:$D$1036), 0)), 0)} -> 89292327 | H20: {=IFERROR(INDEX(DATA!$Q$2:$Q$1036, MATCH(CONCATENATE(YEAR(TODAY()), MONTH(TODAY()), Metrica!$C20), CONCATENATE(DATA!$A$2:$A$1036, DATA!$D$2:$D$1036), 0)), 0)} -> 86825325 | I20: {=IFERROR(INDEX(DATA!$H$2:$H$1036, MATCH(CONCATENATE(YEAR(TODAY()), MONTH(TODAY()), Metrica!$C20), CONCATENATE(DATA!$A$2:$A$1036, DATA!$D$2:$D$1036), 0)), 0)} -> 2467002 | J20: {=IFERROR(INDEX(DATA!$I$2:$I$1036, MATCH(CONCATENATE(YEAR(TODAY()), MONTH(TODAY()), Metrica!$C20), CONCATENATE(DATA!$A$2:$A$1036, DATA!$D$2:$D$1036), 0)), 0)} -> 1803311.3 | K20: {=IFERROR(INDEX(DATA!$L$2:$L$1036, MATCH(CONCATENATE(YEAR(TODAY()), MONTH(TODAY()), Metrica!$C20), CONCATENATE(DATA!$A$2:$A$1036, DATA!$D$2:$D$1036), 0)), 0)} -> 0 | L20: {=IFERROR(INDEX(DATA!$P$2:$P$1036, MATCH(CONCATENATE(YEAR(TODAY()), MONTH(TODAY()), Metrica!$C20), CONCATENATE(DATA!$A$2:$A$1036, DATA!$D$2:$D$1036), 0)), 0)} -> 4270313.3 | M20: {=IFERROR(INDEX(DATA!$R$2:$R$1036, MATCH(CONCATENATE(YEAR(TODAY()), MONTH(TODAY()), Metrica!$C20), CONCATENATE(DATA!$A$2:$A$1036, DATA!$D$2:$D$1036), 0)), 0)} -> 3 | N20: {=IFERROR(INDEX(DATA!$S$2:$S$1036, MATCH(CONCATENATE(YEAR(TODAY()), MONTH(TODAY()), Metrica!$C20), CONCATENATE(DATA!$A$2:$A$1036, DATA!$D$2:$D$1036), 0)), 0)} -> 0 | O20: {=IFERROR(IF(INDEX(DATA!$O$2:$O$1036,MATCH(CONCATENATE(YEAR(TODAY()), MONTH(TODAY()), Metrica!$C20), CONCATENATE(DATA!$A$2 $A$1036, DATA!$D$2:$D$1036), 0)) = 0,"",INDEX(DATA!$O$2:$O$1036,MATCH(CONCATENATE(YEAR(TODAY()), MONTH(TODAY()), Metrica!$C20), CONCATENATE(DATA!$A$2:$A$1036, DATA!$D$2:$D$1036), 0))),"")} | P20: {=IFERROR(INDEX(DATA!$U$2:$U$1036, MATCH(CONCATENATE(YEAR(TODAY()), MONTH(TODAY()), Metrica!$C20), CONCATENATE(DATA!$A$2:$A$1036, DATA!$D$2:$D$1036), 0)), 0)} -> PENDIENTE
A21: LAMAR OPTICAL S.A.S | B21: BANCOLDEX | C21: 5000100411250008 | D21: {=IFERROR(INDEX(DATA!$E$2:$E$1036, MATCH(CONCATENATE(YEAR(TODAY()), MONTH(TODAY()), Metrica!$C21), CONCATENATE(DATA!$A$2:$A$1036, DATA!$D$2:$D$1036), 0)), "")} -> 45549 | E21: {=IFERROR(INDEX(DATA!$F$2:$F$1036, MATCH(CONCATENATE(YEAR(TODAY()), MONTH(TODAY()), Metrica!$C21), CONCATENATE(DATA!$A$2:$A$1036, DATA!$D$2:$D$1036), 0)), "")} -> 24 | F21: {=IFERROR(INDEX(DATA!$G$2:$G$1036, MATCH(CONCATENATE(YEAR(TODAY()), MONTH(TODAY()), Metrica!$C21), CONCATENATE(DATA!$A$2:$A$1036, DATA!$D$2:$D$1036), 0)), "")} -> 12 | G21: {=IFERROR(INDEX(DATA!$Q$2:$Q$1036, MATCH(CONCATENATE(YEAR(TODAY()), MONTH(TODAY()-31), Metrica!$C21), CONCATENATE(DATA!$A$2:$A$1036, DATA!$D$2:$D$1036), 0)), 0)} -> 98484840 | H21: {=IFERROR(INDEX(DATA!$Q$2:$Q$1036, MATCH(CONCATENATE(YEAR(TODAY()), MONTH(TODAY()), Metrica!$C21), CONCATENATE(DATA!$A$2:$A$1036, DATA!$D$2:$D$1036), 0)), 0)} -> 90909082 | I21: {=IFERROR(INDEX(DATA!$H$2:$H$1036, MATCH(CONCATENATE(YEAR(TODAY()), MONTH(TODAY()), Metrica!$C21), CONCATENATE(DATA!$A$2:$A$1036, DATA!$D$2:$D$1036), 0)), 0)} -> 7575758 | J21: {=IFERROR(INDEX(DATA!$I$2:$I$1036, MATCH(CONCATENATE(YEAR(TODAY()), MONTH(TODAY()), Metrica!$C21), CONCATENATE(DATA!$A$2:$A$1036, DATA!$D$2:$D$1036), 0)), 0)} -> 1131838.8 | K21: {=IFERROR(INDEX(DATA!$L$2:$L$1036, MATCH(CONCATENATE(YEAR(TODAY()), MONTH(TODAY()), Metrica!$C21), CONCATENATE(DATA!$A$2:$A$1036, DATA!$D$2:$D$1036), 0)), 0)} -> 0 | L21: {=IFERROR(INDEX(DATA!$P$2:$P$1036, MATCH(CONCATENATE(YEAR(TODAY()), MONTH(TODAY()), Metrica!$C21), CONCATENATE(DATA!$A$2:$A$1036, DATA!$D$2:$D$1036), 0)), 0)} -> 8777439.1 | M21: {=IFERROR(INDEX(DATA!$R$2:$R$1036, MATCH(CONCATENATE(YEAR(TODAY()), MONTH(TODAY()), Metrica!$C21), CONCATENATE(DATA!$A$2:$A$1036, DATA!$D$2:$D$1036), 0)), 0)} -> 20 | N21: {=IFERROR(INDEX(DATA!$S$2:$S$1036, MATCH(CONCATENATE(YEAR(TODAY()), MONTH(TODAY()), Metrica!$C21), CONCATENATE(DATA!$A$2:$A$1036, DATA!$D$2:$D$1036), 0)), 0)} -> 0 | O21: {=IFERROR(IF(INDEX(DATA!$O$2:$O$1036,MATCH(CONCATENATE(YEAR(TODAY()), MONTH(TODAY()), Metrica!$C21), CONCATENATE(DATA!$A$2 $A$1036, DATA!$D$2:$D$1036), 0)) = 0,"",INDEX(DATA!$O$2:$O$1036,MATCH(CONCATENATE(YEAR(TODAY()), MONTH(TODAY()), Metrica!$C21), CONCATENATE(DATA!$A$2:$A$1036, DATA!$D$2:$D$1036), 0))),"")} | P21: {=IFERROR(INDEX(DATA!$U$2:$U$1036, MATCH(CONCATENATE(YEAR(TODAY()), MONTH(TODAY()), Metrica!$C21), CONCATENATE(DATA!$A$2:$A$1036, DATA!$D$2:$D$1036), 0)), 0)} -> PENDIENTE
A22: INVERSIONES RUEDA S.A.S | B22: BANCOLOMBIA | C22: 8140098557 | D22: {=IFERROR(INDEX(DATA!$E$2:$E$1036, MATCH(CONCATENATE(YEAR(TODAY()), MONTH(TODAY()), Metrica!$C22), CONCATENATE(DATA!$A$2:$A$1036, DATA!$D$2:$D$1036), 0)), "")} -> 45565 | E22: {=IFERROR(INDEX(DATA!$F$2:$F$1036, MATCH(CONCATENATE(YEAR(TODAY()), MONTH(TODAY()), Metrica!$C22), CONCATENATE(DATA!$A$2:$A$1036, DATA!$D$2:$D$1036), 0)), "")} -> 13 | F22: {=IFERROR(INDEX(DATA!$G$2:$G$1036, MATCH(CONCATENATE(YEAR(TODAY()), MONTH(TODAY()), Metrica!$C22), CONCATENATE(DATA!$A$2:$A$1036, DATA!$D$2:$D$1036), 0)), "")} -> 25 | G22: {=IFERROR(INDEX(DATA!$Q$2:$Q$1036, MATCH(CONCATENATE(YEAR(TODAY()), MONTH(TODAY()-31), Metrica!$C22), CONCATENATE(DATA!$A$2:$A$1036, DATA!$D$2:$D$1036), 0)), 0)} -> 1.0956986e+08 | H22: {=IFERROR(INDEX(DATA!$Q$2:$Q$1036, MATCH(CONCATENATE(YEAR(TODAY()), MONTH(TODAY()), Metrica!$C22), CONCATENATE(DATA!$A$2:$A$1036, DATA!$D$2:$D$1036), 0)), 0)} -> 1.0535564e+08 | I22: {=IFERROR(INDEX(DATA!$H$2:$H$1036, MATCH(CONCATENATE(YEAR(TODAY()), MONTH(TODAY()), Metrica!$C22), CONCATENATE(DATA!$A$2:$A$1036, DATA!$D$2:$D$1036), 0)), 0)} -> 4214225 | J22: {=IFERROR(INDEX(DATA!$I$2:$I$1036, MATCH(CONCATENATE(YEAR(TODAY()), MONTH(TODAY()), Metrica!$C22), CONCATENATE(DATA!$A$2:$A$1036, DATA!$D$2:$D$1036), 0)), 0)} -> 1765262.5 | K22: {=IFERROR(INDEX(DATA!$L$2:$L$1036, MATCH(CONCATENATE(YEAR(TODAY()), MONTH(TODAY()), Metrica!$C22), CONCATENATE(DATA!$A$2:$A$1036, DATA!$D$2:$D$1036), 0)), 0)} -> 0 | L22: {=IFERROR(INDEX(DATA!$P$2:$P$1036, MATCH(CONCATENATE(YEAR(TODAY()), MONTH(TODAY()), Metrica!$C22), CONCATENATE(DATA!$A$2:$A$1036, DATA!$D$2:$D$1036), 0)), 0)} -> 5979487.5 | M22: {=IFERROR(INDEX(DATA!$R$2:$R$1036, MATCH(CONCATENATE(YEAR(TODAY()), MONTH(TODAY()), Metrica!$C22), CONCATENATE(DATA!$A$2:$A$1036, DATA!$D$2:$D$1036), 0)), 0)} -> 3 | N22: {=IFERROR(INDEX(DATA!$S$2:$S$1036, MATCH(CONCATENATE(YEAR(TODAY()), MONTH(TODAY()), Metrica!$C22), CONCATENATE(DATA!$A$2:$A$1036, DATA!$D$2:$D$1036), 0)), 0)} -> 0 | O22: {=IFERROR(IF(INDEX(DATA!$O$2:$O$1036,MATCH(CONCATENATE(YEAR(TODAY()), MONTH(TODAY()), Metrica!$C22), CONCATENATE(DATA!$A$2 $A$1036, DATA!$D$2:$D$1036), 0)) = 0,"",INDEX(DATA!$O$2:$O$1036,MATCH(CONCATENATE(YEAR(TODAY()), MONTH(TODAY()), Metrica!$C22), CONCATENATE(DATA!$A$2:$A$1036, DATA!$D$2:$D$1036), 0))),"")} | P22: {=IFERROR(INDEX(DATA!$U$2:$U$1036, MATCH(CONCATENATE(YEAR(TODAY()), MONTH(TODAY()), Metrica!$C22), CONCATENATE(DATA!$A$2:$A$1036, DATA!$D$2:$D$1036), 0)), 0)} -> PENDIENTE
A23: LAMAR OPTICAL S.A.S | B23: BANCOLOMBIA | C23: 8140098501 | D23: {=IFERROR(INDEX(DATA!$E$2:$E$1036, MATCH(CONCATENATE(YEAR(TODAY()), MONTH(TODAY()), Metrica!$C23), CONCATENATE(DATA!$A$2:$A$1036, DATA!$D$2:$D$1036), 0)), "")} -> 45553 | E23: {=IFERROR(INDEX(DATA!$F$2:$F$1036, MATCH(CONCATENATE(YEAR(TODAY()), MONTH(TODAY()), Metrica!$C23), CONCATENATE(DATA!$A$2:$A$1036, DATA!$D$2:$D$1036), 0)), "")} -> 13 | F23: {=IFERROR(INDEX(DATA!$G$2:$G$1036, MATCH(CONCATENATE(YEAR(TODAY()), MONTH(TODAY()), Metrica!$C23), CONCATENATE(DATA!$A$2:$A$1036, DATA!$D$2:$D$1036), 0)), "")} -> 39 | G23: {=IFERROR(INDEX(DATA!$Q$2:$Q$1036, MATCH(CONCATENATE(YEAR(TODAY()), MONTH(TODAY()-31), Metrica!$C23), CONCATENATE(DATA!$A$2:$A$1036, DATA!$D$2:$D$1036), 0)), 0)} -> 1.478212e+08 | H23: {=IFERROR(INDEX(DATA!$Q$2:$Q$1036, MATCH(CONCATENATE(YEAR(TODAY()), MONTH(TODAY()), Metrica!$C23), CONCATENATE(DATA!$A$2:$A$1036, DATA!$D$2:$D$1036), 0)), 0)} -> 1.4412567e+08 | I23: {=IFERROR(INDEX(DATA!$H$2:$H$1036, MATCH(CONCATENATE(YEAR(TODAY()), MONTH(TODAY()), Metrica!$C23), CONCATENATE(DATA!$A$2:$A$1036, DATA!$D$2:$D$1036), 0)), 0)} -> 3695530.1 | J23: {=IFERROR(INDEX(DATA!$I$2:$I$1036, MATCH(CONCATENATE(YEAR(TODAY()), MONTH(TODAY()), Metrica!$C23), CONCATENATE(DATA!$A$2:$A$1036, DATA!$D$2:$D$1036), 0)), 0)} -> 2715996.5 | K23: {=IFERROR(INDEX(DATA!$L$2:$L$1036, MATCH(CONCATENATE(YEAR(TODAY()), MONTH(TODAY()), Metrica!$C23), CONCATENATE(DATA!$A$2:$A$1036, DATA!$D$2:$D$1036), 0)), 0)} -> 1350887.7 | L23: {=IFERROR(INDEX(DATA!$P$2:$P$1036, MATCH(CONCATENATE(YEAR(TODAY()), MONTH(TODAY()), Metrica!$C23), CONCATENATE(DATA!$A$2:$A$1036, DATA!$D$2:$D$1036), 0)), 0)} -> 7762414.3 | M23: {=IFERROR(INDEX(DATA!$R$2:$R$1036, MATCH(CONCATENATE(YEAR(TODAY()), MONTH(TODAY()), Metrica!$C23), CONCATENATE(DATA!$A$2:$A$1036, DATA!$D$2:$D$1036), 0)), 0)} -> -15 | N23: {=IFERROR(INDEX(DATA!$S$2:$S$1036, MATCH(CONCATENATE(YEAR(TODAY()), MONTH(TODAY()), Metrica!$C23), CONCATENATE(DATA!$A$2:$A$1036, DATA!$D$2:$D$1036), 0)), 0)} -> 0 | O23: {=IFERROR(IF(INDEX(DATA!$O$2:$O$1036,MATCH(CONCATENATE(YEAR(TODAY()), MONTH(TODAY()), Metrica!$C23), CONCATENATE(DATA!$A$2 $A$1036, DATA!$D$2:$D$1036), 0)) = 0,"",INDEX(DATA!$O$2:$O$1036,MATCH(CONCATENATE(YEAR(TODAY()), MONTH(TODAY()), Metrica!$C23), CONCATENATE(DATA!$A$2:$A$1036, DATA!$D$2:$D$1036), 0))),"")} | P23: {=IFERROR(INDEX(DATA!$U$2:$U$1036, MATCH(CONCATENATE(YEAR(TODAY()), MONTH(TODAY()), Metrica!$C23), CONCATENATE(DATA!$A$2:$A$1036, DATA!$D$2:$D$1036), 0)), 0)} -> PENDIENTE
A24: LAMAR OPTICAL S.A.S | B24: DAVIVIENDA | C24: 7104046002628157 | D24: {=IFERROR(INDEX(DATA!$E$2:$E$1036, MATCH(CONCATENATE(YEAR(TODAY()), MONTH(TODAY()), Metrica!$C24), CONCATENATE(DATA!$A$2:$A$1036, DATA!$D$2:$D$1036), 0)), "")} -> 45537 | E24: {=IFERROR(INDEX(DATA!$F$2:$F$1036, MATCH(CONCATENATE(YEAR(TODAY()), MONTH(TODAY()), Metrica!$C24), CONCATENATE(DATA!$A$2:$A$1036, DATA!$D$2:$D$1036), 0)), "")} -> 12 | F24: {=IFERROR(INDEX(DATA!$G$2:$G$1036, MATCH(CONCATENATE(YEAR(TODAY()), MONTH(TODAY()), Metrica!$C24), CONCATENATE(DATA!$A$2:$A$1036, DATA!$D$2:$D$1036), 0)), "")} -> 24 | G24: {=IFERROR(INDEX(DATA!$Q$2:$Q$1036, MATCH(CONCATENATE(YEAR(TODAY()), MONTH(TODAY()-31), Metrica!$C24), CONCATENATE(DATA!$A$2:$A$1036, DATA!$D$2:$D$1036), 0)), 0)} -> 168750000 | H24: {=IFERROR(INDEX(DATA!$Q$2:$Q$1036, MATCH(CONCATENATE(YEAR(TODAY()), MONTH(TODAY()), Metrica!$C24), CONCATENATE(DATA!$A$2:$A$1036, DATA!$D$2:$D$1036), 0)), 0)} -> 162000000 | I24: {=IFERROR(INDEX(DATA!$H$2:$H$1036, MATCH(CONCATENATE(YEAR(TODAY()), MONTH(TODAY()), Metrica!$C24), CONCATENATE(DATA!$A$2:$A$1036, DATA!$D$2:$D$1036), 0)), 0)} -> 6750000 | J24: {=IFERROR(INDEX(DATA!$I$2:$I$1036, MATCH(CONCATENATE(YEAR(TODAY()), MONTH(TODAY()), Metrica!$C24), CONCATENATE(DATA!$A$2:$A$1036, DATA!$D$2:$D$1036), 0)), 0)} -> 2937087 | K24: {=IFERROR(INDEX(DATA!$L$2:$L$1036, MATCH(CONCATENATE(YEAR(TODAY()), MONTH(TODAY()), Metrica!$C24), CONCATENATE(DATA!$A$2:$A$1036, DATA!$D$2:$D$1036), 0)), 0)} -> 1697040.6 | L24: {=IFERROR(INDEX(DATA!$P$2:$P$1036, MATCH(CONCATENATE(YEAR(TODAY()), MONTH(TODAY()), Metrica!$C24), CONCATENATE(DATA!$A$2:$A$1036, DATA!$D$2:$D$1036), 0)), 0)} -> 17552981 | M24: {=IFERROR(INDEX(DATA!$R$2:$R$1036, MATCH(CONCATENATE(YEAR(TODAY()), MONTH(TODAY()), Metrica!$C24), CONCATENATE(DATA!$A$2:$A$1036, DATA!$D$2:$D$1036), 0)), 0)} -> 1 | N24: {=IFERROR(INDEX(DATA!$S$2:$S$1036, MATCH(CONCATENATE(YEAR(TODAY()), MONTH(TODAY()), Metrica!$C24), CONCATENATE(DATA!$A$2:$A$1036, DATA!$D$2:$D$1036), 0)), 0)} -> 2862725 | O24: {=IFERROR(IF(INDEX(DATA!$O$2:$O$1036,MATCH(CONCATENATE(YEAR(TODAY()), MONTH(TODAY()), Metrica!$C24), CONCATENATE(DATA!$A$2 $A$1036, DATA!$D$2:$D$1036), 0)) = 0,"",INDEX(DATA!$O$2:$O$1036,MATCH(CONCATENATE(YEAR(TODAY()), MONTH(TODAY()), Metrica!$C24), CONCATENATE(DATA!$A$2:$A$1036, DATA!$D$2:$D$1036), 0))),"")} | P24: {=IFERROR(INDEX(DATA!$U$2:$U$1036, MATCH(CONCATENATE(YEAR(TODAY()), MONTH(TODAY()), Metrica!$C24), CONCATENATE(DATA!$A$2:$A$1036, DATA!$D$2:$D$1036), 0)), 0)} -> ABONADO
A25: LAMAR OPTICAL S.A.S | B25: BANCOLOMBIA | C25: 8140098503 | D25: {=IFERROR(INDEX(DATA!$E$2:$E$1036, MATCH(CONCATENATE(YEAR(TODAY()), MONTH(TODAY()), Metrica!$C25), CONCATENATE(DATA!$A$2:$A$1036, DATA!$D$2:$D$1036), 0)), "")} -> 45553 | E25: {=IFERROR(INDEX(DATA!$F$2:$F$1036, MATCH(CONCATENATE(YEAR(TODAY()), MONTH(TODAY()), Metrica!$C25), CONCATENATE(DATA!$A$2:$A$1036, DATA!$D$2:$D$1036), 0)), "")} -> 13 | F25: {=IFERROR(INDEX(DATA!$G$2:$G$1036, MATCH(CONCATENATE(YEAR(TODAY()), MONTH(TODAY()), Metrica!$C25), CONCATENATE(DATA!$A$2:$A$1036, DATA!$D$2:$D$1036), 0)), "")} -> 46 | G25: {=IFERROR(INDEX(DATA!$Q$2:$Q$1036, MATCH(CONCATENATE(YEAR(TODAY()), MONTH(TODAY()-31), Metrica!$C25), CONCATENATE(DATA!$A$2:$A$1036, DATA!$D$2:$D$1036), 0)), 0)} -> 1.7761673e+08 | H25: {=IFERROR(INDEX(DATA!$Q$2:$Q$1036, MATCH(CONCATENATE(YEAR(TODAY()), MONTH(TODAY()), Metrica!$C25), CONCATENATE(DATA!$A$2:$A$1036, DATA!$D$2:$D$1036), 0)), 0)} -> 1.7383765e+08 | I25: {=IFERROR(INDEX(DATA!$H$2:$H$1036, MATCH(CONCATENATE(YEAR(TODAY()), MONTH(TODAY()), Metrica!$C25), CONCATENATE(DATA!$A$2:$A$1036, DATA!$D$2:$D$1036), 0)), 0)} -> 3779079.4 | J25: {=IFERROR(INDEX(DATA!$I$2:$I$1036, MATCH(CONCATENATE(YEAR(TODAY()), MONTH(TODAY()), Metrica!$C25), CONCATENATE(DATA!$A$2:$A$1036, DATA!$D$2:$D$1036), 0)), 0)} -> 2957550.4 | K25: {=IFERROR(INDEX(DATA!$L$2:$L$1036, MATCH(CONCATENATE(YEAR(TODAY()), MONTH(TODAY()), Metrica!$C25), CONCATENATE(DATA!$A$2:$A$1036, DATA!$D$2:$D$1036), 0)), 0)} -> 3492805.2 | L25: {=IFERROR(INDEX(DATA!$P$2:$P$1036, MATCH(CONCATENATE(YEAR(TODAY()), MONTH(TODAY()), Metrica!$C25), CONCATENATE(DATA!$A$2:$A$1036, DATA!$D$2:$D$1036), 0)), 0)} -> 10229435 | M25: {=IFERROR(INDEX(DATA!$R$2:$R$1036, MATCH(CONCATENATE(YEAR(TODAY()), MONTH(TODAY()), Metrica!$C25), CONCATENATE(DATA!$A$2:$A$1036, DATA!$D$2:$D$1036), 0)), 0)} -> -15 | N25: {=IFERROR(INDEX(DATA!$S$2:$S$1036, MATCH(CONCATENATE(YEAR(TODAY()), MONTH(TODAY()), Metrica!$C25), CONCATENATE(DATA!$A$2:$A$1036, DATA!$D$2:$D$1036), 0)), 0)} -> 0 | O25: {=IFERROR(IF(INDEX(DATA!$O$2:$O$1036,MATCH(CONCATENATE(YEAR(TODAY()), MONTH(TODAY()), Metrica!$C25), CONCATENATE(DATA!$A$2 $A$1036, DATA!$D$2:$D$1036), 0)) = 0,"",INDEX(DATA!$O$2:$O$1036,MATCH(CONCATENATE(YEAR(TODAY()), MONTH(TODAY()), Metrica!$C25), CONCATENATE(DATA!$A$2:$A$1036, DATA!$D$2:$D$1036), 0))),"")} | P25: {=IFERROR(INDEX(DATA!$U$2:$U$1036, MATCH(CONCATENATE(YEAR(TODAY()), MONTH(TODAY()), Metrica!$C25), CONCATENATE(DATA!$A$2:$A$1036, DATA!$D$2:$D$1036), 0)), 0)} -> PENDIENTE
A26: LAMAR OPTICAL S.A.S | B26: BANCO DE OCCIDENTE | C26: 180153332 | D26: {=IFERROR(INDEX(DATA!$E$2:$E$1036, MATCH(CONCATENATE(YEAR(TODAY()), MONTH(TODAY()), Metrica!$C26), CONCATENATE(DATA!$A$2:$A$1036, DATA!$D$2:$D$1036), 0)), "")} -> 45564 | E26: {=IFERROR(INDEX(DATA!$F$2:$F$1036, MATCH(CONCATENATE(YEAR(TODAY()), MONTH(TODAY()), Metrica!$C26), CONCATENATE(DATA!$A$2:$A$1036, DATA!$D$2:$D$1036), 0)), "")} -> 17 | F26: {=IFERROR(INDEX(DATA!$G$2:$G$1036, MATCH(CONCATENATE(YEAR(TODAY()), MONTH(TODAY()), Metrica!$C26), CONCATENATE(DATA!$A$2:$A$1036, DATA!$D$2:$D$1036), 0)), "")} -> 43 | G26: {=IFERROR(INDEX(DATA!$Q$2:$Q$1036, MATCH(CONCATENATE(YEAR(TODAY()), MONTH(TODAY()-31), Metrica!$C26), CONCATENATE(DATA!$A$2:$A$1036, DATA!$D$2:$D$1036), 0)), 0)} -> 224008632 | H26: {=IFERROR(INDEX(DATA!$Q$2:$Q$1036, MATCH(CONCATENATE(YEAR(TODAY()), MONTH(TODAY()), Metrica!$C26), CONCATENATE(DATA!$A$2:$A$1036, DATA!$D$2:$D$1036), 0)), 0)} -> 220670938 | I26: {=IFERROR(INDEX(DATA!$H$2:$H$1036, MATCH(CONCATENATE(YEAR(TODAY()), MONTH(TODAY()), Metrica!$C26), CONCATENATE(DATA!$A$2:$A$1036, DATA!$D$2:$D$1036), 0)), 0)} -> 3337694 | J26: {=IFERROR(INDEX(DATA!$I$2:$I$1036, MATCH(CONCATENATE(YEAR(TODAY()), MONTH(TODAY()), Metrica!$C26), CONCATENATE(DATA!$A$2:$A$1036, DATA!$D$2:$D$1036), 0)), 0)} -> 4039077 | K26: {=IFERROR(INDEX(DATA!$L$2:$L$1036, MATCH(CONCATENATE(YEAR(TODAY()), MONTH(TODAY()), Metrica!$C26), CONCATENATE(DATA!$A$2:$A$1036, DATA!$D$2:$D$1036), 0)), 0)} -> 0 | L26: {=IFERROR(INDEX(DATA!$P$2:$P$1036, MATCH(CONCATENATE(YEAR(TODAY()), MONTH(TODAY()), Metrica!$C26), CONCATENATE(DATA!$A$2:$A$1036, DATA!$D$2:$D$1036), 0)), 0)} -> 7376771 | M26: {=IFERROR(INDEX(DATA!$R$2:$R$1036, MATCH(CONCATENATE(YEAR(TODAY()), MONTH(TODAY()), Metrica!$C26), CONCATENATE(DATA!$A$2:$A$1036, DATA!$D$2:$D$1036), 0)), 0)} -> 5 | N26: {=IFERROR(INDEX(DATA!$S$2:$S$1036, MATCH(CONCATENATE(YEAR(TODAY()), MONTH(TODAY()), Metrica!$C26), CONCATENATE(DATA!$A$2:$A$1036, DATA!$D$2:$D$1036), 0)), 0)} -> 0 | O26: {=IFERROR(IF(INDEX(DATA!$O$2:$O$1036,MATCH(CONCATENATE(YEAR(TODAY()), MONTH(TODAY()), Metrica!$C26), CONCATENATE(DATA!$A$2 $A$1036, DATA!$D$2:$D$1036), 0)) = 0,"",INDEX(DATA!$O$2:$O$1036,MATCH(CONCATENATE(YEAR(TODAY()), MONTH(TODAY()), Metrica!$C26), CONCATENATE(DATA!$A$2:$A$1036, DATA!$D$2:$D$1036), 0))),"")} | P26: {=IFERROR(INDEX(DATA!$U$2:$U$1036, MATCH(CONCATENATE(YEAR(TODAY()), MONTH(TODAY()), Metrica!$C26), CONCATENATE(DATA!$A$2:$A$1036, DATA!$D$2:$D$1036), 0)), 0)} -> PENDIENTE
A27: LAMAR OPTICAL S.A.S | B27: BANCOLOMBIA | C27: 8140099622 | D27: {=IFERROR(INDEX([1]DATA!$A$2:$U$1036,MATCH(CONCATENATE(YEAR(TODAY()),MONTH(TODAY()),[1]TABLERO!$C27),CONCATENATE([1]DATA!$A$2:$A$1036,[1]DATA!$D$2:$D$1036),0),MATCH(D$1,[1]DATA!$A$1:$U$1,0)),"")} | E27: {=IFERROR(INDEX([1]DATA!$A$2:$U$1036,MATCH(CONCATENATE(YEAR(TODAY()),MONTH(TODAY()),[1]TABLERO!$C27),CONCATENATE([1]DATA!$A$2:$A$1036,[1]DATA!$D$2:$D$1036),0),MATCH(E$1,[1]DATA!$A$1:$U$1,0)),"")} | F27: {=IFERROR(INDEX([1]DATA!$A$2:$U$1036,MATCH(CONCATENATE(YEAR(TODAY()),MONTH(TODAY()),[1]TABLERO!$C27),CONCATENATE([1]DATA!$A$2:$A$1036,[1]DATA!$D$2:$D$1036),0),MATCH(F$1,[1]DATA!$A$1:$U$1,0)),"")} | G27: {=IFERROR(INDEX([1]DATA!$A$2:$U$1036,MATCH(CONCATENATE(YEAR(TODAY()),MONTH(TODAY()-31),[1]TABLERO!$C27),CONCATENATE([1]DATA!$A$2:$A$1036,[1]DATA!$D$2:$D$1036),0),MATCH(H$1,[1]DATA!$A$1:$U$1,0)),0)} -> 0 | H27: {=IFERROR(INDEX([1]DATA!$A$2:$U$1036,MATCH(CONCATENATE(YEAR(TODAY()),MONTH(TODAY()),[1]TABLERO!$C27),CONCATENATE([1]DATA!$A$2:$A$1036,[1]DATA!$D$2:$D$1036),0),MATCH(H$1,[1]DATA!$A$1:$U$1,0)),"")} | I27: {=IFERROR(INDEX([1]DATA!$A$2:$U$1036,MATCH(CONCATENATE(YEAR(TODAY()),MONTH(TODAY()),[1]TABLERO!$C27),CONCATENATE([1]DATA!$A$2:$A$1036,[1]DATA!$D$2:$D$1036),0),MATCH(I$1,[1]DATA!$A$1:$U$1,0)),"")} | J27: {=IFERROR(INDEX([1]DATA!$A$2:$U$1036,MATCH(CONCATENATE(YEAR(TODAY()),MONTH(TODAY()),[1]TABLERO!$C27),CONCATENATE([1]DATA!$A$2:$A$1036,[1]DATA!$D$2:$D$1036),0),MATCH(J$1,[1]DATA!$A$1:$U$1,0)),"")} | K27: {=IFERROR(INDEX([1]DATA!$A$2:$U$1036,MATCH(CONCATENATE(YEAR(TODAY()),MONTH(TODAY()),[1]TABLERO!$C27),CONCATENATE([1]DATA!$A$2:$A$1036,[1]DATA!$D$2:$D$1036),0),MATCH(K$1,[1]DATA!$A$1:$U$1,0)),"")} | L27: {=IFERROR(INDEX([1]DATA!$A$2:$U$1036,MATCH(CONCATENATE(YEAR(TODAY()),MONTH(TODAY()),[1]TABLERO!$C27),CONCATENATE([1]DATA!$A$2:$A$1036,[1]DATA!$D$2:$D$1036),0),MATCH(L$1,[1]DATA!$A$1:$U$1,0)),"")} | M27: {=IFERROR(INDEX([1]DATA!$A$2:$U$1036,MATCH(CONCATENATE(YEAR(TODAY()),MONTH(TODAY()),[1]TABLERO!$C27),CONCATENATE([1]DATA!$A$2:$A$1036,[1]DATA!$D$2:$D$1036),0),MATCH(M$1,[1]DATA!$A$1:$U$1,0)),"")} | N27: {=IFERROR(INDEX(DATA!$S$2:$S$1036, MATCH(CONCATENATE(YEAR(TODAY()), MONTH(TODAY()), Metrica!$C27), CONCATENATE(DATA!$A$2:$A$1036, DATA!$D$2:$D$1036), 0)), 0)} -> 0 | O27: {=IFERROR(IF(INDEX(DATA!$O$2:$O$1036,MATCH(CONCATENATE(YEAR(TODAY()), MONTH(TODAY()), Metrica!$C27), CONCATENATE(DATA!$A$2 $A$1036, DATA!$D$2:$D$1036), 0)) = 0,"",INDEX(DATA!$O$2:$O$1036,MATCH(CONCATENATE(YEAR(TODAY()), MONTH(TODAY()), Metrica!$C27), CONCATENATE(DATA!$A$2:$A$1036, DATA!$D$2:$D$1036), 0))),"")} | P27: {=IFERROR(INDEX([1]DATA!$A$2:$U$1036,MATCH(CONCATENATE(YEAR(TODAY()),MONTH(TODAY()),[1]TABLERO!$C27),CONCATENATE([1]DATA!$A$2:$A$1036,[1]DATA!$D$2:$D$1036),0),MATCH(P$1,[1]DATA!$A$1:$U$1,0)),"")}
A29: TOTAL | D29: =SUBTOTAL(2,D2:D26) -> 24 | E29: =AVERAGE(E2:E26) -> 21.375 | F29: =AVERAGE(F2:F26) -> 20.208333 | G29: =SUBTOTAL(9,G2:G27) -> 1.3904257e+09 | H29: =SUBTOTAL(9,H2:H27) -> 1.2663751e+09 | I29: =SUBTOTAL(9,I2:I27) -> 60300615 | J29: =SUBTOTAL(9,J2:J27) -> 22371057 | K29: =SUBTOTAL(9,K2:K27) -> 9125307.1 | L29: =SUBTOTAL(9,L2:L27) -> 98061813 | M29: =IFERROR(SUBTOTAL(101,M2:M27),0) -> 1.68 | N29: =SUBTOTAL(9,N2:N27) -> 2862725
J31: PEND X PAGAR | L31: =$L$29-$N$29 -> 95199088
G35: formulas de busqueda y extracción con concatenación

Sheet DATA
A1: TERCERO | B1: TERCERO | C1: EMPRESA | D1: N° PRODUCTO | E1: FECHA MAX PARA PAGAR | F1: CUOTA IN | G1: CUOTA FIN | H1: CUOTA CAPITAL | I1: INTERES | J1: SEGURO | K1: OTROS GASTOS | L1: MORA | M1: INTERES PACTADO | N1: INTERES MENSUAL | O1: INCREMENTO INTERES | P1: TOTAL A PAGAR | Q1: SALDO CAPITAL | R1: DIAS VENCIDO | S1: VALOR PAGADO | T1: FECHA DE PAGO | U1: ESTADO
A2: =CONCATENATE(YEAR($E2),MONTH($E2)) -> 20242 | B2: BANCOLOMBIA | C2: LAMAR OPTICAL S.A.S | D2: 8140099320 | E2: 45335 | F2: 0 | G2: 12 | H2: 0 | I2: 0 | J2: 0 | K2: 0 | L2: 0 | M2: 0.0136 | N2: =I2/Q2 -> 0 | O2: =(N2/M2)-1 -> -1 | P2: =H2+I2+J2+K2+L2 -> 0 | Q2: 17722092 | R2: =IF(T1="",TODAY()-E1,IF(T2="",TODAY()-E2,"OK")) -> OK | S2: 0 | T2: 45335 | U2: =IF(AND(S2="",T2=""),"PENDIENTE",IF(AND(S2<>"",T2<>""),"PAGADO","ABONADO")) -> PAGADO
A3: =CONCATENATE(YEAR($E3),MONTH($E3)) -> 20243 | B3: BANCOLOMBIA | C3: LAMAR OPTICAL S.A.S | D3: 8140099320 | E3: 45364 | F3: 1 | G3: 11 | H3: =$Q$2/12 -> 1476841 | I3: =1717665-H3 -> 240824 | J3: 0 | K3: 0 | L3: =IF(S2="",0,IF(S2<=P2,P2-S2,0)) -> 0 | M3: 0.0136 | N3: =I3/Q3 -> 0.014824271 | O3: =(N3/M3)-1 -> 0.090019912 | P3: =H3+I3+J3+K3+L3 -> 1717665 | Q3: =Q2-H3 -> 16245251 | R3: =IF(T2="",TODAY()-E2,IF(T3="",TODAY()-E3,"OK")) -> OK | S3: 1717665 | T3: 45364 | U3: =IF(AND(S3="",T3=""),"PENDIENTE",IF(AND(S3<>"",T3<>""),"PAGADO","ABONADO")) -> PAGADO
A4: =CONCATENATE(YEAR($E4),MONTH($E4)) -> 20244 | B4: BANCOLOMBIA | C4: LAMAR OPTICAL S.A.S | D4: 8140099320 | E4: 45395 | F4: 2 | G4: 10 | H4: =$Q$2/12 -> 1476841 | I4: 220935.41 | J4: 0 | K4: 0 | L4: =IF(S3="",0,IF(S3<=P3,P3-S3,0)) -> 0 | M4: 0.0136 | N4: =I4/Q4 -> 0.01496 | O4: =(N4/M4)-1 -> 0.1 | P4: =H4+I4+J4+K4+L4 -> 1697776.4 | Q4: =Q3-H4 -> 14768410 | R4: =IF(T3="",TODAY()-E3,IF(T4="",TODAY()-E4,"OK")) -> OK | S4: 1709673 | T4: 45397 | U4: =IF(AND(S4="",T4=""),"PENDIENTE",IF(AND(S4<>"",T4<>""),"PAGADO","ABONADO")) -> PAGADO
A5: =CONCATENATE(YEAR($E5),MONTH($E5)) -> 20245 | B5: BANCOLOMBIA | C5: LAMAR OPTICAL S.A.S | D5: 8140099320 | E5: 45425 | F5: 3 | G5: 9 | H5: =$Q$2/12 -> 1476841 | I5: 200850.38 | J5: 0 | K5: 0 | L5: =IF(S4="",0,IF(S4<=P4,P4-S4,0)) -> 0 | M5: 0.0136 | N5: =I5/Q4 -> 0.0136 | O5: =(N5/M5)-1 -> 0 | P5: =H5+I5+J5+K5+L5 -> 1677691.4 | Q5: =Q4-H5 -> 13291569 | R5: =IF(T4="",TODAY()-E4,IF(T5="",TODAY()-E5,"OK")) -> OK | S5: 1677470 | T5: 45426 | U5: =IF(AND(S5="",T5=""),"PENDIENTE",IF(AND(S5<>"",T5<>""),"PAGADO","ABONADO")) -> PAGADO
A6: =CONCATENATE(YEAR($E6),MONTH($E6)) -> 20246 | B6: BANCOLOMBIA | C6: LAMAR OPTICAL S.A.S | D6: 8140099320 | E6: 45456 | F6: 4 | G6: 8 | H6: =$Q$2/12 -> 1476841 | I6: 180765.34 | J6: 0 | K6: 0 | L6: =IF(S5="",0,IF(S5<=P5,P5-S5,0)) -> 221.376 | M6: 0.0136 | N6: =I6/Q5 -> 0.0136 | O6: =(N6/M6)-1 -> 0 | P6: =H6+I6+J6+K6+L6 -> 1657827.7 | Q6: =Q5-H6 -> 11814728 | R6: =IF(T5="",TODAY()-E5,IF(T6="",TODAY()-E6,"OK")) -> OK | S6: 1659832 | T6: 45456 | U6: =IF(AND(S6="",T6=""),"PENDIENTE",IF(AND(S6<>"",T6<>""),"PAGADO","ABONADO")) -> PAGADO
A7: =CONCATENATE(YEAR($E7),MONTH($E7)) -> 20247 | B7: BANCOLOMBIA | C7: LAMAR OPTICAL S.A.S | D7: 8140099320 | E7: 45486 | F7: 5 | G7: 7 | H7: =$Q$2/12 -> 1476841 | I7: 160680.3 | J7: 0 | K7: 0 | L7: =IF(S6="",0,IF(S6<=P6,P6-S6,0)) -> 0 | M7: 0.0136 | N7: =I7/Q6 -> 0.0136 | O7: =(N7/M7)-1 -> 0 | P7: =H7+I7+J7+K7+L7 -> 1637521.3 | Q7: =Q6-H7 -> 10337887 | R7: =IF(T6="",TODAY()-E6,IF(T7="",TODAY()-E7,"OK")) -> OK | S7: 1632519 | T7: 45488 | U7: =IF(AND(S7="",T7=""),"PENDIENTE",IF(AND(S7<>"",T7<>""),"PAGADO","ABONADO")) -> PAGADO
A8: =CONCATENATE(YEAR($E8),MONTH($E8)) -> 20248 | B8: BANCOLOMBIA | C8: LAMAR OPTICAL S.A.S | D8: 8140099320 | E8: 45517 | F8: 6 | G8: 6 | H8: =$Q$2/12 -> 1476841 | I8: 140595.26 | J8: 0 | K8: 0 | L8: =IF(S7="",0,IF(S7<=P7,P7-S7,0)) -> 5002.3008 | M8: 0.0136 | N8: =I8/Q7 -> 0.0136 | O8: =(N8/M8)-1 -> 0 | P8: =H8+I8+J8+K8+L8 -> 1622438.6 | Q8: =Q7-H8 -> 8861046 | R8: =IF(T7="",TODAY()-E7,IF(T8="",TODAY()-E8,"OK")) -> OK | S8: 1613711 | T8: 45519 | U8: =IF(AND(S8="",T8=""),"PENDIENTE",IF(AND(S8<>"",T8<>""),"PAGADO","ABONADO")) -> PAGADO
A9: =CONCATENATE(YEAR($E9),MONTH($E9)) -> 20249 | B9: BANCOLOMBIA | C9: LAMAR OPTICAL S.A.S | D9: 8140099320 | E9: 45548 | F9: 7 | G9: 5 | H9: =$Q$2/12 -> 1476841 | I9: 120510.23 | J9: 0 | K9: 0 | L9: =IF(S8="",0,IF(S8<=P8,P8-S8,0)) -> 8727.564 | M9: 0.0136 | N9: =I9/Q8 -> 0.0136 | O9: =(N9/M9)-1 -> 0 | P9: =H9+I9+J9+K9+L9 -> 1606078.8 | Q9: =Q8-H9 -> 7384205 | R9: =IF(T8="",TODAY()-E8,IF(T9="",TODAY()-E9,"OK")) -> -10 | U9: =IF(AND(S9="",T9=""),"PENDIENTE",IF(AND(S9<>"",T9<>""),"PAGADO","ABONADO")) -> PENDIENTE
A10: =CONCATENATE(YEAR($E10),MONTH($E10)) -> 202410 | B10: BANCOLOMBIA | C10: LAMAR OPTICAL S.A.S | D10: 8140099320 | E10: 45578 | F10: 8 | G10: 4 | H10: =$Q$2/12 -> 1476841 | I10: 100425.19 | J10: 0 | K10: 0 | L10: =IF(S9="",0,IF(S9<=P9,P9-S9,0)) -> 0 | M10: 0.0136 | N10: =I10/Q9 -> 0.0136 | O10: =(N10/M10)-1 -> 0 | P10: =H10+I10+J10+K10+L10 -> 1577266.2 | Q10: =Q9-H10 -> 5907364 | R10: =IF(T9="",TODAY()-E9,IF(T10="",TODAY()-E10,"OK")) -> -10 | U10: =IF(AND(S10="",T10=""),"PENDIENTE",IF(AND(S10<>"",T10<>""),"PAGADO","ABONADO")) -> PENDIENTE
A11: =CONCATENATE(YEAR($E11),MONTH($E11)) -> 202411 | B11: BANCOLOMBIA | C11: LAMAR OPTICAL S.A.S | D11: 8140099320 | E11: 45609 | F11: 9 | G11: 3 | H11: =$Q$2/12 -> 1476841 | I11: 80340.15 | J11: 0 | K11: 0 | L11: =IF(S10="",0,IF(S10<=P10,P10-S10,0)) -> 0 | M11: 0.0136 | N11: =I11/Q10 -> 0.0136 | O11: =(N11/M11)-1 -> 0 | P11: =H11+I11+J11+K11+L11 -> 1557181.2 | Q11: =Q10-H11 -> 4430523 | R11: =IF(T10="",TODAY()-E10,IF(T11="",TODAY()-E11,"OK")) -> -40 | U11: =IF(AND(S11="",T11=""),"PENDIENTE",IF(AND(S11<>"",T11<>""),"PAGADO","ABONADO")) -> PENDIENTE
A12: =CONCATENATE(YEAR($E12),MONTH($E12)) -> 202412 | B12: BANCOLOMBIA | C12: LAMAR OPTICAL S.A.S | D12: 8140099320 | E12: 45639 | F12: 10 | G12: 2 | H12: =$Q$2/12 -> 1476841 | I12: 60255.113 | J12: 0 | K12: 0 | L12: =IF(S11="",0,IF(S11<=P11,P11-S11,0)) -> 0 | M12: 0.0136 | N12: =I12/Q11 -> 0.0136 | O12: =(N12/M12)-1 -> 0 | P12: =H12+I12+J12+K12+L12 -> 1537096.1 | Q12: =Q11-H12 -> 2953682 | R12: =IF(T11="",TODAY()-E11,IF(T12="",TODAY()-E12,"OK")) -> -71 | U12: =IF(AND(S12="",T12=""),"PENDIENTE",IF(AND(S12<>"",T12<>""),"PAGADO","ABONADO")) -> PENDIENTE
A13: =CONCATENATE(YEAR($E13),MONTH($E13)) -> 20251 | B13: BANCOLOMBIA | C13: LAMAR OPTICAL S.A.S | D13: 8140099320 | E13: 45670 | F13: 11 | G13: 1 | H13: =$Q$2/12 -> 1476841 | I13: 40170.075 | J13: 0 | K13: 0 | L13: =IF(S12="",0,IF(S12<=P12,P12-S12,0)) -> 0 | M13: 0.0136 | N13: =I13/Q12 -> 0.0136 | O13: =(N13/M13)-1 -> 0 | P13: =H13+I13+J13+K13+L13 -> 1517011.1 | Q13: =Q12-H13 -> 1476841 | R13: =IF(T12="",TODAY()-E12,IF(T13="",TODAY()-E13,"OK")) -> -101 | U13: =IF(AND(S13="",T13=""),"PENDIENTE",IF(AND(S13<>"",T13<>""),"PAGADO","ABONADO")) -> PENDIENTE
A14: =CONCATENATE(YEAR($E14),MONTH($E14)) -> 20252 | B14: BANCOLOMBIA | C14: LAMAR OPTICAL S.A.S | D14: 8140099320 | E14: 45701 | F14: 12 | G14: 0 | H14: =$Q$2/12 -> 1476841 | I14: 20085.038 | J14: 0 | K14: 0 | L14: =IF(S13="",0,IF(S13<=P13,P13-S13,0)) -> 0 | M14: 0.0136 | N14: =I14/Q13 -> 0.0136 | O14: =(N14/M14)-1 -> 0 | P14: =H14+I14+J14+K14+L14 -> 1496926 | Q14: =Q13-H14 -> 0 | R14: =IF(T13="",TODAY()-E13,IF(T14="",TODAY()-E14,"OK")) -> -132 | U14: =IF(AND(S14="",T14=""),"PENDIENTE",IF(AND(S14<>"",T14<>""),"PAGADO","ABONADO")) -> PENDIENTE
A15: =CONCATENATE(YEAR($E15),MONTH($E15)) -> 20242 | B15: BANCOLOMBIA | C15: LAMAR OPTICAL S.A.S | D15: 8140099327 | E15: 45335 | F15: 0 | G15: 8 | H15: 0 | I15: 0 | J15: 0 | K15: 0 | L15: =IF(S14="",0,IF(S14<=P14,P14-S14,0)) -> 0 | M15: 0.0136 | N15: 0 | O15: =(N15/M15)-1 -> -1 | P15: =H15+I15+J15+K15+L15 -> 0 | Q15: 85000000 | R15: =IF(T14="",TODAY()-E14,IF(T15="",TODAY()-E15,"OK")) -> -163 | S15: 0 | T15: 45335 | U15: =IF(AND(S15="",T15=""),"PENDIENTE",IF(AND(S15<>"",T15<>""),"PAGADO","ABONADO")) -> PAGADO
A16: =CONCATENATE(YEAR($E16),MONTH($E16)) -> 20245 | B16: BANCOLOMBIA | C16: LAMAR OPTICAL S.A.S | D16: 8140099327 | E16: 45425 | F16: 1 | G16: 7 | H16: 10625000 | I16: 2452675 | J16: 0 | K16: 0 | L16: =IF(S15="",0,IF(S15<=P15,P15-S15,0)) -> 0 | M16: =(0.22176+0.1245)/12 -> 0.028855 | N16: =I16/Q15 -> 0.028855 | O16: =(N16/M16)-1 -> 0 | P16: =H16+I16+J16+K16+L16 -> 13077675 | Q16: =Q15-H16 -> 74375000 | R16: =IF(T15="",TODAY()-E15,IF(T16="",TODAY()-E16,"OK")) -> OK | S16: 14929400 | T16: 45426 | U16: =IF(AND(S16="",T16=""),"PENDIENTE",IF(AND(S16<>"",T16<>""),"PAGADO","ABONADO")) -> PAGADO
A17: =CONCATENATE(YEAR($E17),MONTH($E17)) -> 20248 | B17: BANCOLOMBIA | C17: LAMAR OPTICAL S.A.S | D17: 8140099327 | E17: 45517 | F17: 2 | G17: 6 | H17: 10625000 | I17: 2146090.6 | J17: 0 | K17: 0 | L17: =IF(S16="",0,IF(S16<=P16,P16-S16,0)) -> 0 | M17: =(0.22176+0.1245)/12 -> 0.028855 | N17: =I17/Q16 -> 0.028855 | O17: =(N17/M17)-1 -> 0 | P17: =H17+I17+J17+K17+L17 -> 12771091 | Q17: =Q16-H16 -> 63750000 | R17: =IF(T16="",TODAY()-E16,IF(T17="",TODAY()-E17,"OK")) -> OK | S17: 14297141 | T17: 45518 | U17: =IF(AND(S17="",T17=""),"PENDIENTE",IF(AND(S17<>"",T17<>""),"PAGADO","ABONADO")) -> PAGADO
A18: =CONCATENATE(YEAR($E18),MONTH($E18)) -> 202411 | B18: BANCOLOMBIA | C18: LAMAR OPTICAL S.A.S | D18: 8140099327 | E18: 45609 | F18: 3 | G18: 5 | H18: 10625000 | I18: 1839506.3 | J18: 0 | K18: 0 | L18: =IF(S17="",0,IF(S17<=P17,P17-S17,0)) -> 0 | M18: =(0.22176+0.1245)/12 -> 0.028855 | N18: =I18/Q17 -> 0.028855 | O18: =(N18/M18)-1 -> 0 | P18: =H18+I18+J18+K18+L18 -> 12464506 | Q18: =Q17-H17 -> 53125000 | R18: =IF(T17="",TODAY()-E17,IF(T18="",TODAY()-E18,"OK")) -> -71 | U18: =IF(AND(S18="",T18=""),"PENDIENTE",IF(AND(S18<>"",T18<>""),"PAGADO","ABONADO")) -> PENDIENTE
A19: =CONCATENATE(YEAR($E19),MONTH($E19)) -> 20252 | B19: BANCOLOMBIA | C19: LAMAR OPTICAL S.A.S | D19: 8140099327 | E19: 45701 | F19: 4 | G19: 4 | H19: 10625000 | I19: 1532921.9 | J19: 0 | K19: 0 | L19: =IF(S18="",0,IF(S18<=P18,P18-S18,0)) -> 0 | M19: =(0.22176+0.1245)/12 -> 0.028855 | N19: =I19/Q18 -> 0.028855 | O19: =(N19/M19)-1 -> 0 | P19: =H19+I19+J19+K19+L19 -> 12157922 | Q19: =Q18-H18 -> 42500000 | R19: =IF(T18="",TODAY()-E18,IF(T19="",TODAY()-E19,"OK")) -> -71 | U19: =IF(AND(S19="",T19=""),"PENDIENTE",IF(AND(S19<>"",T19<>""),"PAGADO","ABONADO")) -> PENDIENTE
A20: =CONCATENATE(YEAR($E20),MONTH($E20)) -> 20255 | B20: BANCOLOMBIA | C20: LAMAR OPTICAL S.A.S | D20: 8140099327 | E20: 45790 | F20: 5 | G20: 3 | H20: 10625000 | I20: 1226337.5 | J20: 0 | K20: 0 | L20: =IF(S19="",0,IF(S19<=P19,P19-S19,0)) -> 0 | M20: =(0.22176+0.1245)/12 -> 0.028855 | N20: =I20/Q19 -> 0.028855 | O20: =(N20/M20)-1 -> 0 | P20: =H20+I20+J20+K20+L20 -> 11851338 | Q20: =Q19-H19 -> 31875000 | R20: =IF(T19="",TODAY()-E19,IF(T20="",TODAY()-E20,"OK")) -> -163 | U20: =IF(AND(S20="",T20=""),"PENDIENTE",IF(AND(S20<>"",T20<>""),"PAGADO","ABONADO")) -> PENDIENTE
A21: =CONCATENATE(YEAR($E21),MONTH($E21)) -> 20258 | B21: BANCOLOMBIA | C21: LAMAR OPTICAL S.A.S | D21: 8140099327 | E21: 45882 | F21: 6 | G21: 2 | H21: 10625000 | I21: 919753.13 | J21: 0 | K21: 0 | L21: =IF(S20="",0,IF(S20<=P20,P20-S20,0)) -> 0 | M21: =(0.22176+0.1245)/12 -> 0.028855 | N21: =I21/Q20 -> 0.028855 | O21: =(N21/M21)-1 -> 0 | P21: =H21+I21+J21+K21+L21 -> 11544753 | Q21: =Q20-H20 -> 21250000 | R21: =IF(T20="",TODAY()-E20,IF(T21="",TODAY()-E21,"OK")) -> -252 | U21: =IF(AND(S21="",T21=""),"PENDIENTE",IF(AND(S21<>"",T21<>""),"PAGADO","ABONADO")) -> PENDIENTE
A22: =CONCATENATE(YEAR($E22),MONTH($E22)) -> 202511 | B22: BANCOLOMBIA | C22: LAMAR OPTICAL S.A.S | D22: 8140099327 | E22: 45974 | F22: 7 | G22: 1 | H22: 10625000 | I22: 613168.75 | J22: 0 | K22: 0 | L22: =IF(S21="",0,IF(S21<=P21,P21-S21,0)) -> 0 | M22: =(0.22176+0.1245)/12 -> 0.028855 | N22: =I22/Q21 -> 0.028855 | O22: =(N22/M22)-1 -> 0 | P22: =H22+I22+J22+K22+L22 -> 11238169 | Q22: =Q21-H21 -> 10625000 | R22: =IF(T21="",TODAY()-E21,IF(T22="",TODAY()-E22,"OK")) -> -344 | U22: =IF(AND(S22="",T22=""),"PENDIENTE",IF(AND(S22<>"",T22<>""),"PAGADO","ABONADO")) -> PENDIENTE
A23: =CONCATENATE(YEAR($E23),MONTH($E23)) -> 20262 | B23: BANCOLOMBIA | C23: LAMAR OPTICAL S.A.S | D23: 8140099327 | E23: 46066 | F23: 8 | G23: 0 | H23: 10625000 | I23: 306584.38 | J23: 0 | K23: 0 | L23: =IF(S22="",0,IF(S22<=P22,P22-S22,0)) -> 0 | M23: =(0.22176+0.1245)/12 -> 0.028855 | N23: =I23/Q22 -> 0.028855 | O23: =(N23/M23)-1 -> 0 | P23: =H23+I23+J23+K23+L23 -> 10931584 | Q23: =Q22-H22 -> 0 | R23: =IF(T22="",TODAY()-E22,IF(T23="",TODAY()-E23,"OK")) -> -436 | U23: =IF(AND(S23="",T23=""),"PENDIENTE",IF(AND(S23<>"",T23<>""),"PAGADO","ABONADO")) -> PENDIENTE
A24: =CONCATENATE(YEAR($E24),MONTH($E24)) -> 202111 | B24: SERFINANZAS | C24: INVERSIONES RUEDA S.A.S | D24: 111000149580 | E24: 44513 | F24: 1 | G24: 35 | H24: 2313071.2 | I24: 1019610.8 | J24: 0 | K24: 0 | L24: =IF(S23="",0,IF(S23<=P23,P23-S23,0)) -> 0 | M24: =0.12235329/12 -> 0.010196108 | N24: =I24/100000000 -> 0.010196108 | O24: =(N24/M24)-1 -> 0 | P24: =H24+I24+J24+K24+L24 -> 3332682 | Q24: 97686929 | R24: OK | S24: 3653516 | T24: 44514 | U24: =IF(AND(S24="",T24=""),"PENDIENTE",IF(AND(S24<>"",T24<>""),"PAGADO","ABONADO")) -> PAGADO
A25: =CONCATENATE(YEAR($E25),MONTH($E25)) -> 202112 | B25: SERFINANZAS | C25: INVERSIONES RUEDA S.A.S | D25: 111000149580 | E25: 44543 | F25: 2 | G25: 34 | H25: 2323647.5 | I25: 1026554.7 | J25: 0 | K25: 320834 | L25: =IF(S24="",0,IF(S24<=P24,P24-S24,0)) -> 0 | M25: =0.12235329/12 -> 0.010196108 | N25: =I25/Q24 -> 0.010508619 | O25: =(N25/M25)-1 -> 0.030650093 | P25: =H25+I25+J25+K25+L25 -> 3671036.2 | Q25: 95363281 | R25: =IF(T24="",TODAY()-E24,IF(T25="",TODAY()-E25,"OK")) -> OK | S25: 3672517.6 | T25: 44544 | U25: =IF(AND(S25="",T25=""),"PENDIENTE",IF(AND(S25<>"",T25<>""),"PAGADO","ABONADO")) -> PAGADO
A26: =CONCATENATE(YEAR($E26),MONTH($E26)) -> 20221 | B26: SERFINANZAS | C26: INVERSIONES RUEDA S.A.S | D26: 111000149580 | E26: 44574 | F26: 3 | G26: 33 | H26: 2336323.4 | I26: 1029719.4 | J26: 0 | K26: 320834 | L26: =IF(S25="",0,IF(S25<=P25,P25-S25,0)) -> 0 | M26: =0.12235329/12 -> 0.010196108 | N26: =I26/Q25 -> 0.01079786 | O26: =(N26/M26)-1 -> 0.059017865 | P26: =H26+I26+J26+K26+L26 -> 3686876.8 | Q26: 93026958 | R26: =IF(T25="",TODAY()-E25,IF(T26="",TODAY()-E26,"OK")) -> OK | S26: 3686876.8 | T26: 44574 | U26: =IF(AND(S26="",T26=""),"PENDIENTE",IF(AND(S26<>"",T26<>""),"PAGADO","ABONADO")) -> PAGADO
A27: =CONCATENATE(YEAR($E27),MONTH($E27)) -> 20222 | B27: SERFINANZAS | C27: INVERSIONES RUEDA S.A.S | D27: 111000149580 | E27: 44605 | F27: 4 | G27: 32 | H27: 2347807.1 | I27: 1036806.5 | J27: 0 | K27: 320834 | L27: =IF(S26="",0,IF(S26<=P26,P26-S26,0)) -> 0 | M27: =0.12235329/12 -> 0.010196108 | N27: =I27/Q26 -> 0.011145227 | O27: =(N27/M27)-1 -> 0.093086421 | P27: =H27+I27+J27+K27+L27 -> 3705447.6 | Q27: 90679151 | R27: =IF(T26="",TODAY()-E26,IF(T27="",TODAY()-E27,"OK")) -> OK | S27: 3708570.1 | T27: 44607 | U27: =IF(AND(S27="",T27=""),"PENDIENTE",IF(AND(S27<>"",T27<>""),"PAGADO","ABONADO")) -> PAGADO
A28: =CONCATENATE(YEAR($E28),MONTH($E28)) -> 20223 | B28: SERFINANZAS | C28: INVERSIONES RUEDA S.A.S | D28: 111000149580 | E28: 44633 | F28: 5 | G28: 31 | H28: 2361490.2 | I28: 1040020.6 | J28: 0 | K28: 320834 | L28: =IF(S27="",0,IF(S27<=P27,P27-S27,0)) -> 0 | M28: =0.12235329/12 -> 0.010196108 | N28: =I28/Q27 -> 0.011469236 | O28: =(N28/M28)-1 -> 0.12486415 | P28: =H28+I28+J28+K28+L28 -> 3722344.8 | Q28: 88317661 | R28: =IF(T27="",TODAY()-E27,IF(T28="",TODAY()-E28,"OK")) -> OK | S28: 3730246 | T28: 44637 | U28: =IF(AND(S28="",T28=""),"PENDIENTE",IF(AND(S28<>"",T28<>""),"PAGADO","ABONADO")) -> PAGADO
A29: =CONCATENATE(YEAR($E29),MONTH($E29)) -> 20224 | B29: SERFINANZAS | C29: INVERSIONES RUEDA S.A.S | D29: 111000149580 | E29: 44664 | F29: 6 | G29: 30 | H29: 2357927.6 | I29: 1085324.4 | J29: 0 | K29: 320834 | L29: =IF(S28="",0,IF(S28<=P28,P28-S28,0)) -> 0 | M29: =0.12235329/12 -> 0.010196108 | N29: =I29/Q28 -> 0.012288872 | O29: =(N29/M29)-1 -> 0.20525128 | P29: =H29+I29+J29+K29+L29 -> 3764086 | Q29: 85959733 | R29: =IF(T28="",TODAY()-E28,IF(T29="",TODAY()-E29,"OK")) -> OK | S29: 3786931.1 | T29: 44678 | U29: =IF(AND(S29="",T29=""),"PENDIENTE",IF(AND(S29<>"",T29<>""),"PAGADO","ABONADO")) -> PAGADO
A30: =CONCATENATE(YEAR($E30),MONTH($E30)) -> 20225 | B30: SERFINANZAS | C30: INVERSIONES RUEDA S.A.S | D30: 111000149580 | E30: 44694 | F30: 7 | G30: 29 | H30: 2367950.7 | I30: 1101311.9 | J30: 0 | K30: 320834 | L30: =IF(S29="",0,IF(S29<=P29,P29-S29,0)) -> 0 | M30: =0.12235329/12 -> 0.010196108 | N30: =I30/Q29 -> 0.012811951 | O30: =(N30/M30)-1 -> 0.25655313 | P30: =H30+I30+J30+K30+L30 -> 3790096.5 | Q30: 83591782 | R30: =IF(T29="",TODAY()-E29,IF(T30="",TODAY()-E30,"OK")) -> OK | S30: 3798600 | T30: 44699 | U30: =IF(AND(S30="",T30=""),"PENDIENTE",IF(AND(S30<>"",T30<>""),"PAGADO","ABONADO")) -> PAGADO
A31: =CONCATENATE(YEAR($E31),MONTH($E31)) -> 20226 | B31: SERFINANZAS | C31: INVERSIONES RUEDA S.A.S | D31: 111000149580 | E31: 44725 | F31: 8 | G31: 28 | H31: 2374458 | I31: 1127688 | J31: 0 | K31: 320834 | L31: =IF(S30="",0,IF(S30<=P30,P30-S30,0)) -> 0 | M31: =0.12235329/12 -> 0.010196108 | N31: =I31/Q30 -> 0.013490417 | O31: =(N31/M31)-1 -> 0.32309487 | P31: =H31+I31+J31+K31+L31 -> 3822980.1 | Q31: 81217324 | R31: =IF(T30="",TODAY()-E30,IF(T31="",TODAY()-E31,"OK")) -> OK | S31: 3830000 | T31: 44725 | U31: =IF(AND(S31="",T31=""),"PENDIENTE",IF(AND(S31<>"",T31<>""),"PAGADO","ABONADO")) -> PAGADO
A32: =CONCATENATE(YEAR($E32),MONTH($E32)) -> 20227 | B32: SERFINANZAS | C32: INVERSIONES RUEDA S.A.S | D32: 111000149580 | E32: 44755 | F32: 9 | G32: 27 | H32: 2383830.8 | I32: 1149776.3 | J32: 0 | K32: 315465.93 | L32: =IF(S31="",0,IF(S31<=P31,P31-S31,0)) -> 0 | M32: =0.12235329/12 -> 0.010196108 | N32: =I32/Q31 -> 0.014156787 | O32: =(N32/M32)-1 -> 0.38845012 | P32: =H32+I32+J32+K32+L32 -> 3849073.1 | Q32: 78833493 | R32: =IF(T31="",TODAY()-E31,IF(T32="",TODAY()-E32,"OK")) -> OK | S32: 3950000 | T32: 44784 | U32: =IF(AND(S32="",T32=""),"PENDIENTE",IF(AND(S32<>"",T32<>""),"PAGADO","ABONADO")) -> PAGADO
A33: =CONCATENATE(YEAR($E33),MONTH($E33)) -> 20228 | B33: SERFINANZAS | C33: INVERSIONES RUEDA S.A.S | D33: 111000149580 | E33: 44786 | F33: 10 | G33: 26 | H33: 2393254 | I33: 1174328.4 | J33: 0 | K33: 320834 | L33: =IF(S32="",0,IF(S32<=P32,P32-S32,0)) -> 0 | M33: =0.12235329/12 -> 0.010196108 | N33: =I33/Q32 -> 0.014896312 | O33: =(N33/M33)-1 -> 0.46098033 | P33: =H33+I33+J33+K33+L33 -> 3888416.4 | Q33: 76440239 | R33: =IF(T32="",TODAY()-E32,IF(T33="",TODAY()-E33,"OK")) -> OK | S33: 3842864.7 | T33: 44786 | U33: =IF(AND(S33="",T33=""),"PENDIENTE",IF(AND(S33<>"",T33<>""),"PAGADO","ABONADO")) -> PAGADO
A34: =CONCATENATE(YEAR($E34),MONTH($E34)) -> 20229 | B34: SERFINANZAS | C34: INVERSIONES RUEDA S.A.S | D34: 111000149580 | E34: 44817 | F34: 11 | G34: 25 | H34: 2390310.4 | I34: 1231720.2 | J34: 0 | K34: 320834 | L34: 0 | M34: =0.12235329/12 -> 0.010196108 | N34: =I34/Q33 -> 0.016113506 | O34: =(N34/M34)-1 -> 0.58035856 | P34: =H34+I34+J34+K34+L34 -> 3942864.6 | Q34: 74049929 | R34: =IF(T33="",TODAY()-E33,IF(T34="",TODAY()-E34,"OK")) -> OK | S34: 3972711 | T34: 44832 | U34: =IF(AND(S34="",T34=""),"PENDIENTE",IF(AND(S34<>"",T34<>""),"PAGADO","ABONADO")) -> PAGADO
A35: =CONCATENATE(YEAR($E35),MONTH($E35)) -> 202210 | B35: SERFINANZAS | C35: INVERSIONES RUEDA S.A.S | D35: 111000149580 | E35: 44847 | F35: 12 | G35: 24 | H35: 2409024.9 | I35: 1241170.5 | J35: 0 | K35: 320834 | L35: =IF(S34="",0,IF(S34<=P34,P34-S34,0)) -> 0 | M35: =0.12235329/12 -> 0.010196108 | N35: =I35/Q34 -> 0.016761266 | O35: =(N35/M35)-1 -> 0.64388869 | P35: =H35+I35+J35+K35+L35 -> 3971029.5 | Q35: 71640904 | R35: =IF(T34="",TODAY()-E34,IF(T35="",TODAY()-E35,"OK")) -> OK | S35: 3971029.5 | T35: 44834 | U35: =IF(AND(S35="",T35=""),"PENDIENTE",IF(AND(S35<>"",T35<>""),"PAGADO","ABONADO")) -> PAGADO
A36: =CONCATENATE(YEAR($E36),MONTH($E36)) -> 202211 | B36: SERFINANZAS | C36: INVERSIONES RUEDA S.A.S | D36: 111000149580 | E36: 44878 | F36: 13 | G36: 23 | H36: 2451460.4 | I36: 1195817.9 | J36: 0 | K36: 0 | L36: =IF(S35="",0,IF(S35<=P35,P35-S35,0)) -> 0 | M36: =0.12235329/12 -> 0.010196108 | N36: =I36/Q35 -> 0.016691832 | O36: =(N36/M36)-1 -> 0.63707882 | P36: =H36+I36+J36+K36+L36 -> 3647278.3 | Q36: 69189444 | R36: =IF(T35="",TODAY()-E35,IF(T36="",TODAY()-E36,"OK")) -> OK | S36: 3647278.3 | T36: 44855 | U36: =IF(AND(S36="",T36=""),"PENDIENTE",IF(AND(S36<>"",T36<>""),"PAGADO","ABONADO")) -> PAGADO
A37: =CONCATENATE(YEAR($E37),MONTH($E37)) -> 202212 | B37: SERFINANZAS | C37: INVERSIONES RUEDA S.A.S | D37: 111000149580 | E37: 44908 | F37: 14 | G37: 22 | H37: 2495736 | I37: 1207404.4 | J37: 0 | K37: 0 | L37: =IF(S36="",0,IF(S36<=P36,P36-S36,0)) -> 0 | M37: =0.12235329/12 -> 0.010196108 | N37: =I37/Q36 -> 0.017450703 | O37: =(N37/M37)-1 -> 0.71150634 | P37: =H37+I37+J37+K37+L37 -> 3703140.4 | Q37: 66714531 | R37: =IF(T36="",TODAY()-E36,IF(T37="",TODAY()-E37,"OK")) -> OK | S37: 3709881 | T37: 44924 | U37: =IF(AND(S37="",T37=""),"PENDIENTE",IF(AND(S37<>"",T37<>""),"PAGADO","ABONADO")) -> PAGADO
A38: =CONCATENATE(YEAR($E38),MONTH($E38)) -> 20231 | B38: SERFINANZAS | C38: INVERSIONES RUEDA S.A.S | D38: 111000149580 | E38: 44939 | F38: 15 | G38: 21 | H38: 2528586.2 | I38: 1192036.3 | J38: 0 | K38: 0 | L38: =IF(S37="",0,IF(S37<=P37,P37-S37,0)) -> 0 | M38: =0.12235329/12 -> 0.010196108 | N38: =I38/Q37 -> 0.017867716 | O38: =(N38/M38)-1 -> 0.75240565 | P38: =H38+I38+J38+K38+L38 -> 3720622.5 | Q38: 64208188 | R38: =IF(T37="",TODAY()-E37,IF(T38="",TODAY()-E38,"OK")) -> OK | S38: 6897573.5 | T38: 44949 | U38: =IF(AND(S38="",T38=""),"PENDIENTE",IF(AND(S38<>"",T38<>""),"PAGADO","ABONADO")) -> PAGADO
A39: =CONCATENATE(YEAR($E39),MONTH($E39)) -> 20232 | B39: SERFINANZAS | C39: INVERSIONES RUEDA S.A.S | D39: 111000149580 | E39: 44970 | F39: 16 | G39: 20 | H39: 2557542.1 | I39: 1188606.6 | J39: 0 | K39: 0 | L39: =IF(S38="",0,IF(S38<=P38,P38-S38,0)) -> 0 | M39: =0.12235329/12 -> 0.010196108 | N39: =I39/Q38 -> 0.018511761 | O39: =(N39/M39)-1 -> 0.81557139 | P39: =H39+I39+J39+K39+L39 -> 3746148.7 | Q39: 61670014 | R39: =IF(T38="",TODAY()-E38,IF(T39="",TODAY()-E39,"OK")) -> OK | S39: 3786171.7 | T39: 44995 | U39: =IF(AND(S39="",T39=""),"PENDIENTE",IF(AND(S39<>"",T39<>""),"PAGADO","ABONADO")) -> PAGADO
A40: =CONCATENATE(YEAR($E40),MONTH($E40)) -> 20233 | B40: SERFINANZAS | C40: INVERSIONES RUEDA S.A.S | D40: 111000149580 | E40: 44998 | F40: 17 | G40: 19 | H40: 2628824.9 | I40: 1086345 | J40: 0 | K40: 0 | L40: =IF(S39="",0,IF(S39<=P39,P39-S39,0)) -> 0 | M40: =0.12235329/12 -> 0.010196108 | N40: =I40/Q39 -> 0.017615449 | O40: =(N40/M40)-1 -> 0.72766412 | P40: =H40+I40+J40+K40+L40 -> 3715169.9 | Q40: 59099605 | R40: =IF(T39="",TODAY()-E39,IF(T40="",TODAY()-E40,"OK")) -> OK | S40: 3959097.1 | T40: 45009 | U40: =IF(AND(S40="",T40=""),"PENDIENTE",IF(AND(S40<>"",T40<>""),"PAGADO","ABONADO")) -> PAGADO
A41: =CONCATENATE(YEAR($E41),MONTH($E41)) -> 20234 | B41: SERFINANZAS | C41: INVERSIONES RUEDA S.A.S | D41: 111000149580 | E41: 45029 | F41: 18 | G41: 18 | H41: 2603053.2 | I41: =Q40*N41 -> 1055602.1 | J41: 0 | K41: 0 | L41: =IF(S40="",0,IF(S40<=P40,P40-S40,0)) -> 0 | M41: =0.12235329/12 -> 0.010196108 | N41: =AVERAGE(N37:N40) -> 0.017861407 | O41: =(N41/M41)-1 -> 0.75178688 | P41: =H41+I41+J41+K41+L41 -> 3658655.3 | Q41: 56496552 | R41: =IF(T40="",TODAY()-E40,IF(T41="",TODAY()-E41,"OK")) -> OK | S41: 3757189.7 | T41: 45045 | U41: =IF(AND(S41="",T41=""),"PENDIENTE",IF(AND(S41<>"",T41<>""),"PAGADO","ABONADO")) -> PAGADO
A42: =CONCATENATE(YEAR($E42),MONTH($E42)) -> 20235 | B42: SERFINANZAS | C42: INVERSIONES RUEDA S.A.S | D42: 111000149580 | E42: 45059 | F42: 19 | G42: 17 | H42: 2636111.9 | I42: 938856.17 | J42: 0 | K42: 0 | L42: =IF(S41="",0,IF(S41<=P41,P41-S41,0)) -> 0 | M42: =0.12235329/12 -> 0.010196108 | N42: =AVERAGE(N38:N41) -> 0.017964083 | O42: =(N42/M42)-1 -> 0.76185701 | P42: =H42+I42+J42+K42+L42 -> 3574968.1 | Q42: 53860440 | R42: =IF(T41="",TODAY()-E41,IF(T42="",TODAY()-E42,"OK")) -> OK | S42: 3743994.5 | T42: 45079 | U42: =IF(AND(S42="",T42=""),"PENDIENTE",IF(AND(S42<>"",T42<>""),"PAGADO","ABONADO")) -> PAGADO
A43: =CONCATENATE(YEAR($E43),MONTH($E43)) -> 20236 | B43: SERFINANZAS | C43: INVERSIONES RUEDA S.A.S | D43: 111000149580 | E43: 45090 | F43: 20 | G43: 16 | H43: 2669590.6 | I43: 894937.8 | J43: 0 | K43: 0 | L43: =IF(S42="",0,IF(S42<=P42,P42-S42,0)) -> 0 | M43: =0.12235329/12 -> 0.010196108 | N43: =AVERAGE(N39:N42) -> 0.017988175 | O43: =(N43/M43)-1 -> 0.76421985 | P43: =H43+I43+J43+K43+L43 -> 3564528.4 | Q43: 51190849 | R43: =IF(T42="",TODAY()-E42,IF(T43="",TODAY()-E43,"OK")) -> OK | S43: =800000+2971635.02 -> 3771635 | T43: 45119 | U43: =IF(AND(S43="",T43=""),"PENDIENTE",IF(AND(S43<>"",T43<>""),"PAGADO","ABONADO")) -> PAGADO
A44: =CONCATENATE(YEAR($E44),MONTH($E44)) -> 20237 | B44: SERFINANZAS | C44: INVERSIONES RUEDA S.A.S | D44: 111000149580 | E44: 45120 | F44: 21 | G44: 15 | H44: 2827394.7 | I44: 881432 | J44: 0 | K44: 0 | L44: =IF(S43="",0,IF(S43<=P43,P43-S43,0)) -> 0 | M44: =0.12235329/12 -> 0.010196108 | N44: =AVERAGE(N40:N43) -> 0.017857279 | O44: =(N44/M44)-1 -> 0.75138197 | P44: =H44+I44+J44+K44+L44 -> 3708826.7 | Q44: 48487355 | R44: =IF(T43="",TODAY()-E43,IF(T44="",TODAY()-E44,"OK")) -> OK | S44: 4100000 | T44: 45153 | U44: =IF(AND(S44="",T44=""),"PENDIENTE",IF(AND(S44<>"",T44<>""),"PAGADO","ABONADO")) -> PAGADO
A45: =CONCATENATE(YEAR($E45),MONTH($E45)) -> 20238 | B45: SERFINANZAS | C45: INVERSIONES RUEDA S.A.S | D45: 111000149580 | E45: 45151 | F45: 22 | G45: 14 | H45: 2737828.7 | I45: 805769.72 | J45: 0 | K45: 0 | L45: =IF(S44="",0,IF(S44<=P44,P44-S44,0)) -> 0 | M45: =0.12235329/12 -> 0.010196108 | N45: =AVERAGE(N41:N44) -> 0.017917736 | O45: =(N45/M45)-1 -> 0.75731143 | P45: =H45+I45+J45+K45+L45 -> 3543598.5 | Q45: 45749526 | R45: =IF(T44="",TODAY()-E44,IF(T45="",TODAY()-E45,"OK")) -> OK | S45: 3470503.2 | T45: 45175 | U45: =IF(AND(S45="",T45=""),"PENDIENTE",IF(AND(S45<>"",T45<>""),"PAGADO","ABONADO")) -> PAGADO
A46: =CONCATENATE(YEAR($E46),MONTH($E46)) -> 20239 | B46: SERFINANZAS | C46: INVERSIONES RUEDA S.A.S | D46: 111000149580 | E46: 45182 | F46: 23 | G46: 13 | H46: 2772599.2 | I46: 760275.2 | J46: 0 | K46: 0 | L46: =IF(S45="",0,IF(S45<=P45,P45-S45,0)) -> 73095.218 | M46: =0.12235329/12 -> 0.010196108 | N46: =AVERAGE(N42:N45) -> 0.017931818 | O46: =(N46/M46)-1 -> 0.75869256 | P46: =H46+I46+J46+K46+L46 -> 3605969.6 | Q46: 42976927 | R46: =IF(T45="",TODAY()-E45,IF(T46="",TODAY()-E46,"OK")) -> OK | S46: 3792535.5 | T46: 45212 | U46: =IF(AND(S46="",T46=""),"PENDIENTE",IF(AND(S46<>"",T46<>""),"PAGADO","ABONADO")) -> PAGADO
A47: =CONCATENATE(YEAR($E47),MONTH($E47)) -> 202310 | B47: SERFINANZAS | C47: INVERSIONES RUEDA S.A.S | D47: 111000149580 | E47: 45212 | F47: 24 | G47: 12 | H47: 2807811.2 | I47: 714233.15 | J47: 0 | K47: 0 | L47: =IF(S46="",0,IF(S46<=P46,P46-S46,0)) -> 0 | M47: =0.12235329/12 -> 0.010196108 | N47: =AVERAGE(N43:N46) -> 0.017923752 | O47: =(N47/M47)-1 -> 0.75790145 | P47: =H47+I47+J47+K47+L47 -> 3522044.3 | Q47: 40169116 | R47: =IF(T46="",TODAY()-E46,IF(T47="",TODAY()-E47,"OK")) -> OK | S47: =3700000+100000 -> 3800000 | T47: 45244 | U47: =IF(AND(S47="",T47=""),"PENDIENTE",IF(AND(S47<>"",T47<>""),"PAGADO","ABONADO")) -> PAGADO
A48: =CONCATENATE(YEAR($E48),MONTH($E48)) -> 202311 | B48: SERFINANZAS | C48: INVERSIONES RUEDA S.A.S | D48: 111000149580 | E48: 45243 | F48: 25 | G48: 11 | H48: 2843470.4 | I48: 667548.33 | J48: 0 | K48: 0 | L48: =IF(S47="",0,IF(S47<=P47,P47-S47,0)) -> 0 | M48: =0.12235329/12 -> 0.010196108 | N48: =AVERAGE(N44:N47) -> 0.017907646 | O48: =(N48/M48)-1 -> 0.75632185 | P48: =H48+I48+J48+K48+L48 -> 3511018.7 | Q48: 37325645 | R48: =IF(T47="",TODAY()-E47,IF(T48="",TODAY()-E48,"OK")) -> OK | S48: 3850000 | T48: 45274 | U48: =IF(AND(S48="",T48=""),"PENDIENTE",IF(AND(S48<>"",T48<>""),"PAGADO","ABONADO")) -> PAGADO
A49: =CONCATENATE(YEAR($E49),MONTH($E49)) -> 202312 | B49: SERFINANZAS | C49: INVERSIONES RUEDA S.A.S | D49: 111000149580 | E49: 45273 | F49: 26 | G49: 10 | H49: 3099151.6 | I49: 602611.88 | J49: 0 | K49: 1950725 | L49: =IF(S48="",0,IF(S48<=P48,P48-S48,0)) -> 0 | M49: =0.12235329/12 -> 0.010196108 | N49: =AVERAGE(N45:N48) -> 0.017920238 | O49: =(N49/M49)-1 -> 0.75755682 | P49: =H49+I49+J49+K49+L49 -> 5652488.5 | Q49: 34446063 | R49: =IF(T48="",TODAY()-E48,IF(T49="",TODAY()-E49,"OK")) -> OK | S49: 5700000 | T49: 45308 | U49: =IF(AND(S49="",T49=""),"PENDIENTE",IF(AND(S49<>"",T49<>""),"PAGADO","ABONADO")) -> PAGADO
A50: =CONCATENATE(YEAR($E50),MONTH($E50)) -> 20241 | B50: SERFINANZAS | C50: INVERSIONES RUEDA S.A.S | D50: 111000149580 | E50: 45304 | F50: 27 | G50: 9 | H50: 3162000.2 | I50: 529640.58 | J50: 0 | K50: 0 | L50: =IF(S49="",0,IF(S49<=P49,P49-S49,0)) -> 0 | M50: =0.12235329/12 -> 0.010196108 | N50: =AVERAGE(N46:N49) -> 0.017920864 | O50: =(N50/M50)-1 -> 0.75761817 | P50: =H50+I50+J50+K50+L50 -> 3691640.7 | Q50: 31529910 | R50: =IF(T49="",TODAY()-E49,IF(T50="",TODAY()-E50,"OK")) -> OK | S50: 3757981.7 | T50: 45334 | U50: =IF(AND(S50="",T50=""),"PENDIENTE",IF(AND(S50<>"",T50<>""),"PAGADO","ABONADO")) -> PAGADO
A51: =CONCATENATE(YEAR($E51),MONTH($E51)) -> 20242 | B51: SERFINANZAS | C51: INVERSIONES RUEDA S.A.S | D51: 111000149580 | E51: 45335 | F51: 28 | G51: 8 | H51: 2953188.3 | I51: 523981.47 | J51: 0 | K51: 0 | L51: =IF(S50="",0,IF(S50<=P50,P50-S50,0)) -> 0 | M51: =0.12235329/12 -> 0.010196108 | N51: =AVERAGE(N47:N50) -> 0.017918125 | O51: =(N51/M51)-1 -> 0.75734957 | P51: =H51+I51+J51+K51+L51 -> 3477169.8 | Q51: 28576721 | R51: =IF(T50="",TODAY()-E50,IF(T51="",TODAY()-E51,"OK")) -> OK | S51: 3760000 | T51: 45365 | U51: =IF(AND(S51="",T51=""),"PENDIENTE",IF(AND(S51<>"",T51<>""),"PAGADO","ABONADO")) -> PAGADO
A52: =CONCATENATE(YEAR($E52),MONTH($E52)) -> 20243 | B52: SERFINANZAS | C52: INVERSIONES RUEDA S.A.S | D52: 111000149580 | E52: 45364 | F52: 29 | G52: 7 | H52: 2990693.8 | I52: 474904.76 | J52: 0 | K52: 0 | L52: =IF(S51="",0,IF(S51<=P51,P51-S51,0)) -> 0 | M52: =0.12235329/12 -> 0.010196108 | N52: =AVERAGE(N48:N51) -> 0.017916718 | O52: =(N52/M52)-1 -> 0.7572116 | P52: =H52+I52+J52+K52+L52 -> 3465598.5 | Q52: 25586028 | R52: =IF(T51="",TODAY()-E51,IF(T52="",TODAY()-E52,"OK")) -> OK | S52: 3766609.7 | T52: 45394 | U52: =IF(AND(S52="",T52=""),"PENDIENTE",IF(AND(S52<>"",T52<>""),"PAGADO","ABONADO")) -> PAGADO
A53: =CONCATENATE(YEAR($E53),MONTH($E53)) -> 20244 | B53: SERFINANZAS | C53: INVERSIONES RUEDA S.A.S | D53: 111000149580 | E53: 45395 | F53: 30 | G53: 6 | H53: 3028675.6 | I53: 425203.99 | J53: 0 | K53: 0 | L53: =IF(S52="",0,IF(S52<=P52,P52-S52,0)) -> 0 | M53: =0.12235329/12 -> 0.010196108 | N53: =AVERAGE(N49:N52) -> 0.017918986 | O53: =(N53/M53)-1 -> 0.75743404 | P53: =H53+I53+J53+K53+L53 -> 3453879.6 | Q53: 22557352 | R53: =IF(T52="",TODAY()-E52,IF(T53="",TODAY()-E53,"OK")) -> OK | S53: 3748304.8 | T53: 45422 | U53: =IF(AND(S53="",T53=""),"PENDIENTE",IF(AND(S53<>"",T53<>""),"PAGADO","ABONADO")) -> PAGADO
A54: =CONCATENATE(YEAR($E54),MONTH($E54)) -> 20245 | B54: SERFINANZAS | C54: INVERSIONES RUEDA S.A.S | D54: 111000149580 | E54: 45425 | F54: 31 | G54: 5 | H54: 3067139.8 | I54: 374871.17 | J54: 0 | K54: 0 | L54: =IF(S53="",0,IF(S53<=P53,P53-S53,0)) -> 0 | M54: =0.12235329/12 -> 0.010196108 | N54: =AVERAGE(N50:N53) -> 0.017918673 | O54: =(N54/M54)-1 -> 0.75740335 | P54: =H54+I54+J54+K54+L54 -> 3442010.9 | Q54: 19490212 | R54: =IF(T53="",TODAY()-E53,IF(T54="",TODAY()-E54,"OK")) -> OK | S54: 3750256.5 | T54: 45454 | U54: =IF(AND(S54="",T54=""),"PENDIENTE",IF(AND(S54<>"",T54<>""),"PAGADO","ABONADO")) -> PAGADO
A55: =CONCATENATE(YEAR($E55),MONTH($E55)) -> 20246 | B55: SERFINANZAS | C55: INVERSIONES RUEDA S.A.S | D55: 111000149580 | E55: 45456 | F55: 32 | G55: 4 | H55: 3106092.4 | I55: 323899.85 | J55: 0 | K55: 0 | L55: =IF(S54="",0,IF(S54<=P54,P54-S54,0)) -> 0 | M55: =0.12235329/12 -> 0.010196108 | N55: =AVERAGE(N51:N54) -> 0.017918126 | O55: =(N55/M55)-1 -> 0.75734964 | P55: =H55+I55+J55+K55+L55 -> 3429992.3 | Q55: 16384120 | R55: =IF(T54="",TODAY()-E54,IF(T55="",TODAY()-E55,"OK")) -> OK | S55: 3688182.3 | T55: 45461 | U55: =IF(AND(S55="",T55=""),"PENDIENTE",IF(AND(S55<>"",T55<>""),"PAGADO","ABONADO")) -> PAGADO
A56: =CONCATENATE(YEAR($E56),MONTH($E56)) -> 20247 | B56: SERFINANZAS | C56: INVERSIONES RUEDA S.A.S | D56: 111000149580 | E56: 45486 | F56: 33 | G56: 3 | H56: 3145539.8 | I56: 272280.98 | J56: 0 | K56: 0 | L56: =IF(S55="",0,IF(S55<=P55,P55-S55,0)) -> 0 | M56: =0.12235329/12 -> 0.010196108 | N56: =AVERAGE(N52:N55) -> 0.017918126 | O56: =(N56/M56)-1 -> 0.75734966 | P56: =H56+I56+J56+K56+L56 -> 3417820.8 | Q56: 13238580 | R56: =IF(T55="",TODAY()-E55,IF(T56="",TODAY()-E56,"OK")) -> OK | S56: 3720293.5 | T56: 45505 | U56: =IF(AND(S56="",T56=""),"PENDIENTE",IF(AND(S56<>"",T56<>""),"PAGADO","ABONADO")) -> PAGADO
A57: =CONCATENATE(YEAR($E57),MONTH($E57)) -> 20248 | B57: SERFINANZAS | C57: INVERSIONES RUEDA S.A.S | D57: 111000149580 | E57: 45517 | F57: 34 | G57: 2 | H57: 3185488.2 | I57: 220006.49 | J57: 0 | K57: 0 | L57: =IF(S56="",0,IF(S56<=P56,P56-S56,0)) -> 0 | M57: =0.12235329/12 -> 0.010196108 | N57: =AVERAGE(N53:N56) -> 0.017918478 | O57: =(N57/M57)-1 -> 0.75738417 | P57: =H57+I57+J57+K57+L57 -> 3405494.7 | Q57: 10053092 | R57: =IF(T56="",TODAY()-E56,IF(T57="",TODAY()-E57,"OK")) -> 21 | U57: =IF(AND(S57="",T57=""),"PENDIENTE",IF(AND(S57<>"",T57<>""),"PAGADO","ABONADO")) -> PENDIENTE
A58: =CONCATENATE(YEAR($E58),MONTH($E58)) -> 20249 | B58: SERFINANZAS | C58: INVERSIONES RUEDA S.A.S | D58: 111000149580 | E58: 45548 | F58: 35 | G58: 1 | H58: 3225943.9 | I58: 167068.2 | J58: 0 | K58: 0 | L58: =IF(S57="",0,IF(S57<=P57,P57-S57,0)) -> 0 | M58: =0.12235329/12 -> 0.010196108 | N58: =AVERAGE(N54:N57) -> 0.017918351 | O58: =(N58/M58)-1 -> 0.75737171 | P58: =H58+I58+J58+K58+L58 -> 3393012.1 | Q58: 6827147.9 | R58: =IF(T57="",TODAY()-E57,IF(T58="",TODAY()-E58,"OK")) -> 21 | U58: =IF(AND(S58="",T58=""),"PENDIENTE",IF(AND(S58<>"",T58<>""),"PAGADO","ABONADO")) -> PENDIENTE
A59: =CONCATENATE(YEAR($E59),MONTH($E59)) -> 202410 | B59: SERFINANZAS | C59: INVERSIONES RUEDA S.A.S | D59: 111000149580 | E59: 45578 | F59: 36 | G59: 0 | H59: 3266913.4 | I59: 113457.56 | J59: 0 | K59: 0 | L59: =IF(S58="",0,IF(S58<=P58,P58-S58,0)) -> 0 | M59: =0.12235329/12 -> 0.010196108 | N59: =AVERAGE(N55:N58) -> 0.01791827 | O59: =(N59/M59)-1 -> 0.7573638 | P59: =H59+I59+J59+K59+L59 -> 3380370.9 | Q59: 3560234.5 | R59: =IF(T58="",TODAY()-E58,IF(T59="",TODAY()-E59,"OK")) -> -10 | U59: =IF(AND(S59="",T59=""),"PENDIENTE",IF(AND(S59<>"",T59<>""),"PAGADO","ABONADO")) -> PENDIENTE
A60: =CONCATENATE(YEAR($E60),MONTH($E60)) -> 20226 | B60: SERFINANZAS | C60: LAMAR OPTICAL S.A.S | D60: 111000176362 | E60: 44738 | F60: 1 | G60: 35 | H60: 702911.21 | I60: 470435 | J60: 0 | K60: 0 | L60: =IF(S59="",0,IF(S59<=P59,P59-S59,0)) -> 0 | M60: =0.17201626/12 -> 0.014334688 | N60: =I60/32818000 -> 0.014334664 | O60: =(N60/M60)-1 -> -1.7042141e-06 | P60: =H60+I60+J60+K60+L60 -> 1173346.2 | Q60: 32115089 | R60: OK | S60: 1180000 | T60: 44742 | U60: =IF(AND(S60="",T60=""),"PENDIENTE",IF(AND(S60<>"",T60<>""),"PAGADO","ABONADO")) -> PAGADO
A61: =CONCATENATE(YEAR($E61),MONTH($E61)) -> 20227 | B61: SERFINANZAS | C61: LAMAR OPTICAL S.A.S | D61: 111000176362 | E61: 44768 | F61: 2 | G61: 34 | H61: 708571.15 | I61: 466730.34 | J61: 0 | K61: 0 | L61: =IF(S60="",0,IF(S60<=P60,P60-S60,0)) -> 0 | M61: =0.17201626/12 -> 0.014334688 | N61: =I61/Q60 -> 0.014533055 | O61: =(N61/M61)-1 -> 0.013838201 | P61: =H61+I61+J61+K61+L61 -> 1175301.5 | Q61: 31406518 | R61: =IF(T60="",TODAY()-E60,IF(T61="",TODAY()-E61,"OK")) -> OK | S61: 1250000 | T61: 44786 | U61: =IF(AND(S61="",T61=""),"PENDIENTE",IF(AND(S61<>"",T61<>""),"PAGADO","ABONADO")) -> PAGADO
A62: =CONCATENATE(YEAR($E62),MONTH($E62)) -> 20228 | B62: SERFINANZAS | C62: LAMAR OPTICAL S.A.S | D62: 111000176362 | E62: 44799 | F62: 3 | G62: 33 | H62: 703100 | I62: 500563.23 | J62: 0 | K62: 0 | L62: =IF(S61="",0,IF(S61<=P61,P61-S61,0)) -> 0 | M62: =0.17201626/12 -> 0.014334688 | N62: =I62/Q61 -> 0.015938196 | O62: =(N62/M62)-1 -> 0.11186204 | P62: =H62+I62+J62+K62+L62 -> 1203663.2 | Q62: 30703418 | R62: =IF(T61="",TODAY()-E61,IF(T62="",TODAY()-E62,"OK")) -> OK | S62: 1143954.7 | T62: 44805 | U62: =IF(AND(S62="",T62=""),"PENDIENTE",IF(AND(S62<>"",T62<>""),"PAGADO","ABONADO")) -> PAGADO
A63: =CONCATENATE(YEAR($E63),MONTH($E63)) -> 20229 | B63: SERFINANZAS | C63: LAMAR OPTICAL S.A.S | D63: 111000176362 | E63: 44830 | F63: 4 | G63: 32 | H63: 704532.9 | I63: 513976.46 | J63: 0 | K63: 0 | L63: =IF(S62="",0,IF(S62<=P62,P62-S62,0)) -> 59708.53 | M63: =0.17201626/12 -> 0.014334688 | N63: =I63/Q62 -> 0.016740041 | O63: =(N63/M63)-1 -> 0.16779942 | P63: =H63+I63+J63+K63+L63 -> 1278217.9 | Q63: 29998885 | R63: =IF(T62="",TODAY()-E62,IF(T63="",TODAY()-E63,"OK")) -> OK | S63: 1220844.6 | T63: 44834 | U63: =IF(AND(S63="",T63=""),"PENDIENTE",IF(AND(S63<>"",T63<>""),"PAGADO","ABONADO")) -> PAGADO
A64: =CONCATENATE(YEAR($E64),MONTH($E64)) -> 202210 | B64: SERFINANZAS | C64: LAMAR OPTICAL S.A.S | D64: 111000176362 | E64: 44860 | F64: 5 | G64: 31 | H64: 712454.68 | I64: 511953.71 | J64: 0 | K64: 0 | L64: =IF(S63="",0,IF(S63<=P63,P63-S63,0)) -> 57373.3 | M64: =0.17201626/12 -> 0.014334688 | N64: =I64/Q63 -> 0.017065758 | O64: =(N64/M64)-1 -> 0.19052174 | P64: =H64+I64+J64+K64+L64 -> 1281781.7 | Q64: 29286430 | R64: =IF(T63="",TODAY()-E63,IF(T64="",TODAY()-E64,"OK")) -> OK | S64: 1237088.2 | T64: 44877 | U64: =IF(AND(S64="",T64=""),"PENDIENTE",IF(AND(S64<>"",T64<>""),"PAGADO","ABONADO")) -> PAGADO
A65: =CONCATENATE(YEAR($E65),MONTH($E65)) -> 202211 | B65: SERFINANZAS | C65: LAMAR OPTICAL S.A.S | D65: 111000176362 | E65: 44891 | F65: 6 | G65: 30 | H65: 720680.58 | I65: 509704.54 | J65: 0 | K65: 0 | L65: =IF(S64="",0,IF(S64<=P64,P64-S64,0)) -> 44693.52 | M65: =0.17201626/12 -> 0.014334688 | N65: =I65/Q64 -> 0.01740412 | O65: =(N65/M65)-1 -> 0.21412615 | P65: =H65+I65+J65+K65+L65 -> 1275078.6 | Q65: 28525383 | R65: =IF(T64="",TODAY()-E64,IF(T65="",TODAY()-E65,"OK")) -> OK | S65: 1232324.2 | T65: 44894 | U65: =IF(AND(S65="",T65=""),"PENDIENTE",IF(AND(S65<>"",T65<>""),"PAGADO","ABONADO")) -> PAGADO
A66: =CONCATENATE(YEAR($E66),MONTH($E66)) -> 202212 | B66: SERFINANZAS | C66: LAMAR OPTICAL S.A.S | D66: 111000176362 | E66: 44921 | F66: 7 | G66: 29 | H66: 723900.56 | I66: 520684.19 | J66: 0 | K66: 0 | L66: =IF(S65="",0,IF(S65<=P65,P65-S65,0)) -> 42754.4 | M66: =0.17201626/12 -> 0.014334688 | N66: =I66/Q65 -> 0.018253364 | O66: =(N66/M66)-1 -> 0.27337012 | P66: =H66+I66+J66+K66+L66 -> 1287339.2 | Q66: 27804702 | R66: =IF(T65="",TODAY()-E65,IF(T66="",TODAY()-E66,"OK")) -> OK | S66: 1263011.6 | T66: 44946 | U66: =IF(AND(S66="",T66=""),"PENDIENTE",IF(AND(S66<>"",T66<>""),"PAGADO","ABONADO")) -> PAGADO
A67: =CONCATENATE(YEAR($E67),MONTH($E67)) -> 20231 | B67: SERFINANZAS | C67: LAMAR OPTICAL S.A.S | D67: 111000176362 | E67: 44952 | F67: 8 | G67: 28 | H67: 728789.74 | I67: 528516.1 | J67: 0 | K67: 0 | L67: =IF(S66="",0,IF(S66<=P66,P66-S66,0)) -> 24327.55 | M67: =0.17201626/12 -> 0.014334688 | N67: =I67/Q66 -> 0.019008155 | O67: =(N67/M67)-1 -> 0.32602502 | P67: =H67+I67+J67+K67+L67 -> 1281633.4 | Q67: 27012441 | R67: =IF(T66="",TODAY()-E66,IF(T67="",TODAY()-E67,"OK")) -> OK | S67: 1259486.2 | T67: 44952 | U67: =IF(AND(S67="",T67=""),"PENDIENTE",IF(AND(S67<>"",T67<>""),"PAGADO","ABONADO")) -> PAGADO
A68: =CONCATENATE(YEAR($E68),MONTH($E68)) -> 20232 | B68: SERFINANZAS | C68: LAMAR OPTICAL S.A.S | D68: 111000176362 | E68: 44983 | F68: 9 | G68: 27 | H68: 741317.37 | I68: 517986.45 | J68: 0 | K68: 0 | L68: =IF(S67="",0,IF(S67<=P67,P67-S67,0)) -> 22147.15 | M68: =0.17201626/12 -> 0.014334688 | N68: =I68/Q67 -> 0.019175847 | O68: =(N68/M68)-1 -> 0.33772336 | P68: =H68+I68+J68+K68+L68 -> 1281451 | Q68: 26216267 | R68: =IF(T67="",TODAY()-E67,IF(T68="",TODAY()-E68,"OK")) -> OK | S68: 1278767.6 | T68: 45008 | U68: =IF(AND(S68="",T68=""),"PENDIENTE",IF(AND(S68<>"",T68<>""),"PAGADO","ABONADO")) -> PAGADO
A69: =CONCATENATE(YEAR($E69),MONTH($E69)) -> 20233 | B69: SERFINANZAS | C69: LAMAR OPTICAL S.A.S | D69: 111000176362 | E69: 45011 | F69: 10 | G69: 26 | H69: 752227.12 | I69: 512019.4 | J69: 0 | K69: 0 | L69: =IF(S68="",0,IF(S68<=P68,P68-S68,0)) -> 2683.37 | M69: =0.17201626/12 -> 0.014334688 | N69: =I69/Q68 -> 0.019530599 | O69: =(N69/M69)-1 -> 0.36247111 | P69: =H69+I69+J69+K69+L69 -> 1266929.9 | Q69: 25408133 | R69: =IF(T68="",TODAY()-E68,IF(T69="",TODAY()-E69,"OK")) -> OK | S69: 1278536.1 | T69: 45029 | U69: =IF(AND(S69="",T69=""),"PENDIENTE",IF(AND(S69<>"",T69<>""),"PAGADO","ABONADO")) -> PAGADO
A70: =CONCATENATE(YEAR($E70),MONTH($E70)) -> 20234 | B70: SERFINANZAS | C70: LAMAR OPTICAL S.A.S | D70: 111000176362 | E70: 45042 | F70: 11 | G70: 25 | H70: 774748.76 | I70: 477633.97 | J70: 0 | K70: 0 | L70: =IF(S69="",0,IF(S69<=P69,P69-S69,0)) -> 0 | M70: =0.17201626/12 -> 0.014334688 | N70: =I70/Q69 -> 0.018798468 | O70: =(N70/M70)-1 -> 0.31139704 | P70: =H70+I70+J70+K70+L70 -> 1252382.7 | Q70: 24587398 | R70: =IF(T69="",TODAY()-E69,IF(T70="",TODAY()-E70,"OK")) -> OK | S70: 1274157.3 | T70: 45066 | U70: =IF(AND(S70="",T70=""),"PENDIENTE",IF(AND(S70<>"",T70<>""),"PAGADO","ABONADO")) -> PAGADO
A71: =CONCATENATE(YEAR($E71),MONTH($E71)) -> 20235 | B71: SERFINANZAS | C71: LAMAR OPTICAL S.A.S | D71: 111000176362 | E71: 45072 | F71: 12 | G71: 24 | H71: 795099.67 | I71: 448612.53 | J71: 0 | K71: 0 | L71: =IF(S70="",0,IF(S70<=P70,P70-S70,0)) -> 0 | M71: =0.17201626/12 -> 0.014334688 | N71: =I71/Q70 -> 0.018245629 | O71: =(N71/M71)-1 -> 0.27283052 | P71: =H71+I71+J71+K71+L71 -> 1243712.2 | Q71: 23754208 | R71: =IF(T70="",TODAY()-E70,IF(T71="",TODAY()-E71,"OK")) -> OK | S71: 1255078.5 | T71: 45086 | U71: =IF(AND(S71="",T71=""),"PENDIENTE",IF(AND(S71<>"",T71<>""),"PAGADO","ABONADO")) -> PAGADO
A72: =CONCATENATE(YEAR($E72),MONTH($E72)) -> 20236 | B72: SERFINANZAS | C72: LAMAR OPTICAL S.A.S | D72: 111000176362 | E72: 45103 | F72: 13 | G72: 23 | H72: 819782.4 | I72: 430112.25 | J72: 0 | K72: 0 | L72: =IF(S71="",0,IF(S71<=P71,P71-S71,0)) -> 0 | M72: =0.17201626/12 -> 0.014334688 | N72: =I72/Q71 -> 0.018106781 | O72: =(N72/M72)-1 -> 0.26314439 | P72: =H72+I72+J72+K72+L72 -> 1249894.6 | Q72: 22910462 | R72: =IF(T71="",TODAY()-E71,IF(T72="",TODAY()-E72,"OK")) -> OK | S72: =1268288.18 -> 1268288.2 | T72: 45133 | U72: =IF(AND(S72="",T72=""),"PENDIENTE",IF(AND(S72<>"",T72<>""),"PAGADO","ABONADO")) -> PAGADO
A73: =CONCATENATE(YEAR($E73),MONTH($E73)) -> 20237 | B73: SERFINANZAS | C73: LAMAR OPTICAL S.A.S | D73: 111000176362 | E73: 45133 | F73: 14 | G73: 22 | H73: 856135.82 | I73: 440556.78 | J73: 0 | K73: 0 | L73: =IF(S72="",0,IF(S72<=P72,P72-S72,0)) -> 0 | M73: =0.17201626/12 -> 0.014334688 | N73: =I73/Q72 -> 0.019229502 | O73: =(N73/M73)-1 -> 0.34146638 | P73: =H73+I73+J73+K73+L73 -> 1296692.6 | Q73: 22054326 | R73: =IF(T72="",TODAY()-E72,IF(T73="",TODAY()-E73,"OK")) -> OK | S73: 1275213.1 | T73: 45163 | U73: =IF(AND(S73="",T73=""),"PENDIENTE",IF(AND(S73<>"",T73<>""),"PAGADO","ABONADO")) -> PAGADO
A74: =CONCATENATE(YEAR($E74),MONTH($E74)) -> 20238 | B74: SERFINANZAS | C74: LAMAR OPTICAL S.A.S | D74: 111000176362 | E74: 45164 | F74: 15 | G74: 21 | H74: 831827.72 | I74: 422561.68 | J74: 0 | K74: 1167828 | L74: =IF(S73="",0,IF(S73<=P73,P73-S73,0)) -> 21479.475 | M74: =0.17201626/12 -> 0.014334688 | N74: =I74/Q73 -> 0.019160036 | O74: =(N74/M74)-1 -> 0.33662034 | P74: =H74+I74+J74+K74+L74 -> 2443696.9 | Q74: 21185792 | R74: =IF(T73="",TODAY()-E73,IF(T74="",TODAY()-E74,"OK")) -> OK | S74: 2444104.6 | T74: 45191 | U74: =IF(AND(S74="",T74=""),"PENDIENTE",IF(AND(S74<>"",T74<>""),"PAGADO","ABONADO")) -> PAGADO
A75: =CONCATENATE(YEAR($E75),MONTH($E75)) -> 20239 | B75: SERFINANZAS | C75: LAMAR OPTICAL S.A.S | D75: 111000176362 | E75: 45195 | F75: 16 | G75: 20 | H75: 845399.43 | I75: 412005.05 | J75: 0 | K75: 0 | L75: =IF(S74="",0,IF(S74<=P74,P74-S74,0)) -> 0 | M75: =0.17201626/12 -> 0.014334688 | N75: =I75/Q74 -> 0.019447234 | O75: =(N75/M75)-1 -> 0.35665552 | P75: =H75+I75+J75+K75+L75 -> 1257404.5 | Q75: 20304888 | R75: =IF(T74="",TODAY()-E74,IF(T75="",TODAY()-E75,"OK")) -> OK | S75: 1281127.5 | T75: 45225 | U75: =IF(AND(S75="",T75=""),"PENDIENTE",IF(AND(S75<>"",T75<>""),"PAGADO","ABONADO")) -> PAGADO
A76: =CONCATENATE(YEAR($E76),MONTH($E76)) -> 202310 | B76: SERFINANZAS | C76: LAMAR OPTICAL S.A.S | D76: 111000176362 | E76: 45225 | F76: 17 | G76: 19 | H76: 893280.77 | I76: 389840.09 | J76: 0 | K76: 0 | L76: =IF(S75="",0,IF(S75<=P75,P75-S75,0)) -> 0 | M76: =0.17201626/12 -> 0.014334688 | N76: =I76/Q75 -> 0.019199322 | O76: =(N76/M76)-1 -> 0.339361 | P76: =H76+I76+J76+K76+L76 -> 1283120.9 | Q76: 19411607 | R76: =IF(T75="",TODAY()-E75,IF(T76="",TODAY()-E76,"OK")) -> OK | S76: 1350000 | T76: 45257 | U76: =IF(AND(S76="",T76=""),"PENDIENTE",IF(AND(S76<>"",T76<>""),"PAGADO","ABONADO")) -> PAGADO
A77: =CONCATENATE(YEAR($E77),MONTH($E77)) -> 202311 | B77: SERFINANZAS | C77: LAMAR OPTICAL S.A.S | D77: 111000176362 | E77: 45256 | F77: 18 | G77: 18 | H77: 906099.53 | I77: 372595.32 | J77: 0 | K77: 0 | L77: =IF(S76="",0,IF(S76<=P76,P76-S76,0)) -> 0 | M77: =0.17201626/12 -> 0.014334688 | N77: =I77/Q76 -> 0.01919446 | O77: =(N77/M77)-1 -> 0.3390218 | P77: =H77+I77+J77+K77+L77 -> 1278694.8 | Q77: 18505507 | R77: =IF(T76="",TODAY()-E76,IF(T77="",TODAY()-E77,"OK")) -> OK | S77: 1251000 | T77: 45286 | U77: =IF(AND(S77="",T77=""),"PENDIENTE",IF(AND(S77<>"",T77<>""),"PAGADO","ABONADO")) -> PAGADO
A78: =CONCATENATE(YEAR($E78),MONTH($E78)) -> 202312 | B78: SERFINANZAS | C78: LAMAR OPTICAL S.A.S | D78: 111000176362 | E78: 45286 | F78: 19 | G78: 17 | H78: 919037.41 | I78: 355041.11 | J78: 0 | K78: 0 | L78: =IF(S77="",0,IF(S77<=P77,P77-S77,0)) -> 27694.85 | M78: =0.17201626/12 -> 0.014334688 | N78: =I78/Q77 -> 0.0191857 | O78: =(N78/M78)-1 -> 0.33841066 | P78: =H78+I78+J78+K78+L78 -> 1301773.4 | Q78: 17586470 | R78: =IF(T77="",TODAY()-E77,IF(T78="",TODAY()-E78,"OK")) -> OK | S78: 1219399.2 | T78: 45316 | U78: =IF(AND(S78="",T78=""),"PENDIENTE",IF(AND(S78<>"",T78<>""),"PAGADO","ABONADO")) -> PAGADO
A79: =CONCATENATE(YEAR($E79),MONTH($E79)) -> 20241 | B79: SERFINANZAS | C79: LAMAR OPTICAL S.A.S | D79: 111000176362 | E79: 45317 | F79: 20 | G79: 16 | H79: 917026.04 | I79: 331045 | J79: 0 | K79: 0 | L79: =IF(S78="",0,IF(S78<=P78,P78-S78,0)) -> 82374.181 | M79: =0.17201626/12 -> 0.014334688 | N79: =I79/Q78 -> 0.018823846 | O79: =(N79/M79)-1 -> 0.31316743 | P79: =H79+I79+J79+K79+L79 -> 1330445.2 | Q79: 16654351 | R79: =IF(T78="",TODAY()-E78,IF(T79="",TODAY()-E79,"OK")) -> OK | S79: 1271634.2 | T79: 45346 | U79: =IF(AND(S79="",T79=""),"PENDIENTE",IF(AND(S79<>"",T79<>""),"PAGADO","ABONADO")) -> PAGADO
A80: =CONCATENATE(YEAR($E80),MONTH($E80)) -> 20242 | B80: SERFINANZAS | C80: LAMAR OPTICAL S.A.S | D80: 111000176362 | E80: 45348 | F80: 21 | G80: 15 | H80: 939268.05 | I80: 301315.97 | J80: 0 | K80: 0 | L80: =IF(S79="",0,IF(S79<=P79,P79-S79,0)) -> 58810.971 | M80: =0.17201626/12 -> 0.014334688 | N80: =AVERAGE(N76:N79) -> 0.019100832 | O80: =(N80/M80)-1 -> 0.33249022 | P80: =H80+I80+J80+K80+L80 -> 1299395 | Q80: 15708970 | R80: =IF(T79="",TODAY()-E79,IF(T80="",TODAY()-E80,"OK")) -> OK | S80: 1265000 | T80: 45378 | U80: =IF(AND(S80="",T80=""),"PENDIENTE",IF(AND(S80<>"",T80<>""),"PAGADO","ABONADO")) -> PAGADO
A81: =CONCATENATE(YEAR($E81),MONTH($E81)) -> 20243 | B81: SERFINANZAS | C81: LAMAR OPTICAL S.A.S | D81: 111000176362 | E81: 45377 | F81: 22 | G81: 14 | H81: 958873.71 | I81: =Q80*N81 -> 299667.59 | J81: 0 | K81: 0 | L81: =IF(S80="",0,IF(S80<=P80,P80-S80,0)) -> 34394.991 | M81: =0.17201626/12 -> 0.014334688 | N81: =AVERAGE(N77:N80) -> 0.019076209 | O81: =(N81/M81)-1 -> 0.33077253 | P81: =H81+I81+J81+K81+L81 -> 1292936.3 | Q81: 14750096 | R81: =IF(T80="",TODAY()-E80,IF(T81="",TODAY()-E81,"OK")) -> OK | S81: 1257801.4 | T81: 45407 | U81: =IF(AND(S81="",T81=""),"PENDIENTE",IF(AND(S81<>"",T81<>""),"PAGADO","ABONADO")) -> PAGADO
A82: =CONCATENATE(YEAR($E82),MONTH($E82)) -> 20244 | B82: SERFINANZAS | C82: LAMAR OPTICAL S.A.S | D82: 111000176362 | E82: 45408 | F82: 23 | G82: 13 | H82: 972540.9 | I82: =Q81*N82 -> 280939.86 | J82: 0 | K82: 0 | L82: =IF(S81="",0,IF(S81<=P81,P81-S81,0)) -> 35134.864 | M82: =0.17201626/12 -> 0.014334688 | N82: =AVERAGE(N78:N81) -> 0.019046647 | O82: =(N82/M82)-1 -> 0.32871021 | P82: =H82+I82+J82+K82+L82 -> 1288615.6 | Q82: 13777555 | R82: =IF(T81="",TODAY()-E81,IF(T82="",TODAY()-E82,"OK")) -> OK | S82: 1400000 | T82: 45439 | U82: =IF(AND(S82="",T82=""),"PENDIENTE",IF(AND(S82<>"",T82<>""),"PAGADO","ABONADO")) -> PAGADO
A83: =CONCATENATE(YEAR($E83),MONTH($E83)) -> 20245 | B83: SERFINANZAS | C83: LAMAR OPTICAL S.A.S | D83: 111000176362 | E83: 45438 | F83: 24 | G83: 12 | H83: 986396.67 | I83: =Q82*N83 -> 261937.27 | J83: 0 | K83: 0 | L83: =IF(S82="",0,IF(S82<=P82,P82-S82,0)) -> 0 | M83: =0.17201626/12 -> 0.014334688 | N83: =AVERAGE(N79:N82) -> 0.019011883 | O83: =(N83/M83)-1 -> 0.3262851 | P83: =H83+I83+J83+K83+L83 -> 1248333.9 | Q83: 12791158 | R83: =IF(T82="",TODAY()-E82,IF(T83="",TODAY()-E83,"OK")) -> OK | S83: 1106711 | T83: 45456 | U83: =IF(AND(S83="",T83=""),"PENDIENTE",IF(AND(S83<>"",T83<>""),"PAGADO","ABONADO")) -> PAGADO
A84: =CONCATENATE(YEAR($E84),MONTH($E84)) -> 20246 | B84: SERFINANZAS | C84: LAMAR OPTICAL S.A.S | D84: 111000176362 | E84: 45469 | F84: 25 | G84: 11 | H84: 1000453.1 | I84: =Q83*N84 -> 243785.31 | J84: 0 | K84: 0 | L84: =IF(S83="",0,IF(S83<=P83,P83-S83,0)) -> 141622.94 | M84: =0.17201626/12 -> 0.014334688 | N84: =AVERAGE(N80:N83) -> 0.019058893 | O84: =(N84/M84)-1 -> 0.32956451 | P84: =H84+I84+J84+K84+L84 -> 1385861.4 | Q84: 11790705 | R84: =IF(T83="",TODAY()-E83,IF(T84="",TODAY()-E84,"OK")) -> OK | S84: 1233974.9 | T84: 45471 | U84: =IF(AND(S84="",T84=""),"PENDIENTE",IF(AND(S84<>"",T84<>""),"PAGADO","ABONADO")) -> PAGADO
A85: =CONCATENATE(YEAR($E85),MONTH($E85)) -> 20247 | B85: SERFINANZAS | C85: LAMAR OPTICAL S.A.S | D85: 111000176362 | E85: 45499 | F85: 26 | G85: 10 | H85: 1014714.9 | I85: =Q84*N85 -> 224594.16 | J85: 0 | K85: 0 | L85: =IF(S84="",0,IF(S84<=P84,P84-S84,0)) -> 151886.52 | M85: =0.17201626/12 -> 0.014334688 | N85: =AVERAGE(N81:N84) -> 0.019048408 | O85: =(N85/M85)-1 -> 0.32883309 | P85: =H85+I85+J85+K85+L85 -> 1391195.6 | Q85: 10775990 | R85: =IF(T84="",TODAY()-E84,IF(T85="",TODAY()-E85,"OK")) -> OK | S85: 1916707.6 | T85: 45514 | U85: =IF(AND(S85="",T85=""),"PENDIENTE",IF(AND(S85<>"",T85<>""),"PAGADO","ABONADO")) -> PAGADO
A86: =CONCATENATE(YEAR($E86),MONTH($E86)) -> 20248 | B86: SERFINANZAS | C86: LAMAR OPTICAL S.A.S | D86: 111000176362 | E86: 45530 | F86: 27 | G86: 9 | H86: 1029176.1 | I86: =Q85*N86 -> 205190.56 | J86: 0 | K86: 0 | L86: =IF(S85="",0,IF(S85<=P85,P85-S85,0)) -> 0 | M86: =0.17201626/12 -> 0.014334688 | N86: =AVERAGE(N82:N85) -> 0.019041458 | O86: =(N86/M86)-1 -> 0.32834823 | P86: =H86+I86+J86+K86+L86 -> 1234366.7 | Q86: 9746814 | R86: =IF(T85="",TODAY()-E85,IF(T86="",TODAY()-E86,"OK")) -> 8 | U86: =IF(AND(S86="",T86=""),"PENDIENTE",IF(AND(S86<>"",T86<>""),"PAGADO","ABONADO")) -> PENDIENTE
A87: =CONCATENATE(YEAR($E87),MONTH($E87)) -> 20249 | B87: SERFINANZAS | C87: LAMAR OPTICAL S.A.S | D87: 111000176362 | E87: 45561 | F87: 28 | G87: 8 | H87: 1043843 | I87: =Q86*N87 -> 185580.9 | J87: 0 | K87: 0 | L87: =IF(S86="",0,IF(S86<=P86,P86-S86,0)) -> 0 | M87: =0.17201626/12 -> 0.014334688 | N87: =AVERAGE(N83:N86) -> 0.019040161 | O87: =(N87/M87)-1 -> 0.32825773 | P87: =H87+I87+J87+K87+L87 -> 1229424 | Q87: 8702971 | R87: =IF(T86="",TODAY()-E86,IF(T87="",TODAY()-E87,"OK")) -> 8 | U87: =IF(AND(S87="",T87=""),"PENDIENTE",IF(AND(S87<>"",T87<>""),"PAGADO","ABONADO")) -> PENDIENTE
A88: =CONCATENATE(YEAR($E88),MONTH($E88)) -> 202410 | B88: SERFINANZAS | C88: LAMAR OPTICAL S.A.S | D88: 111000176362 | E88: 45591 | F88: 29 | G88: 7 | H88: 1058720 | I88: =Q87*N88 -> 165767.49 | J88: 0 | K88: 0 | L88: =IF(S87="",0,IF(S87<=P87,P87-S87,0)) -> 0 | M88: =0.17201626/12 -> 0.014334688 | N88: =AVERAGE(N84:N87) -> 0.01904723 | O88: =(N88/M88)-1 -> 0.32875089 | P88: =H88+I88+J88+K88+L88 -> 1224487.5 | Q88: 7644251 | R88: =IF(T87="",TODAY()-E87,IF(T88="",TODAY()-E88,"OK")) -> -23 | U88: =IF(AND(S88="",T88=""),"PENDIENTE",IF(AND(S88<>"",T88<>""),"PAGADO","ABONADO")) -> PENDIENTE
A89: =CONCATENATE(YEAR($E89),MONTH($E89)) -> 202411 | B89: SERFINANZAS | C89: LAMAR OPTICAL S.A.S | D89: 111000176362 | E89: 45622 | F89: 30 | G89: 6 | H89: 1073809.3 | I89: =Q88*N89 -> 145579.52 | J89: 0 | K89: 0 | L89: =IF(S88="",0,IF(S88<=P88,P88-S88,0)) -> 0 | M89: =0.17201626/12 -> 0.014334688 | N89: =AVERAGE(N85:N88) -> 0.019044314 | O89: =(N89/M89)-1 -> 0.32854748 | P89: =H89+I89+J89+K89+L89 -> 1219388.9 | Q89: 6570441.7 | R89: =IF(T88="",TODAY()-E88,IF(T89="",TODAY()-E89,"OK")) -> -53 | U89: =IF(AND(S89="",T89=""),"PENDIENTE",IF(AND(S89<>"",T89<>""),"PAGADO","ABONADO")) -> PENDIENTE
A90: =CONCATENATE(YEAR($E90),MONTH($E90)) -> 202412 | B90: SERFINANZAS | C90: LAMAR OPTICAL S.A.S | D90: 111000176362 | E90: 45652 | F90: 31 | G90: 5 | H90: 1089113.1 | I90: =Q89*N90 -> 125122.83 | J90: 0 | K90: 0 | L90: =IF(S89="",0,IF(S89<=P89,P89-S89,0)) -> 0 | M90: =0.17201626/12 -> 0.014334688 | N90: =AVERAGE(N86:N89) -> 0.019043291 | O90: =(N90/M90)-1 -> 0.32847608 | P90: =H90+I90+J90+K90+L90 -> 1214235.9 | Q90: 5481328.6 | R90: =IF(T89="",TODAY()-E89,IF(T90="",TODAY()-E90,"OK")) -> -84 | U90: =IF(AND(S90="",T90=""),"PENDIENTE",IF(AND(S90<>"",T90<>""),"PAGADO","ABONADO")) -> PENDIENTE
A91: =CONCATENATE(YEAR($E91),MONTH($E91)) -> 20251 | B91: SERFINANZAS | C91: LAMAR OPTICAL S.A.S | D91: 111000176362 | E91: 45683 | F91: 32 | G91: 4 | H91: 1104634.9 | I91: =Q90*N91 -> 104385.05 | J91: 0 | K91: 0 | L91: =IF(S90="",0,IF(S90<=P90,P90-S90,0)) -> 0 | M91: =0.17201626/12 -> 0.014334688 | N91: =AVERAGE(N87:N90) -> 0.019043749 | O91: =(N91/M91)-1 -> 0.32850805 | P91: =H91+I91+J91+K91+L91 -> 1209020 | Q91: 4376693.7 | R91: =IF(T90="",TODAY()-E90,IF(T91="",TODAY()-E91,"OK")) -> -114 | U91: =IF(AND(S91="",T91=""),"PENDIENTE",IF(AND(S91<>"",T91<>""),"PAGADO","ABONADO")) -> PENDIENTE
A92: =CONCATENATE(YEAR($E92),MONTH($E92)) -> 20252 | B92: SERFINANZAS | C92: LAMAR OPTICAL S.A.S | D92: 111000176362 | E92: 45714 | F92: 33 | G92: 3 | H92: 1120378.3 | I92: =Q91*N92 -> 83352.581 | J92: 0 | K92: 0 | L92: =IF(S91="",0,IF(S91<=P91,P91-S91,0)) -> 0 | M92: =0.17201626/12 -> 0.014334688 | N92: =AVERAGE(N88:N91) -> 0.019044646 | O92: =(N92/M92)-1 -> 0.32857063 | P92: =H92+I92+J92+K92+L92 -> 1203730.8 | Q92: 3256315.4 | R92: =IF(T91="",TODAY()-E91,IF(T92="",TODAY()-E92,"OK")) -> -145 | U92: =IF(AND(S92="",T92=""),"PENDIENTE",IF(AND(S92<>"",T92<>""),"PAGADO","ABONADO")) -> PENDIENTE
A93: =CONCATENATE(YEAR($E93),MONTH($E93)) -> 20253 | B93: SERFINANZAS | C93: LAMAR OPTICAL S.A.S | D93: 111000176362 | E93: 45742 | F93: 34 | G93: 2 | H93: 1136345.9 | I93: =Q92*N93 -> 62013.27 | J93: 0 | K93: 0 | L93: =IF(S92="",0,IF(S92<=P92,P92-S92,0)) -> 0 | M93: =0.17201626/12 -> 0.014334688 | N93: =AVERAGE(N89:N92) -> 0.019044 | O93: =(N93/M93)-1 -> 0.32852556 | P93: =H93+I93+J93+K93+L93 -> 1198359.2 | Q93: 2119969.5 | R93: =IF(T92="",TODAY()-E92,IF(T93="",TODAY()-E93,"OK")) -> -176 | U93: =IF(AND(S93="",T93=""),"PENDIENTE",IF(AND(S93<>"",T93<>""),"PAGADO","ABONADO")) -> PENDIENTE
A94: =CONCATENATE(YEAR($E94),MONTH($E94)) -> 20254 | B94: SERFINANZAS | C94: LAMAR OPTICAL S.A.S | D94: 111000176362 | E94: 45773 | F94: 35 | G94: 1 | H94: 1152541.1 | I94: =Q93*N94 -> 40372.532 | J94: 0 | K94: 0 | L94: =IF(S93="",0,IF(S93<=P93,P93-S93,0)) -> 0 | M94: =0.17201626/12 -> 0.014334688 | N94: =AVERAGE(N90:N93) -> 0.019043921 | O94: =(N94/M94)-1 -> 0.32852008 | P94: =H94+I94+J94+K94+L94 -> 1192913.6 | Q94: 967428.42 | R94: =IF(T93="",TODAY()-E93,IF(T94="",TODAY()-E94,"OK")) -> -204 | U94: =IF(AND(S94="",T94=""),"PENDIENTE",IF(AND(S94<>"",T94<>""),"PAGADO","ABONADO")) -> PENDIENTE
A95: =CONCATENATE(YEAR($E95),MONTH($E95)) -> 20255 | B95: SERFINANZAS | C95: LAMAR OPTICAL S.A.S | D95: 111000176362 | E95: 45803 | F95: 36 | G95: 0 | H95: 880996.56 | I95: =Q94*N95 -> 18423.783 | J95: 0 | K95: 0 | L95: =IF(S94="",0,IF(S94<=P94,P94-S94,0)) -> 0 | M95: =0.17201626/12 -> 0.014334688 | N95: =AVERAGE(N91:N94) -> 0.019044079 | O95: =(N95/M95)-1 -> 0.32853108 | P95: =H95+I95+J95+K95+L95 -> 899420.34 | Q95: 86431.864 | R95: =IF(T94="",TODAY()-E94,IF(T95="",TODAY()-E95,"OK")) -> -235 | U95: =IF(AND(S95="",T95=""),"PENDIENTE",IF(AND(S95<>"",T95<>""),"PAGADO","ABONADO")) -> PENDIENTE
A96: =CONCATENATE(YEAR($E96),MONTH($E96)) -> 20226 | B96: SERFINANZAS | C96: INVERSIONES RUEDA S.A.S | D96: 111000176344 | E96: 44738 | F96: 1 | G96: 35 | H96: 351434.18 | I96: 235203.57 | J96: 0 | K96: 0 | L96: =IF(S95="",0,IF(S95<=P95,P95-S95,0)) -> 0 | M96: =0.17201626/12 -> 0.014334688 | N96: =I96/16408000 -> 0.014334689 | O96: =(N96/M96)-1 -> 1.6269595e-08 | P96: =H96+I96+J96+K96+L96 -> 586637.75 | Q96: 16056566 | R96: OK | S96: 590000 | T96: 44742 | U96: =IF(AND(S96="",T96=""),"PENDIENTE",IF(AND(S96<>"",T96<>""),"PAGADO","ABONADO")) -> PAGADO
A97: =CONCATENATE(YEAR($E97),MONTH($E97)) -> 20227 | B97: SERFINANZAS | C97: INVERSIONES RUEDA S.A.S | D97: 111000176344 | E97: 44768 | F97: 2 | G97: 34 | H97: 354263.98 | I97: 233314.99 | J97: 0 | K97: 0 | L97: =IF(S96="",0,IF(S96<=P96,P96-S96,0)) -> 0 | M97: =0.17201626/12 -> 0.014334688 | N97: =I97/Q96 -> 0.014530815 | O97: =(N97/M97)-1 -> 0.013681973 | P97: =H97+I97+J97+K97+L97 -> 587578.97 | Q97: =Q96-H97 -> 15702302 | R97: =IF(T96="",TODAY()-E96,IF(T97="",TODAY()-E97,"OK")) -> OK | S97: 610000 | T97: 44786 | U97: =IF(AND(S97="",T97=""),"PENDIENTE",IF(AND(S97<>"",T97<>""),"PAGADO","ABONADO")) -> PAGADO
A98: =CONCATENATE(YEAR($E98),MONTH($E98)) -> 20228 | B98: SERFINANZAS | C98: INVERSIONES RUEDA S.A.S | D98: 111000176344 | E98: 44799 | F98: 3 | G98: 33 | H98: 351528.74 | I98: 250266.36 | J98: 0 | K98: 0 | L98: =IF(S97="",0,IF(S97<=P97,P97-S97,0)) -> 0 | M98: =0.17201626/12 -> 0.014334688 | N98: =I98/Q97 -> 0.015938196 | O98: =(N98/M98)-1 -> 0.11186203 | P98: =H98+I98+J98+K98+L98 -> 601795.1 | Q98: =Q97-H98 -> 15350773 | R98: =IF(T97="",TODAY()-E97,IF(T98="",TODAY()-E98,"OK")) -> OK | S98: 586868.44 | T98: 44805 | U98: =IF(AND(S98="",T98=""),"PENDIENTE",IF(AND(S98<>"",T98<>""),"PAGADO","ABONADO")) -> PAGADO
A99: =CONCATENATE(YEAR($E99),MONTH($E99)) -> 20229 | B99: SERFINANZAS | C99: INVERSIONES RUEDA S.A.S | D99: 111000176344 | E99: 44830 | F99: 4 | G99: 32 | H99: 352244.98 | I99: 256972.57 | J99: 0 | K99: 0 | L99: =IF(S98="",0,IF(S98<=P98,P98-S98,0)) -> 14926.66 | M99: =0.17201626/12 -> 0.014334688 | N99: =I99/Q98 -> 0.016740041 | O99: =(N99/M99)-1 -> 0.16779943 | P99: =H99+I99+J99+K99+L99 -> 624144.21 | Q99: =Q98-H99 -> 14998528 | R99: =IF(T98="",TODAY()-E98,IF(T99="",TODAY()-E99,"OK")) -> OK | S99: 613392.42 | T99: 44842 | U99: =IF(AND(S99="",T99=""),"PENDIENTE",IF(AND(S99<>"",T99<>""),"PAGADO","ABONADO")) -> PAGADO
A100: =CONCATENATE(YEAR($E100),MONTH($E100)) -> 202210 | B100: SERFINANZAS | C100: INVERSIONES RUEDA S.A.S | D100: 111000176344 | E100: 44860 | F100: 5 | G100: 31 | H100: 356205.62 | I100: 255961.26 | J100: 0 | K100: 0 | L100: =IF(S99="",0,IF(S99<=P99,P99-S99,0)) -> 10751.79 | M100: =0.17201626/12 -> 0.014334688 | N100: =I100/Q99 -> 0.017065759 | O100: =(N100/M100)-1 -> 0.19052177 | P100: =H100+I100+J100+K100+L100 -> 622918.67 | Q100: =Q99-H100 -> 14642322 | R100: =IF(T99="",TODAY()-E99,IF(T100="",TODAY()-E100,"OK")) -> OK | S100: 700000 | T100: 44853 | U100: =IF(AND(S100="",T100=""),"PENDIENTE",IF(AND(S100<>"",T100<>""),"PAGADO","ABONADO")) -> PAGADO
...
